[
  {
    "frame": 0,
    "timestep": 1,
    "time": 0.0,
    "ee_pos_m": [
      -0.008020497858524323,
      0.1424264907836914,
      -0.0015417147660627961
    ],
    "ee_normal": [
      0.0,
      0.9999990463256836,
      0.0
    ],
    "knife": {
      "y_anim": 0.09864659607410431,
      "z_offset": 0.0009587852982804179
    },
    "relative_eef_force": 0.0,
    "force_world_N": {
      "x": 0.0,
      "y": 0.0,
      "z": 0.0,
      "norm": 9.999999974752427e-07
    },
    "force_normalized": {
      "x": 0.0,
      "y": 0.0,
      "z": 0.0
    },
    "scales": {
      "dx": 0.004166666883975267,
      "dt": 8.213426389724273e-06,
      "E": 6500000.0,
      "vcap_dx_over_dt": 507.29947360192307
    },
    "telemetry": {
      "material": {
        "E_Pa": 6500000.0,
        "sigma_y_Pa": 300000.0,
        "E_ref_Pa": 300000.0,
        "sigma_ref_Pa": 5000.0
      },
      "knife_resistance": {
        "k2_base_per_s": 0.0,
        "k2_eff_per_s": 0.0,
        "mat_gain": 279.28480087537883,
        "c_hat": 0.0,
        "c_hat_current": 0.0
      }
    }
  },
  {
    "frame": 1,
    "timestep": 2031,
    "time": 0.016666666666666666,
    "ee_pos_m": [
      -0.008020497858524323,
      0.13993093371391296,
      -0.0015417147660627961
    ],
    "ee_normal": [
      0.0,
      0.9999990463256836,
      0.0
    ],
    "knife": {
      "y_anim": 0.09615102410316467,
      "z_offset": 0.0009587852982804179
    },
    "relative_eef_force": 0.0,
    "force_world_N": {
      "x": 0.0,
      "y": 0.0,
      "z": 0.0,
      "norm": 9.999999974752427e-07
    },
    "force_normalized": {
      "x": 0.0,
      "y": 0.0,
      "z": 0.0
    },
    "scales": {
      "dx": 0.004166666883975267,
      "dt": 8.213426389724273e-06,
      "E": 6500000.0,
      "vcap_dx_over_dt": 507.29947360192307
    },
    "telemetry": {
      "material": {
        "E_Pa": 6500000.0,
        "sigma_y_Pa": 300000.0,
        "E_ref_Pa": 300000.0,
        "sigma_ref_Pa": 5000.0
      },
      "knife_resistance": {
        "k2_base_per_s": 0.0,
        "k2_eff_per_s": 0.0,
        "mat_gain": 279.28480087537883,
        "c_hat": 0.0,
        "c_hat_current": 0.0
      }
    }
  },
  {
    "frame": 2,
    "timestep": 4060,
    "time": 0.03333333333333333,
    "ee_pos_m": [
      -0.008020497858524323,
      0.13743658363819122,
      -0.0015417147660627961
    ],
    "ee_normal": [
      0.0,
      0.9999990463256836,
      0.0
    ],
    "knife": {
      "y_anim": 0.09365668147802353,
      "z_offset": 0.0009587852982804179
    },
    "relative_eef_force": 0.0,
    "force_world_N": {
      "x": 0.0,
      "y": 0.0,
      "z": 0.0,
      "norm": 9.999999974752427e-07
    },
    "force_normalized": {
      "x": 0.0,
      "y": 0.0,
      "z": 0.0
    },
    "scales": {
      "dx": 0.004166666883975267,
      "dt": 8.213426389724273e-06,
      "E": 6500000.0,
      "vcap_dx_over_dt": 507.29947360192307
    },
    "telemetry": {
      "material": {
        "E_Pa": 6500000.0,
        "sigma_y_Pa": 300000.0,
        "E_ref_Pa": 300000.0,
        "sigma_ref_Pa": 5000.0
      },
      "knife_resistance": {
        "k2_base_per_s": 0.0,
        "k2_eff_per_s": 0.0,
        "mat_gain": 279.28480087537883,
        "c_hat": 0.0,
        "c_hat_current": 0.0
      }
    }
  },
  {
    "frame": 3,
    "timestep": 6089,
    "time": 0.05,
    "ee_pos_m": [
      -0.008020497858524323,
      0.13494223356246948,
      -0.0015417147660627961
    ],
    "ee_normal": [
      0.0,
      0.9999990463256836,
      0.0
    ],
    "knife": {
      "y_anim": 0.09116233885288239,
      "z_offset": 0.0009587852982804179
    },
    "relative_eef_force": 0.0,
    "force_world_N": {
      "x": 0.0,
      "y": 0.0,
      "z": 0.0,
      "norm": 9.999999974752427e-07
    },
    "force_normalized": {
      "x": 0.0,
      "y": 0.0,
      "z": 0.0
    },
    "scales": {
      "dx": 0.004166666883975267,
      "dt": 8.213426389724273e-06,
      "E": 6500000.0,
      "vcap_dx_over_dt": 507.29947360192307
    },
    "telemetry": {
      "material": {
        "E_Pa": 6500000.0,
        "sigma_y_Pa": 300000.0,
        "E_ref_Pa": 300000.0,
        "sigma_ref_Pa": 5000.0
      },
      "knife_resistance": {
        "k2_base_per_s": 0.0,
        "k2_eff_per_s": 0.0,
        "mat_gain": 279.28480087537883,
        "c_hat": 0.0,
        "c_hat_current": 0.0
      }
    }
  },
  {
    "frame": 4,
    "timestep": 8118,
    "time": 0.06666666666666667,
    "ee_pos_m": [
      -0.008020497858524323,
      0.13244789838790894,
      -0.0015417147660627961
    ],
    "ee_normal": [
      0.0,
      0.9999990463256836,
      0.0
    ],
    "knife": {
      "y_anim": 0.08866799622774124,
      "z_offset": 0.0009587852982804179
    },
    "relative_eef_force": 0.0,
    "force_world_N": {
      "x": 0.0,
      "y": 0.0,
      "z": 0.0,
      "norm": 9.999999974752427e-07
    },
    "force_normalized": {
      "x": 0.0,
      "y": 0.0,
      "z": 0.0
    },
    "scales": {
      "dx": 0.004166666883975267,
      "dt": 8.213426389724273e-06,
      "E": 6500000.0,
      "vcap_dx_over_dt": 507.29947360192307
    },
    "telemetry": {
      "material": {
        "E_Pa": 6500000.0,
        "sigma_y_Pa": 300000.0,
        "E_ref_Pa": 300000.0,
        "sigma_ref_Pa": 5000.0
      },
      "knife_resistance": {
        "k2_base_per_s": 0.0,
        "k2_eff_per_s": 0.0,
        "mat_gain": 279.28480087537883,
        "c_hat": 0.0,
        "c_hat_current": 0.0
      }
    }
  },
  {
    "frame": 5,
    "timestep": 10147,
    "time": 0.08333333333333333,
    "ee_pos_m": [
      -0.008020497858524323,
      0.1299535632133484,
      -0.0015417147660627961
    ],
    "ee_normal": [
      0.0,
      0.9999990463256836,
      0.0
    ],
    "knife": {
      "y_anim": 0.0861736536026001,
      "z_offset": 0.0009587852982804179
    },
    "relative_eef_force": 0.0,
    "force_world_N": {
      "x": 0.0,
      "y": 0.0,
      "z": 0.0,
      "norm": 9.999999974752427e-07
    },
    "force_normalized": {
      "x": 0.0,
      "y": 0.0,
      "z": 0.0
    },
    "scales": {
      "dx": 0.004166666883975267,
      "dt": 8.213426389724273e-06,
      "E": 6500000.0,
      "vcap_dx_over_dt": 507.29947360192307
    },
    "telemetry": {
      "material": {
        "E_Pa": 6500000.0,
        "sigma_y_Pa": 300000.0,
        "E_ref_Pa": 300000.0,
        "sigma_ref_Pa": 5000.0
      },
      "knife_resistance": {
        "k2_base_per_s": 0.0,
        "k2_eff_per_s": 0.0,
        "mat_gain": 279.28480087537883,
        "c_hat": 0.0,
        "c_hat_current": 0.0
      }
    }
  },
  {
    "frame": 6,
    "timestep": 12177,
    "time": 0.09999999999999999,
    "ee_pos_m": [
      -0.008020497858524323,
      0.12745797634124756,
      -0.0015417147660627961
    ],
    "ee_normal": [
      0.0,
      0.9999990463256836,
      0.0
    ],
    "knife": {
      "y_anim": 0.08367808163166046,
      "z_offset": 0.0009587852982804179
    },
    "relative_eef_force": 0.0,
    "force_world_N": {
      "x": 0.0,
      "y": 0.0,
      "z": 0.0,
      "norm": 9.999999974752427e-07
    },
    "force_normalized": {
      "x": 0.0,
      "y": 0.0,
      "z": 0.0
    },
    "scales": {
      "dx": 0.004166666883975267,
      "dt": 8.213426389724273e-06,
      "E": 6500000.0,
      "vcap_dx_over_dt": 507.29947360192307
    },
    "telemetry": {
      "material": {
        "E_Pa": 6500000.0,
        "sigma_y_Pa": 300000.0,
        "E_ref_Pa": 300000.0,
        "sigma_ref_Pa": 5000.0
      },
      "knife_resistance": {
        "k2_base_per_s": 0.0,
        "k2_eff_per_s": 0.0,
        "mat_gain": 279.28480087537883,
        "c_hat": 0.0,
        "c_hat_current": 0.0
      }
    }
  },
  {
    "frame": 7,
    "timestep": 14206,
    "time": 0.11666666666666665,
    "ee_pos_m": [
      -0.008020497858524323,
      0.12496364116668701,
      -0.0015417147660627961
    ],
    "ee_normal": [
      0.0,
      0.9999990463256836,
      0.0
    ],
    "knife": {
      "y_anim": 0.08118373900651932,
      "z_offset": 0.0009587852982804179
    },
    "relative_eef_force": 0.0,
    "force_world_N": {
      "x": 0.0,
      "y": 0.0,
      "z": 0.0,
      "norm": 9.999999974752427e-07
    },
    "force_normalized": {
      "x": 0.0,
      "y": 0.0,
      "z": 0.0
    },
    "scales": {
      "dx": 0.004166666883975267,
      "dt": 8.213426389724273e-06,
      "E": 6500000.0,
      "vcap_dx_over_dt": 507.29947360192307
    },
    "telemetry": {
      "material": {
        "E_Pa": 6500000.0,
        "sigma_y_Pa": 300000.0,
        "E_ref_Pa": 300000.0,
        "sigma_ref_Pa": 5000.0
      },
      "knife_resistance": {
        "k2_base_per_s": 0.0,
        "k2_eff_per_s": 0.0,
        "mat_gain": 279.28480087537883,
        "c_hat": 0.0,
        "c_hat_current": 0.0
      }
    }
  },
  {
    "frame": 8,
    "timestep": 16235,
    "time": 0.13333333333333333,
    "ee_pos_m": [
      -0.008020497858524323,
      0.12246929854154587,
      -0.0015417147660627961
    ],
    "ee_normal": [
      0.0,
      0.9999990463256836,
      0.0
    ],
    "knife": {
      "y_anim": 0.07868939638137817,
      "z_offset": 0.0009587852982804179
    },
    "relative_eef_force": 0.0,
    "force_world_N": {
      "x": 0.0,
      "y": 0.0,
      "z": 0.0,
      "norm": 9.999999974752427e-07
    },
    "force_normalized": {
      "x": 0.0,
      "y": 0.0,
      "z": 0.0
    },
    "scales": {
      "dx": 0.004166666883975267,
      "dt": 8.213426389724273e-06,
      "E": 6500000.0,
      "vcap_dx_over_dt": 507.29947360192307
    },
    "telemetry": {
      "material": {
        "E_Pa": 6500000.0,
        "sigma_y_Pa": 300000.0,
        "E_ref_Pa": 300000.0,
        "sigma_ref_Pa": 5000.0
      },
      "knife_resistance": {
        "k2_base_per_s": 0.0,
        "k2_eff_per_s": 0.0,
        "mat_gain": 279.28480087537883,
        "c_hat": 0.0,
        "c_hat_current": 0.0
      }
    }
  },
  {
    "frame": 9,
    "timestep": 18264,
    "time": 0.15,
    "ee_pos_m": [
      -0.008020497858524323,
      0.11997495591640472,
      -0.0015417147660627961
    ],
    "ee_normal": [
      0.0,
      0.9999990463256836,
      0.0
    ],
    "knife": {
      "y_anim": 0.07619505375623703,
      "z_offset": 0.0009587852982804179
    },
    "relative_eef_force": 0.0,
    "force_world_N": {
      "x": 0.0,
      "y": 0.0,
      "z": 0.0,
      "norm": 9.999999974752427e-07
    },
    "force_normalized": {
      "x": 0.0,
      "y": 0.0,
      "z": 0.0
    },
    "scales": {
      "dx": 0.004166666883975267,
      "dt": 8.213426389724273e-06,
      "E": 6500000.0,
      "vcap_dx_over_dt": 507.29947360192307
    },
    "telemetry": {
      "material": {
        "E_Pa": 6500000.0,
        "sigma_y_Pa": 300000.0,
        "E_ref_Pa": 300000.0,
        "sigma_ref_Pa": 5000.0
      },
      "knife_resistance": {
        "k2_base_per_s": 0.0,
        "k2_eff_per_s": 0.0,
        "mat_gain": 279.28480087537883,
        "c_hat": 0.0,
        "c_hat_current": 0.0
      }
    }
  },
  {
    "frame": 10,
    "timestep": 20293,
    "time": 0.16666666666666666,
    "ee_pos_m": [
      -0.008020497858524323,
      0.11748061329126358,
      -0.0015417147660627961
    ],
    "ee_normal": [
      0.0,
      0.9999990463256836,
      0.0
    ],
    "knife": {
      "y_anim": 0.07370071113109589,
      "z_offset": 0.0009587852982804179
    },
    "relative_eef_force": 0.0,
    "force_world_N": {
      "x": 0.0,
      "y": 0.0,
      "z": 0.0,
      "norm": 9.999999974752427e-07
    },
    "force_normalized": {
      "x": 0.0,
      "y": 0.0,
      "z": 0.0
    },
    "scales": {
      "dx": 0.004166666883975267,
      "dt": 8.213426389724273e-06,
      "E": 6500000.0,
      "vcap_dx_over_dt": 507.29947360192307
    },
    "telemetry": {
      "material": {
        "E_Pa": 6500000.0,
        "sigma_y_Pa": 300000.0,
        "E_ref_Pa": 300000.0,
        "sigma_ref_Pa": 5000.0
      },
      "knife_resistance": {
        "k2_base_per_s": 0.0,
        "k2_eff_per_s": 0.0,
        "mat_gain": 279.28480087537883,
        "c_hat": 0.0,
        "c_hat_current": 0.0
      }
    }
  },
  {
    "frame": 11,
    "timestep": 22323,
    "time": 0.18333333333333332,
    "ee_pos_m": [
      -0.008020497858524323,
      0.11498504132032394,
      -0.0015417147660627961
    ],
    "ee_normal": [
      0.0,
      0.9999990463256836,
      0.0
    ],
    "knife": {
      "y_anim": 0.07120513916015625,
      "z_offset": 0.0009587852982804179
    },
    "relative_eef_force": 0.0,
    "force_world_N": {
      "x": 0.0,
      "y": 0.0,
      "z": 0.0,
      "norm": 9.999999974752427e-07
    },
    "force_normalized": {
      "x": 0.0,
      "y": 0.0,
      "z": 0.0
    },
    "scales": {
      "dx": 0.004166666883975267,
      "dt": 8.213426389724273e-06,
      "E": 6500000.0,
      "vcap_dx_over_dt": 507.29947360192307
    },
    "telemetry": {
      "material": {
        "E_Pa": 6500000.0,
        "sigma_y_Pa": 300000.0,
        "E_ref_Pa": 300000.0,
        "sigma_ref_Pa": 5000.0
      },
      "knife_resistance": {
        "k2_base_per_s": 0.0,
        "k2_eff_per_s": 0.0,
        "mat_gain": 279.28480087537883,
        "c_hat": 0.0,
        "c_hat_current": 0.0
      }
    }
  },
  {
    "frame": 12,
    "timestep": 24352,
    "time": 0.19999999999999998,
    "ee_pos_m": [
      -0.008020497858524323,
      0.1124906986951828,
      -0.0015417147660627961
    ],
    "ee_normal": [
      0.0,
      0.9999990463256836,
      0.0
    ],
    "knife": {
      "y_anim": 0.0687107965350151,
      "z_offset": 0.0009587852982804179
    },
    "relative_eef_force": 0.0,
    "force_world_N": {
      "x": 0.0,
      "y": 0.0,
      "z": 0.0,
      "norm": 9.999999974752427e-07
    },
    "force_normalized": {
      "x": 0.0,
      "y": 0.0,
      "z": 0.0
    },
    "scales": {
      "dx": 0.004166666883975267,
      "dt": 8.213426389724273e-06,
      "E": 6500000.0,
      "vcap_dx_over_dt": 507.29947360192307
    },
    "telemetry": {
      "material": {
        "E_Pa": 6500000.0,
        "sigma_y_Pa": 300000.0,
        "E_ref_Pa": 300000.0,
        "sigma_ref_Pa": 5000.0
      },
      "knife_resistance": {
        "k2_base_per_s": 0.0,
        "k2_eff_per_s": 0.0,
        "mat_gain": 279.28480087537883,
        "c_hat": 0.0,
        "c_hat_current": 0.0
      }
    }
  },
  {
    "frame": 13,
    "timestep": 26381,
    "time": 0.21666666666666665,
    "ee_pos_m": [
      -0.008020497858524323,
      0.10999635607004166,
      -0.0015417147660627961
    ],
    "ee_normal": [
      0.0,
      0.9999990463256836,
      0.0
    ],
    "knife": {
      "y_anim": 0.06621645390987396,
      "z_offset": 0.0009587852982804179
    },
    "relative_eef_force": 0.0,
    "force_world_N": {
      "x": 0.0,
      "y": 0.0,
      "z": 0.0,
      "norm": 9.999999974752427e-07
    },
    "force_normalized": {
      "x": 0.0,
      "y": 0.0,
      "z": 0.0
    },
    "scales": {
      "dx": 0.004166666883975267,
      "dt": 8.213426389724273e-06,
      "E": 6500000.0,
      "vcap_dx_over_dt": 507.29947360192307
    },
    "telemetry": {
      "material": {
        "E_Pa": 6500000.0,
        "sigma_y_Pa": 300000.0,
        "E_ref_Pa": 300000.0,
        "sigma_ref_Pa": 5000.0
      },
      "knife_resistance": {
        "k2_base_per_s": 0.0,
        "k2_eff_per_s": 0.0,
        "mat_gain": 279.28480087537883,
        "c_hat": 0.0,
        "c_hat_current": 0.0
      }
    }
  },
  {
    "frame": 14,
    "timestep": 28410,
    "time": 0.2333333333333333,
    "ee_pos_m": [
      -0.008020497858524323,
      0.10750201344490051,
      -0.0015417147660627961
    ],
    "ee_normal": [
      0.0,
      0.9999990463256836,
      0.0
    ],
    "knife": {
      "y_anim": 0.06372211128473282,
      "z_offset": 0.0009587852982804179
    },
    "relative_eef_force": 0.0,
    "force_world_N": {
      "x": 0.0,
      "y": 0.0,
      "z": 0.0,
      "norm": 9.999999974752427e-07
    },
    "force_normalized": {
      "x": 0.0,
      "y": 0.0,
      "z": 0.0
    },
    "scales": {
      "dx": 0.004166666883975267,
      "dt": 8.213426389724273e-06,
      "E": 6500000.0,
      "vcap_dx_over_dt": 507.29947360192307
    },
    "telemetry": {
      "material": {
        "E_Pa": 6500000.0,
        "sigma_y_Pa": 300000.0,
        "E_ref_Pa": 300000.0,
        "sigma_ref_Pa": 5000.0
      },
      "knife_resistance": {
        "k2_base_per_s": 0.0,
        "k2_eff_per_s": 0.0,
        "mat_gain": 279.28480087537883,
        "c_hat": 0.0,
        "c_hat_current": 0.0
      }
    }
  },
  {
    "frame": 15,
    "timestep": 30439,
    "time": 0.24999999999999997,
    "ee_pos_m": [
      -0.008020497858524323,
      0.10500381141901016,
      -0.0015417147660627961
    ],
    "ee_normal": [
      0.0,
      0.9999990463256836,
      0.0
    ],
    "knife": {
      "y_anim": 0.06122391298413277,
      "z_offset": 0.0009587852982804179
    },
    "relative_eef_force": 0.0,
    "force_world_N": {
      "x": 0.0,
      "y": 0.0,
      "z": 0.0,
      "norm": 9.999999974752427e-07
    },
    "force_normalized": {
      "x": 0.0,
      "y": 0.0,
      "z": 0.0
    },
    "scales": {
      "dx": 0.004166666883975267,
      "dt": 8.213426389724273e-06,
      "E": 6500000.0,
      "vcap_dx_over_dt": 507.29947360192307
    },
    "telemetry": {
      "material": {
        "E_Pa": 6500000.0,
        "sigma_y_Pa": 300000.0,
        "E_ref_Pa": 300000.0,
        "sigma_ref_Pa": 5000.0
      },
      "knife_resistance": {
        "k2_base_per_s": 0.0,
        "k2_eff_per_s": 0.0,
        "mat_gain": 279.28480087537883,
        "c_hat": 0.0,
        "c_hat_current": 0.0
      }
    }
  },
  {
    "frame": 16,
    "timestep": 32469,
    "time": 0.26666666666666666,
    "ee_pos_m": [
      -0.008020497858524323,
      0.10250067710876465,
      -0.0015417147660627961
    ],
    "ee_normal": [
      0.0,
      0.9999990463256836,
      0.0
    ],
    "knife": {
      "y_anim": 0.05872077867388725,
      "z_offset": 0.0009587852982804179
    },
    "relative_eef_force": 0.0,
    "force_world_N": {
      "x": 0.0,
      "y": 0.0,
      "z": 0.0,
      "norm": 9.999999974752427e-07
    },
    "force_normalized": {
      "x": 0.0,
      "y": 0.0,
      "z": 0.0
    },
    "scales": {
      "dx": 0.004166666883975267,
      "dt": 8.213426389724273e-06,
      "E": 6500000.0,
      "vcap_dx_over_dt": 507.29947360192307
    },
    "telemetry": {
      "material": {
        "E_Pa": 6500000.0,
        "sigma_y_Pa": 300000.0,
        "E_ref_Pa": 300000.0,
        "sigma_ref_Pa": 5000.0
      },
      "knife_resistance": {
        "k2_base_per_s": 0.0,
        "k2_eff_per_s": 0.0,
        "mat_gain": 279.28480087537883,
        "c_hat": 0.0,
        "c_hat_current": 0.0
      }
    }
  },
  {
    "frame": 17,
    "timestep": 34498,
    "time": 0.2833333333333333,
    "ee_pos_m": [
      -0.008020497858524323,
      0.09999877959489822,
      -0.0015417147660627961
    ],
    "ee_normal": [
      0.0,
      0.9999990463256836,
      0.0
    ],
    "knife": {
      "y_anim": 0.05621887743473053,
      "z_offset": 0.0009587852982804179
    },
    "relative_eef_force": 0.0,
    "force_world_N": {
      "x": 0.0,
      "y": 0.0,
      "z": 0.0,
      "norm": 9.999999974752427e-07
    },
    "force_normalized": {
      "x": 0.0,
      "y": 0.0,
      "z": 0.0
    },
    "scales": {
      "dx": 0.004166666883975267,
      "dt": 8.213426389724273e-06,
      "E": 6500000.0,
      "vcap_dx_over_dt": 507.29947360192307
    },
    "telemetry": {
      "material": {
        "E_Pa": 6500000.0,
        "sigma_y_Pa": 300000.0,
        "E_ref_Pa": 300000.0,
        "sigma_ref_Pa": 5000.0
      },
      "knife_resistance": {
        "k2_base_per_s": 0.0,
        "k2_eff_per_s": 0.0,
        "mat_gain": 279.28480087537883,
        "c_hat": 0.0,
        "c_hat_current": 0.0
      }
    }
  },
  {
    "frame": 18,
    "timestep": 36527,
    "time": 0.3,
    "ee_pos_m": [
      -0.008020497858524323,
      0.0974968746304512,
      -0.0015417147660627961
    ],
    "ee_normal": [
      0.0,
      0.9999990463256836,
      0.0
    ],
    "knife": {
      "y_anim": 0.05371697619557381,
      "z_offset": 0.0009587852982804179
    },
    "relative_eef_force": 0.879076961427927,
    "force_world_N": {
      "x": -0.0003289386222604662,
      "y": -0.02340097539126873,
      "z": -0.012558242306113243,
      "norm": 0.02656080573797226
    },
    "force_normalized": {
      "x": -0.01238436158746481,
      "y": -0.8810340762138367,
      "z": -0.4728110432624817
    },
    "scales": {
      "dx": 0.004166666883975267,
      "dt": 8.213426389724273e-06,
      "E": 6500000.0,
      "vcap_dx_over_dt": 507.29947360192307
    },
    "telemetry": {
      "material": {
        "E_Pa": 6500000.0,
        "sigma_y_Pa": 300000.0,
        "E_ref_Pa": 300000.0,
        "sigma_ref_Pa": 5000.0
      },
      "knife_resistance": {
        "k2_base_per_s": 0.0,
        "k2_eff_per_s": 0.0,
        "mat_gain": 279.28480087537883,
        "c_hat": 0.001770826056599617,
        "c_hat_current": 0.0017711323253631415
      }
    }
  },
  {
    "frame": 19,
    "timestep": 38556,
    "time": 0.31666666666666665,
    "ee_pos_m": [
      -0.008020497858524323,
      0.09499497711658478,
      -0.0015417147660627961
    ],
    "ee_normal": [
      0.0,
      0.9999990463256836,
      0.0
    ],
    "knife": {
      "y_anim": 0.051215074956417084,
      "z_offset": 0.0009587852982804179
    },
    "relative_eef_force": 3.410298191010952,
    "force_world_N": {
      "x": -0.0013018358731642365,
      "y": -0.09186823666095734,
      "z": -0.04871854558587074,
      "norm": 0.10399602353572845
    },
    "force_normalized": {
      "x": -0.012518131174147129,
      "y": -0.8833822011947632,
      "z": -0.4684654772281647
    },
    "scales": {
      "dx": 0.004166666883975267,
      "dt": 8.213426389724273e-06,
      "E": 6500000.0,
      "vcap_dx_over_dt": 507.29947360192307
    },
    "telemetry": {
      "material": {
        "E_Pa": 6500000.0,
        "sigma_y_Pa": 300000.0,
        "E_ref_Pa": 300000.0,
        "sigma_ref_Pa": 5000.0
      },
      "knife_resistance": {
        "k2_base_per_s": 0.0,
        "k2_eff_per_s": 0.0,
        "mat_gain": 279.28480087537883,
        "c_hat": 0.0022976305335760117,
        "c_hat_current": 0.0022977006753560777
      }
    }
  },
  {
    "frame": 20,
    "timestep": 40585,
    "time": 0.3333333333333333,
    "ee_pos_m": [
      -0.008020497858524323,
      0.09249307215213776,
      -0.0015417147660627961
    ],
    "ee_normal": [
      0.0,
      0.9999990463256836,
      0.0
    ],
    "knife": {
      "y_anim": 0.04871317371726036,
      "z_offset": 0.0009587852982804179
    },
    "relative_eef_force": 6.703390553593636,
    "force_world_N": {
      "x": -0.0025745388120412827,
      "y": -0.17451204359531403,
      "z": -0.0957627221941948,
      "norm": 0.1990778148174286
    },
    "force_normalized": {
      "x": -0.012932323850691319,
      "y": -0.8766021728515625,
      "z": -0.4810316264629364
    },
    "scales": {
      "dx": 0.004166666883975267,
      "dt": 8.213426389724273e-06,
      "E": 6500000.0,
      "vcap_dx_over_dt": 507.29947360192307
    },
    "telemetry": {
      "material": {
        "E_Pa": 6500000.0,
        "sigma_y_Pa": 300000.0,
        "E_ref_Pa": 300000.0,
        "sigma_ref_Pa": 5000.0
      },
      "knife_resistance": {
        "k2_base_per_s": 0.0,
        "k2_eff_per_s": 0.0,
        "mat_gain": 279.28480087537883,
        "c_hat": 0.004421255085617304,
        "c_hat_current": 0.004421545471614007
      }
    }
  },
  {
    "frame": 21,
    "timestep": 42615,
    "time": 0.35,
    "ee_pos_m": [
      -0.008020497858524323,
      0.08998993784189224,
      -0.0015417147660627961
    ],
    "ee_normal": [
      0.0,
      0.9999990463256836,
      0.0
    ],
    "knife": {
      "y_anim": 0.04621003940701485,
      "z_offset": 0.0009587852982804179
    },
    "relative_eef_force": 9.773638248443604,
    "force_world_N": {
      "x": -0.003782667452469468,
      "y": -0.2555723190307617,
      "z": -0.13962340354919434,
      "norm": 0.29125040769577026
    },
    "force_normalized": {
      "x": -0.012987681664526463,
      "y": -0.8775002956390381,
      "z": -0.47939297556877136
    },
    "scales": {
      "dx": 0.004166666883975267,
      "dt": 8.213426389724273e-06,
      "E": 6500000.0,
      "vcap_dx_over_dt": 507.29947360192307
    },
    "telemetry": {
      "material": {
        "E_Pa": 6500000.0,
        "sigma_y_Pa": 300000.0,
        "E_ref_Pa": 300000.0,
        "sigma_ref_Pa": 5000.0
      },
      "knife_resistance": {
        "k2_base_per_s": 0.0,
        "k2_eff_per_s": 0.0,
        "mat_gain": 279.28480087537883,
        "c_hat": 0.005173064768314362,
        "c_hat_current": 0.005174430606058731
      }
    }
  },
  {
    "frame": 22,
    "timestep": 44644,
    "time": 0.36666666666666664,
    "ee_pos_m": [
      -0.008020497858524323,
      0.08748804032802582,
      -0.0015417147660627961
    ],
    "ee_normal": [
      0.0,
      0.9999990463256836,
      0.0
    ],
    "knife": {
      "y_anim": 0.043708138167858124,
      "z_offset": 0.0009587852982804179
    },
    "relative_eef_force": 40.33386707305908,
    "force_world_N": {
      "x": -0.011700969189405441,
      "y": -0.9649329781532288,
      "z": -0.5761981010437012,
      "norm": 1.123939037322998
    },
    "force_normalized": {
      "x": -0.010410679504275322,
      "y": -0.8585278391838074,
      "z": -0.5126595497131348
    },
    "scales": {
      "dx": 0.004166666883975267,
      "dt": 8.213426389724273e-06,
      "E": 6500000.0,
      "vcap_dx_over_dt": 507.29947360192307
    },
    "telemetry": {
      "material": {
        "E_Pa": 6500000.0,
        "sigma_y_Pa": 300000.0,
        "E_ref_Pa": 300000.0,
        "sigma_ref_Pa": 5000.0
      },
      "knife_resistance": {
        "k2_base_per_s": 0.0,
        "k2_eff_per_s": 0.0,
        "mat_gain": 279.28480087537883,
        "c_hat": 0.006720971316099167,
        "c_hat_current": 0.006723775708708799
      }
    }
  },
  {
    "frame": 23,
    "timestep": 46673,
    "time": 0.3833333333333333,
    "ee_pos_m": [
      -0.008020497858524323,
      0.0849861353635788,
      -0.0015417147660627961
    ],
    "ee_normal": [
      0.0,
      0.9999990463256836,
      0.0
    ],
    "knife": {
      "y_anim": 0.0412062369287014,
      "z_offset": 0.0009587852982804179
    },
    "relative_eef_force": 58.654183745384216,
    "force_world_N": {
      "x": -0.022211527451872826,
      "y": -1.4048736095428467,
      "z": -0.837916910648346,
      "norm": 1.6359312534332275
    },
    "force_normalized": {
      "x": -0.013577299192547798,
      "y": -0.8587607741355896,
      "z": -0.5121956467628479
    },
    "scales": {
      "dx": 0.004166666883975267,
      "dt": 8.213426389724273e-06,
      "E": 6500000.0,
      "vcap_dx_over_dt": 507.29947360192307
    },
    "telemetry": {
      "material": {
        "E_Pa": 6500000.0,
        "sigma_y_Pa": 300000.0,
        "E_ref_Pa": 300000.0,
        "sigma_ref_Pa": 5000.0
      },
      "knife_resistance": {
        "k2_base_per_s": 0.0,
        "k2_eff_per_s": 0.0,
        "mat_gain": 279.28480087537883,
        "c_hat": 0.011537875048816204,
        "c_hat_current": 0.011544703109219548
      }
    }
  },
  {
    "frame": 24,
    "timestep": 48702,
    "time": 0.39999999999999997,
    "ee_pos_m": [
      -0.008020497858524323,
      0.08248423039913177,
      -0.0015417147660627961
    ],
    "ee_normal": [
      0.0,
      0.9999990463256836,
      0.0
    ],
    "knife": {
      "y_anim": 0.03870433568954468,
      "z_offset": 0.0009587852982804179
    },
    "relative_eef_force": 90.67601561546326,
    "force_world_N": {
      "x": -0.04552057385444641,
      "y": -2.1670663356781006,
      "z": -1.295371651649475,
      "norm": 2.5251219272613525
    },
    "force_normalized": {
      "x": -0.018027080222964287,
      "y": -0.8582026362419128,
      "z": -0.5129936933517456
    },
    "scales": {
      "dx": 0.004166666883975267,
      "dt": 8.213426389724273e-06,
      "E": 6500000.0,
      "vcap_dx_over_dt": 507.29947360192307
    },
    "telemetry": {
      "material": {
        "E_Pa": 6500000.0,
        "sigma_y_Pa": 300000.0,
        "E_ref_Pa": 300000.0,
        "sigma_ref_Pa": 5000.0
      },
      "knife_resistance": {
        "k2_base_per_s": 0.0,
        "k2_eff_per_s": 0.0,
        "mat_gain": 279.28480087537883,
        "c_hat": 0.011397912167012691,
        "c_hat_current": 0.011399315356122154
      }
    }
  },
  {
    "frame": 25,
    "timestep": 50731,
    "time": 0.41666666666666663,
    "ee_pos_m": [
      -0.008020497858524323,
      0.07998233288526535,
      -0.0015417147660627961
    ],
    "ee_normal": [
      0.0,
      0.9999990463256836,
      0.0
    ],
    "knife": {
      "y_anim": 0.036202434450387955,
      "z_offset": 0.0009587852982804179
    },
    "relative_eef_force": 181.6274881362915,
    "force_world_N": {
      "x": -0.06366300582885742,
      "y": -4.513474464416504,
      "z": -2.5946784019470215,
      "norm": 5.206521987915039
    },
    "force_normalized": {
      "x": -0.012227549217641354,
      "y": -0.8668885827064514,
      "z": -0.4983515739440918
    },
    "scales": {
      "dx": 0.004166666883975267,
      "dt": 8.213426389724273e-06,
      "E": 6500000.0,
      "vcap_dx_over_dt": 507.29947360192307
    },
    "telemetry": {
      "material": {
        "E_Pa": 6500000.0,
        "sigma_y_Pa": 300000.0,
        "E_ref_Pa": 300000.0,
        "sigma_ref_Pa": 5000.0
      },
      "knife_resistance": {
        "k2_base_per_s": 0.0,
        "k2_eff_per_s": 0.0,
        "mat_gain": 279.28480087537883,
        "c_hat": 0.016710028052330017,
        "c_hat_current": 0.01671104744216169
      }
    }
  },
  {
    "frame": 26,
    "timestep": 52761,
    "time": 0.4333333333333333,
    "ee_pos_m": [
      -0.008020497858524323,
      0.07747919857501984,
      -0.0015417147660627961
    ],
    "ee_normal": [
      0.0,
      0.9999990463256836,
      0.0
    ],
    "knife": {
      "y_anim": 0.03369930014014244,
      "z_offset": 0.0009587852982804179
    },
    "relative_eef_force": 258.5060667991638,
    "force_world_N": {
      "x": -0.09268637746572495,
      "y": -6.69036340713501,
      "z": -3.692943811416626,
      "norm": 7.6424736976623535
    },
    "force_normalized": {
      "x": -0.012127798050642014,
      "y": -0.8754185438156128,
      "z": -0.4832131564617157
    },
    "scales": {
      "dx": 0.004166666883975267,
      "dt": 8.213426389724273e-06,
      "E": 6500000.0,
      "vcap_dx_over_dt": 507.29947360192307
    },
    "telemetry": {
      "material": {
        "E_Pa": 6500000.0,
        "sigma_y_Pa": 300000.0,
        "E_ref_Pa": 300000.0,
        "sigma_ref_Pa": 5000.0
      },
      "knife_resistance": {
        "k2_base_per_s": 0.0,
        "k2_eff_per_s": 0.0,
        "mat_gain": 279.28480087537883,
        "c_hat": 0.022040920332074165,
        "c_hat_current": 0.02204358603798893
      }
    }
  },
  {
    "frame": 27,
    "timestep": 54790,
    "time": 0.44999999999999996,
    "ee_pos_m": [
      -0.008020497858524323,
      0.07497738301753998,
      -0.0015417147660627961
    ],
    "ee_normal": [
      0.0,
      0.9999990463256836,
      0.0
    ],
    "knife": {
      "y_anim": 0.031197478994727135,
      "z_offset": 0.0009587852982804179
    },
    "relative_eef_force": 425.0411033630371,
    "force_world_N": {
      "x": -0.15567530691623688,
      "y": -10.984012603759766,
      "z": -6.072015762329102,
      "norm": 12.551580429077148
    },
    "force_normalized": {
      "x": -0.012402844615280628,
      "y": -0.8751099109649658,
      "z": -0.48376503586769104
    },
    "scales": {
      "dx": 0.004166666883975267,
      "dt": 8.213426389724273e-06,
      "E": 6500000.0,
      "vcap_dx_over_dt": 507.29947360192307
    },
    "telemetry": {
      "material": {
        "E_Pa": 6500000.0,
        "sigma_y_Pa": 300000.0,
        "E_ref_Pa": 300000.0,
        "sigma_ref_Pa": 5000.0
      },
      "knife_resistance": {
        "k2_base_per_s": 0.0,
        "k2_eff_per_s": 0.0,
        "mat_gain": 279.28480087537883,
        "c_hat": 0.021204646676778793,
        "c_hat_current": 0.0212052750409239
      }
    }
  },
  {
    "frame": 28,
    "timestep": 56819,
    "time": 0.4666666666666666,
    "ee_pos_m": [
      -0.008020497858524323,
      0.0724792554974556,
      -0.0015417147660627961
    ],
    "ee_normal": [
      0.0,
      0.9999990463256836,
      0.0
    ],
    "knife": {
      "y_anim": 0.0286993570625782,
      "z_offset": 0.0009587852982804179
    },
    "relative_eef_force": 572.4530220031738,
    "force_world_N": {
      "x": -0.21828575432300568,
      "y": -14.839644432067871,
      "z": -8.177900314331055,
      "norm": 16.94523048400879
    },
    "force_normalized": {
      "x": -0.012881840579211712,
      "y": -0.8757416605949402,
      "z": -0.48260778188705444
    },
    "scales": {
      "dx": 0.004166666883975267,
      "dt": 8.213426389724273e-06,
      "E": 6500000.0,
      "vcap_dx_over_dt": 507.29947360192307
    },
    "telemetry": {
      "material": {
        "E_Pa": 6500000.0,
        "sigma_y_Pa": 300000.0,
        "E_ref_Pa": 300000.0,
        "sigma_ref_Pa": 5000.0
      },
      "knife_resistance": {
        "k2_base_per_s": 0.0,
        "k2_eff_per_s": 0.0,
        "mat_gain": 279.28480087537883,
        "c_hat": 0.023145567625761032,
        "c_hat_current": 0.02314931607585686
      }
    }
  },
  {
    "frame": 29,
    "timestep": 58848,
    "time": 0.4833333333333333,
    "ee_pos_m": [
      -0.008020497858524323,
      0.06998113542795181,
      -0.0015417147660627961
    ],
    "ee_normal": [
      0.0,
      0.9999990463256836,
      0.0
    ],
    "knife": {
      "y_anim": 0.026201235130429268,
      "z_offset": 0.0009587852982804179
    },
    "relative_eef_force": 756.2410736083984,
    "force_world_N": {
      "x": -0.2692447006702423,
      "y": -19.689014434814453,
      "z": -10.803443908691406,
      "norm": 22.459836959838867
    },
    "force_normalized": {
      "x": -0.011987829580903053,
      "y": -0.8766320943832397,
      "z": -0.48101168870925903
    },
    "scales": {
      "dx": 0.004166666883975267,
      "dt": 8.213426389724273e-06,
      "E": 6500000.0,
      "vcap_dx_over_dt": 507.29947360192307
    },
    "telemetry": {
      "material": {
        "E_Pa": 6500000.0,
        "sigma_y_Pa": 300000.0,
        "E_ref_Pa": 300000.0,
        "sigma_ref_Pa": 5000.0
      },
      "knife_resistance": {
        "k2_base_per_s": 0.0,
        "k2_eff_per_s": 0.0,
        "mat_gain": 279.28480087537883,
        "c_hat": 0.022332370281219482,
        "c_hat_current": 0.02233302009834455
      }
    }
  }
]