[
  {
    "frame": 0,
    "timestep": 1,
    "time": 0.0,
    "ee_pos_m": [
      -0.008020497858524323,
      0.1424238085746765,
      -0.0015417147660627961
    ],
    "ee_normal": [
      0.0,
      0.9999990463256836,
      0.0
    ],
    "knife": {
      "y_anim": 0.09864391386508942,
      "z_offset": 0.0009587852982804179
    },
    "relative_eef_force": 0.0,
    "force_world_N": {
      "x": 0.0,
      "y": 0.0,
      "z": 0.0,
      "norm": 9.999999974752427e-07
    },
    "force_normalized": {
      "x": 0.0,
      "y": 0.0,
      "z": 0.0
    },
    "scales": {
      "dx": 0.004166666883975267,
      "dt": 1.956452385842877e-05,
      "E": 1200000.0,
      "vcap_dx_over_dt": 212.97052328621774
    },
    "telemetry": {
      "material": {
        "E_Pa": 1200000.0,
        "sigma_y_Pa": 50000.0,
        "E_ref_Pa": 300000.0,
        "sigma_ref_Pa": 5000.0
      },
      "knife_resistance": {
        "k2_base_per_s": 0.0,
        "k2_eff_per_s": 0.0,
        "mat_gain": 20.0,
        "c_hat": 0.0,
        "c_hat_current": 0.0
      }
    }
  },
  {
    "frame": 1,
    "timestep": 853,
    "time": 0.016666666666666666,
    "ee_pos_m": [
      -0.008020497858524323,
      0.13909116387367249,
      -0.0015417147660627961
    ],
    "ee_normal": [
      0.0,
      0.9999990463256836,
      0.0
    ],
    "knife": {
      "y_anim": 0.09531126916408539,
      "z_offset": 0.0009587852982804179
    },
    "relative_eef_force": 0.0,
    "force_world_N": {
      "x": 0.0,
      "y": 0.0,
      "z": 0.0,
      "norm": 9.999999974752427e-07
    },
    "force_normalized": {
      "x": 0.0,
      "y": 0.0,
      "z": 0.0
    },
    "scales": {
      "dx": 0.004166666883975267,
      "dt": 1.956452385842877e-05,
      "E": 1200000.0,
      "vcap_dx_over_dt": 212.97052328621774
    },
    "telemetry": {
      "material": {
        "E_Pa": 1200000.0,
        "sigma_y_Pa": 50000.0,
        "E_ref_Pa": 300000.0,
        "sigma_ref_Pa": 5000.0
      },
      "knife_resistance": {
        "k2_base_per_s": 0.0,
        "k2_eff_per_s": 0.0,
        "mat_gain": 20.0,
        "c_hat": 0.0,
        "c_hat_current": 0.0
      }
    }
  },
  {
    "frame": 2,
    "timestep": 1705,
    "time": 0.03333333333333333,
    "ee_pos_m": [
      -0.008020497858524323,
      0.13575851917266846,
      -0.0015417147660627961
    ],
    "ee_normal": [
      0.0,
      0.9999990463256836,
      0.0
    ],
    "knife": {
      "y_anim": 0.09197862446308136,
      "z_offset": 0.0009587852982804179
    },
    "relative_eef_force": 0.0,
    "force_world_N": {
      "x": 0.0,
      "y": 0.0,
      "z": 0.0,
      "norm": 9.999999974752427e-07
    },
    "force_normalized": {
      "x": 0.0,
      "y": 0.0,
      "z": 0.0
    },
    "scales": {
      "dx": 0.004166666883975267,
      "dt": 1.956452385842877e-05,
      "E": 1200000.0,
      "vcap_dx_over_dt": 212.97052328621774
    },
    "telemetry": {
      "material": {
        "E_Pa": 1200000.0,
        "sigma_y_Pa": 50000.0,
        "E_ref_Pa": 300000.0,
        "sigma_ref_Pa": 5000.0
      },
      "knife_resistance": {
        "k2_base_per_s": 0.0,
        "k2_eff_per_s": 0.0,
        "mat_gain": 20.0,
        "c_hat": 0.0,
        "c_hat_current": 0.0
      }
    }
  },
  {
    "frame": 3,
    "timestep": 2557,
    "time": 0.05,
    "ee_pos_m": [
      -0.008020497858524323,
      0.13242587447166443,
      -0.0015417147660627961
    ],
    "ee_normal": [
      0.0,
      0.9999990463256836,
      0.0
    ],
    "knife": {
      "y_anim": 0.08864597976207733,
      "z_offset": 0.0009587852982804179
    },
    "relative_eef_force": 0.0,
    "force_world_N": {
      "x": 0.0,
      "y": 0.0,
      "z": 0.0,
      "norm": 9.999999974752427e-07
    },
    "force_normalized": {
      "x": 0.0,
      "y": 0.0,
      "z": 0.0
    },
    "scales": {
      "dx": 0.004166666883975267,
      "dt": 1.956452385842877e-05,
      "E": 1200000.0,
      "vcap_dx_over_dt": 212.97052328621774
    },
    "telemetry": {
      "material": {
        "E_Pa": 1200000.0,
        "sigma_y_Pa": 50000.0,
        "E_ref_Pa": 300000.0,
        "sigma_ref_Pa": 5000.0
      },
      "knife_resistance": {
        "k2_base_per_s": 0.0,
        "k2_eff_per_s": 0.0,
        "mat_gain": 20.0,
        "c_hat": 0.0,
        "c_hat_current": 0.0
      }
    }
  },
  {
    "frame": 4,
    "timestep": 3409,
    "time": 0.06666666666666667,
    "ee_pos_m": [
      -0.008020497858524323,
      0.1290932297706604,
      -0.0015417147660627961
    ],
    "ee_normal": [
      0.0,
      0.9999990463256836,
      0.0
    ],
    "knife": {
      "y_anim": 0.0853133350610733,
      "z_offset": 0.0009587852982804179
    },
    "relative_eef_force": 0.0,
    "force_world_N": {
      "x": 0.0,
      "y": 0.0,
      "z": 0.0,
      "norm": 9.999999974752427e-07
    },
    "force_normalized": {
      "x": 0.0,
      "y": 0.0,
      "z": 0.0
    },
    "scales": {
      "dx": 0.004166666883975267,
      "dt": 1.956452385842877e-05,
      "E": 1200000.0,
      "vcap_dx_over_dt": 212.97052328621774
    },
    "telemetry": {
      "material": {
        "E_Pa": 1200000.0,
        "sigma_y_Pa": 50000.0,
        "E_ref_Pa": 300000.0,
        "sigma_ref_Pa": 5000.0
      },
      "knife_resistance": {
        "k2_base_per_s": 0.0,
        "k2_eff_per_s": 0.0,
        "mat_gain": 20.0,
        "c_hat": 0.0,
        "c_hat_current": 0.0
      }
    }
  },
  {
    "frame": 5,
    "timestep": 4261,
    "time": 0.08333333333333333,
    "ee_pos_m": [
      -0.008020497858524323,
      0.12576058506965637,
      -0.0015417147660627961
    ],
    "ee_normal": [
      0.0,
      0.9999990463256836,
      0.0
    ],
    "knife": {
      "y_anim": 0.08198069036006927,
      "z_offset": 0.0009587852982804179
    },
    "relative_eef_force": 0.0,
    "force_world_N": {
      "x": 0.0,
      "y": 0.0,
      "z": 0.0,
      "norm": 9.999999974752427e-07
    },
    "force_normalized": {
      "x": 0.0,
      "y": 0.0,
      "z": 0.0
    },
    "scales": {
      "dx": 0.004166666883975267,
      "dt": 1.956452385842877e-05,
      "E": 1200000.0,
      "vcap_dx_over_dt": 212.97052328621774
    },
    "telemetry": {
      "material": {
        "E_Pa": 1200000.0,
        "sigma_y_Pa": 50000.0,
        "E_ref_Pa": 300000.0,
        "sigma_ref_Pa": 5000.0
      },
      "knife_resistance": {
        "k2_base_per_s": 0.0,
        "k2_eff_per_s": 0.0,
        "mat_gain": 20.0,
        "c_hat": 0.0,
        "c_hat_current": 0.0
      }
    }
  },
  {
    "frame": 6,
    "timestep": 5113,
    "time": 0.09999999999999999,
    "ee_pos_m": [
      -0.008020497858524323,
      0.12242794781923294,
      -0.0015417147660627961
    ],
    "ee_normal": [
      0.0,
      0.9999990463256836,
      0.0
    ],
    "knife": {
      "y_anim": 0.07864804565906525,
      "z_offset": 0.0009587852982804179
    },
    "relative_eef_force": 1.7320804111659527,
    "force_world_N": {
      "x": -0.0005908395978622139,
      "y": -0.04638802632689476,
      "z": -0.024744005873799324,
      "norm": 0.05257916823029518
    },
    "force_normalized": {
      "x": -0.011237142607569695,
      "y": -0.8822510242462158,
      "z": -0.4706047475337982
    },
    "scales": {
      "dx": 0.004166666883975267,
      "dt": 1.956452385842877e-05,
      "E": 1200000.0,
      "vcap_dx_over_dt": 212.97052328621774
    },
    "telemetry": {
      "material": {
        "E_Pa": 1200000.0,
        "sigma_y_Pa": 50000.0,
        "E_ref_Pa": 300000.0,
        "sigma_ref_Pa": 5000.0
      },
      "knife_resistance": {
        "k2_base_per_s": 0.0,
        "k2_eff_per_s": 0.0,
        "mat_gain": 20.0,
        "c_hat": 0.011591115966439247,
        "c_hat_current": 0.011592876429174217
      }
    }
  },
  {
    "frame": 7,
    "timestep": 5965,
    "time": 0.11666666666666665,
    "ee_pos_m": [
      -0.008020497858524323,
      0.11909530311822891,
      -0.0015417147660627961
    ],
    "ee_normal": [
      0.0,
      0.9999990463256836,
      0.0
    ],
    "knife": {
      "y_anim": 0.07531540095806122,
      "z_offset": 0.0009587852982804179
    },
    "relative_eef_force": 8.724330291152,
    "force_world_N": {
      "x": -0.0030326261185109615,
      "y": -0.23204249143600464,
      "z": -0.1246332898736,
      "norm": 0.2634139358997345
    },
    "force_normalized": {
      "x": -0.011512777768075466,
      "y": -0.8809043765068054,
      "z": -0.47314614057540894
    },
    "scales": {
      "dx": 0.004166666883975267,
      "dt": 1.956452385842877e-05,
      "E": 1200000.0,
      "vcap_dx_over_dt": 212.97052328621774
    },
    "telemetry": {
      "material": {
        "E_Pa": 1200000.0,
        "sigma_y_Pa": 50000.0,
        "E_ref_Pa": 300000.0,
        "sigma_ref_Pa": 5000.0
      },
      "knife_resistance": {
        "k2_base_per_s": 0.0,
        "k2_eff_per_s": 0.0,
        "mat_gain": 20.0,
        "c_hat": 0.017988519743084908,
        "c_hat_current": 0.017986755013912396
      }
    }
  },
  {
    "frame": 8,
    "timestep": 6817,
    "time": 0.13333333333333333,
    "ee_pos_m": [
      -0.008020497858524323,
      0.11576265841722488,
      -0.0015417147660627961
    ],
    "ee_normal": [
      0.0,
      0.9999990463256836,
      0.0
    ],
    "knife": {
      "y_anim": 0.07198275625705719,
      "z_offset": 0.0009587852982804179
    },
    "relative_eef_force": 35.020615458488464,
    "force_world_N": {
      "x": -0.012021329253911972,
      "y": -0.9007384777069092,
      "z": -0.5002945065498352,
      "norm": 1.0304226875305176
    },
    "force_normalized": {
      "x": -0.011666405946016312,
      "y": -0.8741446733474731,
      "z": -0.4855235815048218
    },
    "scales": {
      "dx": 0.004166666883975267,
      "dt": 1.956452385842877e-05,
      "E": 1200000.0,
      "vcap_dx_over_dt": 212.97052328621774
    },
    "telemetry": {
      "material": {
        "E_Pa": 1200000.0,
        "sigma_y_Pa": 50000.0,
        "E_ref_Pa": 300000.0,
        "sigma_ref_Pa": 5000.0
      },
      "knife_resistance": {
        "k2_base_per_s": 0.0,
        "k2_eff_per_s": 0.0,
        "mat_gain": 20.0,
        "c_hat": 0.022708984091877937,
        "c_hat_current": 0.022711240598194588
      }
    }
  },
  {
    "frame": 9,
    "timestep": 7668,
    "time": 0.15,
    "ee_pos_m": [
      -0.008020497858524323,
      0.11243392527103424,
      -0.0015417147660627961
    ],
    "ee_normal": [
      0.0,
      0.9999990463256836,
      0.0
    ],
    "knife": {
      "y_anim": 0.06865402311086655,
      "z_offset": 0.0009587852982804179
    },
    "relative_eef_force": 107.18755841255188,
    "force_world_N": {
      "x": -0.03431866690516472,
      "y": -2.5858314037323,
      "z": -1.5312508344650269,
      "norm": 3.005401134490967
    },
    "force_normalized": {
      "x": -0.011418997310101986,
      "y": -0.8603947758674622,
      "z": -0.5094996690750122
    },
    "scales": {
      "dx": 0.004166666883975267,
      "dt": 1.956452385842877e-05,
      "E": 1200000.0,
      "vcap_dx_over_dt": 212.97052328621774
    },
    "telemetry": {
      "material": {
        "E_Pa": 1200000.0,
        "sigma_y_Pa": 50000.0,
        "E_ref_Pa": 300000.0,
        "sigma_ref_Pa": 5000.0
      },
      "knife_resistance": {
        "k2_base_per_s": 0.0,
        "k2_eff_per_s": 0.0,
        "mat_gain": 20.0,
        "c_hat": 0.024644408375024796,
        "c_hat_current": 0.024643358948993686
      }
    }
  },
  {
    "frame": 10,
    "timestep": 8520,
    "time": 0.16666666666666666,
    "ee_pos_m": [
      -0.008020497858524323,
      0.10910128057003021,
      -0.0015417147660627961
    ],
    "ee_normal": [
      0.0,
      0.9999990463256836,
      0.0
    ],
    "knife": {
      "y_anim": 0.06532137840986252,
      "z_offset": 0.0009587852982804179
    },
    "relative_eef_force": 170.59137105941772,
    "force_world_N": {
      "x": -0.054129526019096375,
      "y": -4.099973678588867,
      "z": -2.4370195865631104,
      "norm": 4.769883155822754
    },
    "force_normalized": {
      "x": -0.011348186992108822,
      "y": -0.8595543503761292,
      "z": -0.5109180808067322
    },
    "scales": {
      "dx": 0.004166666883975267,
      "dt": 1.956452385842877e-05,
      "E": 1200000.0,
      "vcap_dx_over_dt": 212.97052328621774
    },
    "telemetry": {
      "material": {
        "E_Pa": 1200000.0,
        "sigma_y_Pa": 50000.0,
        "E_ref_Pa": 300000.0,
        "sigma_ref_Pa": 5000.0
      },
      "knife_resistance": {
        "k2_base_per_s": 0.0,
        "k2_eff_per_s": 0.0,
        "mat_gain": 20.0,
        "c_hat": 0.030160734429955482,
        "c_hat_current": 0.030149949744448987
      }
    }
  },
  {
    "frame": 11,
    "timestep": 9372,
    "time": 0.18333333333333332,
    "ee_pos_m": [
      -0.008020497858524323,
      0.10576863586902618,
      -0.0015417147660627961
    ],
    "ee_normal": [
      0.0,
      0.9999990463256836,
      0.0
    ],
    "knife": {
      "y_anim": 0.06198873370885849,
      "z_offset": 0.0009587852982804179
    },
    "relative_eef_force": 233.00962209701538,
    "force_world_N": {
      "x": -0.07417159527540207,
      "y": -5.66541051864624,
      "z": -3.3287088871002197,
      "norm": 6.571353912353516
    },
    "force_normalized": {
      "x": -0.011287109926342964,
      "y": -0.862137496471405,
      "z": -0.5065484046936035
    },
    "scales": {
      "dx": 0.004166666883975267,
      "dt": 1.956452385842877e-05,
      "E": 1200000.0,
      "vcap_dx_over_dt": 212.97052328621774
    },
    "telemetry": {
      "material": {
        "E_Pa": 1200000.0,
        "sigma_y_Pa": 50000.0,
        "E_ref_Pa": 300000.0,
        "sigma_ref_Pa": 5000.0
      },
      "knife_resistance": {
        "k2_base_per_s": 0.0,
        "k2_eff_per_s": 0.0,
        "mat_gain": 20.0,
        "c_hat": 0.03429420664906502,
        "c_hat_current": 0.03429537380252844
      }
    }
  },
  {
    "frame": 12,
    "timestep": 10224,
    "time": 0.19999999999999998,
    "ee_pos_m": [
      -0.008020497858524323,
      0.10243599116802216,
      -0.0015417147660627961
    ],
    "ee_normal": [
      0.0,
      0.9999990463256836,
      0.0
    ],
    "knife": {
      "y_anim": 0.05865608900785446,
      "z_offset": 0.0009587852982804179
    },
    "relative_eef_force": 298.8296699523926,
    "force_world_N": {
      "x": -0.09556007385253906,
      "y": -7.381199359893799,
      "z": -4.26899528503418,
      "norm": 8.527342796325684
    },
    "force_normalized": {
      "x": -0.011206313036382198,
      "y": -0.8655919432640076,
      "z": -0.5006243586540222
    },
    "scales": {
      "dx": 0.004166666883975267,
      "dt": 1.956452385842877e-05,
      "E": 1200000.0,
      "vcap_dx_over_dt": 212.97052328621774
    },
    "telemetry": {
      "material": {
        "E_Pa": 1200000.0,
        "sigma_y_Pa": 50000.0,
        "E_ref_Pa": 300000.0,
        "sigma_ref_Pa": 5000.0
      },
      "knife_resistance": {
        "k2_base_per_s": 0.0,
        "k2_eff_per_s": 0.0,
        "mat_gain": 20.0,
        "c_hat": 0.03437303751707077,
        "c_hat_current": 0.034364369633160065
      }
    }
  },
  {
    "frame": 13,
    "timestep": 11076,
    "time": 0.21666666666666665,
    "ee_pos_m": [
      -0.008020497858524323,
      0.09910334646701813,
      -0.0015417147660627961
    ],
    "ee_normal": [
      0.0,
      0.9999990463256836,
      0.0
    ],
    "knife": {
      "y_anim": 0.05532344430685043,
      "z_offset": 0.0009587852982804179
    },
    "relative_eef_force": 385.97044944763184,
    "force_world_N": {
      "x": -0.12663646042346954,
      "y": -9.804303169250488,
      "z": -5.513863563537598,
      "norm": 11.249137878417969
    },
    "force_normalized": {
      "x": -0.01125743705779314,
      "y": -0.8715603947639465,
      "z": -0.4901587665081024
    },
    "scales": {
      "dx": 0.004166666883975267,
      "dt": 1.956452385842877e-05,
      "E": 1200000.0,
      "vcap_dx_over_dt": 212.97052328621774
    },
    "telemetry": {
      "material": {
        "E_Pa": 1200000.0,
        "sigma_y_Pa": 50000.0,
        "E_ref_Pa": 300000.0,
        "sigma_ref_Pa": 5000.0
      },
      "knife_resistance": {
        "k2_base_per_s": 0.0,
        "k2_eff_per_s": 0.0,
        "mat_gain": 20.0,
        "c_hat": 0.0384083166718483,
        "c_hat_current": 0.0384037235166808
      }
    }
  },
  {
    "frame": 14,
    "timestep": 11928,
    "time": 0.2333333333333333,
    "ee_pos_m": [
      -0.008020497858524323,
      0.0957707017660141,
      -0.0015417147660627961
    ],
    "ee_normal": [
      0.0,
      0.9999990463256836,
      0.0
    ],
    "knife": {
      "y_anim": 0.051990799605846405,
      "z_offset": 0.0009587852982804179
    },
    "relative_eef_force": 440.04348278045654,
    "force_world_N": {
      "x": -0.14447808265686035,
      "y": -11.513651847839355,
      "z": -6.286335468292236,
      "norm": 13.118806838989258
    },
    "force_normalized": {
      "x": -0.011013050563633442,
      "y": -0.8776447176933289,
      "z": -0.47918501496315
    },
    "scales": {
      "dx": 0.004166666883975267,
      "dt": 1.956452385842877e-05,
      "E": 1200000.0,
      "vcap_dx_over_dt": 212.97052328621774
    },
    "telemetry": {
      "material": {
        "E_Pa": 1200000.0,
        "sigma_y_Pa": 50000.0,
        "E_ref_Pa": 300000.0,
        "sigma_ref_Pa": 5000.0
      },
      "knife_resistance": {
        "k2_base_per_s": 0.0,
        "k2_eff_per_s": 0.0,
        "mat_gain": 20.0,
        "c_hat": 0.04595767334103584,
        "c_hat_current": 0.04596226458063483
      }
    }
  },
  {
    "frame": 15,
    "timestep": 12780,
    "time": 0.24999999999999997,
    "ee_pos_m": [
      -0.008020497858524323,
      0.09243805706501007,
      -0.0015417147660627961
    ],
    "ee_normal": [
      0.0,
      0.9999990463256836,
      0.0
    ],
    "knife": {
      "y_anim": 0.04865815490484238,
      "z_offset": 0.0009587852982804179
    },
    "relative_eef_force": 479.01426792144775,
    "force_world_N": {
      "x": -0.15707668662071228,
      "y": -12.946547508239746,
      "z": -6.8430609703063965,
      "norm": 14.644633293151855
    },
    "force_normalized": {
      "x": -0.01072588749229908,
      "y": -0.8840472102165222,
      "z": -0.4672743082046509
    },
    "scales": {
      "dx": 0.004166666883975267,
      "dt": 1.956452385842877e-05,
      "E": 1200000.0,
      "vcap_dx_over_dt": 212.97052328621774
    },
    "telemetry": {
      "material": {
        "E_Pa": 1200000.0,
        "sigma_y_Pa": 50000.0,
        "E_ref_Pa": 300000.0,
        "sigma_ref_Pa": 5000.0
      },
      "knife_resistance": {
        "k2_base_per_s": 0.0,
        "k2_eff_per_s": 0.0,
        "mat_gain": 20.0,
        "c_hat": 0.07167521119117737,
        "c_hat_current": 0.07009745457169425
      }
    }
  },
  {
    "frame": 16,
    "timestep": 13632,
    "time": 0.26666666666666666,
    "ee_pos_m": [
      -0.008020497858524323,
      0.08910541236400604,
      -0.0015417147660627961
    ],
    "ee_normal": [
      0.0,
      0.9999990463256836,
      0.0
    ],
    "knife": {
      "y_anim": 0.04532551020383835,
      "z_offset": 0.0009587852982804179
    },
    "relative_eef_force": 510.3558397293091,
    "force_world_N": {
      "x": -0.16786353290081024,
      "y": -14.408293724060059,
      "z": -7.290797710418701,
      "norm": 16.148773193359375
    },
    "force_normalized": {
      "x": -0.010394816286861897,
      "y": -0.8922221660614014,
      "z": -0.4514768719673157
    },
    "scales": {
      "dx": 0.004166666883975267,
      "dt": 1.956452385842877e-05,
      "E": 1200000.0,
      "vcap_dx_over_dt": 212.97052328621774
    },
    "telemetry": {
      "material": {
        "E_Pa": 1200000.0,
        "sigma_y_Pa": 50000.0,
        "E_ref_Pa": 300000.0,
        "sigma_ref_Pa": 5000.0
      },
      "knife_resistance": {
        "k2_base_per_s": 0.0,
        "k2_eff_per_s": 0.0,
        "mat_gain": 20.0,
        "c_hat": 0.06153009831905365,
        "c_hat_current": 0.061533559398018335
      }
    }
  },
  {
    "frame": 17,
    "timestep": 14483,
    "time": 0.2833333333333333,
    "ee_pos_m": [
      -0.008020497858524323,
      0.0857766717672348,
      -0.0015417147660627961
    ],
    "ee_normal": [
      0.0,
      0.9999990463256836,
      0.0
    ],
    "knife": {
      "y_anim": 0.041996777057647705,
      "z_offset": 0.0009587852982804179
    },
    "relative_eef_force": 559.76881980896,
    "force_world_N": {
      "x": -0.17639560997486115,
      "y": -16.407930374145508,
      "z": -7.996697425842285,
      "norm": 18.253726959228516
    },
    "force_normalized": {
      "x": -0.009663539007306099,
      "y": -0.8988811373710632,
      "z": -0.43808573484420776
    },
    "scales": {
      "dx": 0.004166666883975267,
      "dt": 1.956452385842877e-05,
      "E": 1200000.0,
      "vcap_dx_over_dt": 212.97052328621774
    },
    "telemetry": {
      "material": {
        "E_Pa": 1200000.0,
        "sigma_y_Pa": 50000.0,
        "E_ref_Pa": 300000.0,
        "sigma_ref_Pa": 5000.0
      },
      "knife_resistance": {
        "k2_base_per_s": 0.0,
        "k2_eff_per_s": 0.0,
        "mat_gain": 20.0,
        "c_hat": 0.06641088426113129,
        "c_hat_current": 0.06640436885527373
      }
    }
  },
  {
    "frame": 18,
    "timestep": 15335,
    "time": 0.3,
    "ee_pos_m": [
      -0.008020497858524323,
      0.08244402706623077,
      -0.0015417147660627961
    ],
    "ee_normal": [
      0.0,
      0.9999990463256836,
      0.0
    ],
    "knife": {
      "y_anim": 0.03866413235664368,
      "z_offset": 0.0009587852982804179
    },
    "relative_eef_force": 611.0718631744385,
    "force_world_N": {
      "x": -0.1910928636789322,
      "y": -18.185306549072266,
      "z": -8.729598045349121,
      "norm": 20.172948837280273
    },
    "force_normalized": {
      "x": -0.009472728706896305,
      "y": -0.9014699459075928,
      "z": -0.4327378273010254
    },
    "scales": {
      "dx": 0.004166666883975267,
      "dt": 1.956452385842877e-05,
      "E": 1200000.0,
      "vcap_dx_over_dt": 212.97052328621774
    },
    "telemetry": {
      "material": {
        "E_Pa": 1200000.0,
        "sigma_y_Pa": 50000.0,
        "E_ref_Pa": 300000.0,
        "sigma_ref_Pa": 5000.0
      },
      "knife_resistance": {
        "k2_base_per_s": 0.0,
        "k2_eff_per_s": 0.0,
        "mat_gain": 20.0,
        "c_hat": 0.06652955710887909,
        "c_hat_current": 0.0665373132113246
      }
    }
  },
  {
    "frame": 19,
    "timestep": 16187,
    "time": 0.31666666666666665,
    "ee_pos_m": [
      -0.008020497858524323,
      0.07911138236522675,
      -0.0015417147660627961
    ],
    "ee_normal": [
      0.0,
      0.9999990463256836,
      0.0
    ],
    "knife": {
      "y_anim": 0.03533148765563965,
      "z_offset": 0.0009587852982804179
    },
    "relative_eef_force": 655.708065032959,
    "force_world_N": {
      "x": -0.18549534678459167,
      "y": -19.903390884399414,
      "z": -9.367258071899414,
      "norm": 21.998294830322266
    },
    "force_normalized": {
      "x": -0.008432259783148766,
      "y": -0.9047697186470032,
      "z": -0.42581745982170105
    },
    "scales": {
      "dx": 0.004166666883975267,
      "dt": 1.956452385842877e-05,
      "E": 1200000.0,
      "vcap_dx_over_dt": 212.97052328621774
    },
    "telemetry": {
      "material": {
        "E_Pa": 1200000.0,
        "sigma_y_Pa": 50000.0,
        "E_ref_Pa": 300000.0,
        "sigma_ref_Pa": 5000.0
      },
      "knife_resistance": {
        "k2_base_per_s": 0.0,
        "k2_eff_per_s": 0.0,
        "mat_gain": 20.0,
        "c_hat": 0.0679597333073616,
        "c_hat_current": 0.06789137917710886
      }
    }
  },
  {
    "frame": 20,
    "timestep": 17039,
    "time": 0.3333333333333333,
    "ee_pos_m": [
      -0.008020497858524323,
      0.07577873766422272,
      -0.0015417147660627961
    ],
    "ee_normal": [
      0.0,
      0.9999990463256836,
      0.0
    ],
    "knife": {
      "y_anim": 0.03199884295463562,
      "z_offset": 0.0009587852982804179
    },
    "relative_eef_force": 680.8695888519287,
    "force_world_N": {
      "x": -0.20743364095687866,
      "y": -21.07277488708496,
      "z": -9.72670841217041,
      "norm": 23.210208892822266
    },
    "force_normalized": {
      "x": -0.008937172591686249,
      "y": -0.9079097509384155,
      "z": -0.4190702736377716
    },
    "scales": {
      "dx": 0.004166666883975267,
      "dt": 1.956452385842877e-05,
      "E": 1200000.0,
      "vcap_dx_over_dt": 212.97052328621774
    },
    "telemetry": {
      "material": {
        "E_Pa": 1200000.0,
        "sigma_y_Pa": 50000.0,
        "E_ref_Pa": 300000.0,
        "sigma_ref_Pa": 5000.0
      },
      "knife_resistance": {
        "k2_base_per_s": 0.0,
        "k2_eff_per_s": 0.0,
        "mat_gain": 20.0,
        "c_hat": 0.06968608498573303,
        "c_hat_current": 0.06970997634099671
      }
    }
  },
  {
    "frame": 21,
    "timestep": 17891,
    "time": 0.35,
    "ee_pos_m": [
      -0.008020497858524323,
      0.0724448710680008,
      -0.0015417147660627961
    ],
    "ee_normal": [
      0.0,
      0.9999990463256836,
      0.0
    ],
    "knife": {
      "y_anim": 0.02866496704518795,
      "z_offset": 0.0009587852982804179
    },
    "relative_eef_force": 704.9880313873291,
    "force_world_N": {
      "x": -0.20870739221572876,
      "y": -22.300338745117188,
      "z": -10.071257591247559,
      "norm": 24.469961166381836
    },
    "force_normalized": {
      "x": -0.008529126644134521,
      "y": -0.911335289478302,
      "z": -0.41157636046409607
    },
    "scales": {
      "dx": 0.004166666883975267,
      "dt": 1.956452385842877e-05,
      "E": 1200000.0,
      "vcap_dx_over_dt": 212.97052328621774
    },
    "telemetry": {
      "material": {
        "E_Pa": 1200000.0,
        "sigma_y_Pa": 50000.0,
        "E_ref_Pa": 300000.0,
        "sigma_ref_Pa": 5000.0
      },
      "knife_resistance": {
        "k2_base_per_s": 0.0,
        "k2_eff_per_s": 0.0,
        "mat_gain": 20.0,
        "c_hat": 0.07739970833063126,
        "c_hat_current": 0.07740018873978832
      }
    }
  },
  {
    "frame": 22,
    "timestep": 18743,
    "time": 0.36666666666666664,
    "ee_pos_m": [
      -0.008020497858524323,
      0.06911063194274902,
      -0.0015417147660627961
    ],
    "ee_normal": [
      0.0,
      0.9999990463256836,
      0.0
    ],
    "knife": {
      "y_anim": 0.025330735370516777,
      "z_offset": 0.0009587852982804179
    },
    "relative_eef_force": 752.2511291503906,
    "force_world_N": {
      "x": -0.22176815569400787,
      "y": -23.958763122558594,
      "z": -10.746444702148438,
      "norm": 26.259431838989258
    },
    "force_normalized": {
      "x": -0.008445275947451591,
      "y": -0.912386953830719,
      "z": -0.40924131870269775
    },
    "scales": {
      "dx": 0.004166666883975267,
      "dt": 1.956452385842877e-05,
      "E": 1200000.0,
      "vcap_dx_over_dt": 212.97052328621774
    },
    "telemetry": {
      "material": {
        "E_Pa": 1200000.0,
        "sigma_y_Pa": 50000.0,
        "E_ref_Pa": 300000.0,
        "sigma_ref_Pa": 5000.0
      },
      "knife_resistance": {
        "k2_base_per_s": 0.0,
        "k2_eff_per_s": 0.0,
        "mat_gain": 20.0,
        "c_hat": 0.07805204391479492,
        "c_hat_current": 0.07805523172056686
      }
    }
  },
  {
    "frame": 23,
    "timestep": 19595,
    "time": 0.3833333333333333,
    "ee_pos_m": [
      -0.008020497858524323,
      0.06577640026807785,
      -0.0015417147660627961
    ],
    "ee_normal": [
      0.0,
      0.9999990463256836,
      0.0
    ],
    "knife": {
      "y_anim": 0.021996503695845604,
      "z_offset": 0.0009587852982804179
    },
    "relative_eef_force": 809.8953723907471,
    "force_world_N": {
      "x": -0.23066572844982147,
      "y": -26.03240394592285,
      "z": -11.569933891296387,
      "norm": 28.4886417388916
    },
    "force_normalized": {
      "x": -0.00809676107019186,
      "y": -0.9137818813323975,
      "z": -0.40612444281578064
    },
    "scales": {
      "dx": 0.004166666883975267,
      "dt": 1.956452385842877e-05,
      "E": 1200000.0,
      "vcap_dx_over_dt": 212.97052328621774
    },
    "telemetry": {
      "material": {
        "E_Pa": 1200000.0,
        "sigma_y_Pa": 50000.0,
        "E_ref_Pa": 300000.0,
        "sigma_ref_Pa": 5000.0
      },
      "knife_resistance": {
        "k2_base_per_s": 0.0,
        "k2_eff_per_s": 0.0,
        "mat_gain": 20.0,
        "c_hat": 0.08042546361684799,
        "c_hat_current": 0.08040772374595256
      }
    }
  },
  {
    "frame": 24,
    "timestep": 20447,
    "time": 0.39999999999999997,
    "ee_pos_m": [
      -0.008020497858524323,
      0.06244216859340668,
      -0.0015417147660627961
    ],
    "ee_normal": [
      0.0,
      0.9999990463256836,
      0.0
    ],
    "knife": {
      "y_anim": 0.01866227202117443,
      "z_offset": 0.0009587852982804179
    },
    "relative_eef_force": 840.0527381896973,
    "force_world_N": {
      "x": -0.24448083341121674,
      "y": -27.33725929260254,
      "z": -12.000753402709961,
      "norm": 29.856386184692383
    },
    "force_normalized": {
      "x": -0.008188560605049133,
      "y": -0.9156252145767212,
      "z": -0.40194928646087646
    },
    "scales": {
      "dx": 0.004166666883975267,
      "dt": 1.956452385842877e-05,
      "E": 1200000.0,
      "vcap_dx_over_dt": 212.97052328621774
    },
    "telemetry": {
      "material": {
        "E_Pa": 1200000.0,
        "sigma_y_Pa": 50000.0,
        "E_ref_Pa": 300000.0,
        "sigma_ref_Pa": 5000.0
      },
      "knife_resistance": {
        "k2_base_per_s": 0.0,
        "k2_eff_per_s": 0.0,
        "mat_gain": 20.0,
        "c_hat": 0.0841224417090416,
        "c_hat_current": 0.08407802302236475
      }
    }
  },
  {
    "frame": 25,
    "timestep": 21299,
    "time": 0.41666666666666663,
    "ee_pos_m": [
      -0.008020497858524323,
      0.05910801142454147,
      -0.0015417147660627961
    ],
    "ee_normal": [
      0.0,
      0.9999990463256836,
      0.0
    ],
    "knife": {
      "y_anim": 0.015328111127018929,
      "z_offset": 0.0009587852982804179
    },
    "relative_eef_force": 838.2739925384521,
    "force_world_N": {
      "x": -0.22528423368930817,
      "y": -27.907135009765625,
      "z": -11.975342750549316,
      "norm": 30.368864059448242
    },
    "force_normalized": {
      "x": -0.007418263237923384,
      "y": -0.9189390540122986,
      "z": -0.39432963728904724
    },
    "scales": {
      "dx": 0.004166666883975267,
      "dt": 1.956452385842877e-05,
      "E": 1200000.0,
      "vcap_dx_over_dt": 212.97052328621774
    },
    "telemetry": {
      "material": {
        "E_Pa": 1200000.0,
        "sigma_y_Pa": 50000.0,
        "E_ref_Pa": 300000.0,
        "sigma_ref_Pa": 5000.0
      },
      "knife_resistance": {
        "k2_base_per_s": 0.0,
        "k2_eff_per_s": 0.0,
        "mat_gain": 20.0,
        "c_hat": 0.08173425495624542,
        "c_hat_current": 0.08156803460365925
      }
    }
  },
  {
    "frame": 26,
    "timestep": 22150,
    "time": 0.4333333333333333,
    "ee_pos_m": [
      -0.008020497858524323,
      0.05577848479151726,
      -0.0015417147660627961
    ],
    "ee_normal": [
      0.0,
      0.9999990463256836,
      0.0
    ],
    "knife": {
      "y_anim": 0.011998585425317287,
      "z_offset": 0.0009587852982804179
    },
    "relative_eef_force": 848.77610206604,
    "force_world_N": {
      "x": -0.245175302028656,
      "y": -28.354164123535156,
      "z": -12.125372886657715,
      "norm": 30.838993072509766
    },
    "force_normalized": {
      "x": -0.007950171828269958,
      "y": -0.9194257259368896,
      "z": -0.393183171749115
    },
    "scales": {
      "dx": 0.004166666883975267,
      "dt": 1.956452385842877e-05,
      "E": 1200000.0,
      "vcap_dx_over_dt": 212.97052328621774
    },
    "telemetry": {
      "material": {
        "E_Pa": 1200000.0,
        "sigma_y_Pa": 50000.0,
        "E_ref_Pa": 300000.0,
        "sigma_ref_Pa": 5000.0
      },
      "knife_resistance": {
        "k2_base_per_s": 0.0,
        "k2_eff_per_s": 0.0,
        "mat_gain": 20.0,
        "c_hat": 0.09695259481668472,
        "c_hat_current": 0.09706754765705243
      }
    }
  },
  {
    "frame": 27,
    "timestep": 23002,
    "time": 0.44999999999999996,
    "ee_pos_m": [
      -0.008020497858524323,
      0.05244504660367966,
      -0.0015417147660627961
    ],
    "ee_normal": [
      0.0,
      0.9999990463256836,
      0.0
    ],
    "knife": {
      "y_anim": 0.008665147237479687,
      "z_offset": 0.0009587852982804179
    },
    "relative_eef_force": 849.1089534759521,
    "force_world_N": {
      "x": -0.21908538043498993,
      "y": -28.577375411987305,
      "z": -12.130127906799316,
      "norm": 31.046005249023438
    },
    "force_normalized": {
      "x": -0.007056797854602337,
      "y": -0.9204847812652588,
      "z": -0.3907146155834198
    },
    "scales": {
      "dx": 0.004166666883975267,
      "dt": 1.956452385842877e-05,
      "E": 1200000.0,
      "vcap_dx_over_dt": 212.97052328621774
    },
    "telemetry": {
      "material": {
        "E_Pa": 1200000.0,
        "sigma_y_Pa": 50000.0,
        "E_ref_Pa": 300000.0,
        "sigma_ref_Pa": 5000.0
      },
      "knife_resistance": {
        "k2_base_per_s": 0.0,
        "k2_eff_per_s": 0.0,
        "mat_gain": 20.0,
        "c_hat": 0.09294585138559341,
        "c_hat_current": 0.09296273233596705
      }
    }
  },
  {
    "frame": 28,
    "timestep": 23854,
    "time": 0.4666666666666666,
    "ee_pos_m": [
      -0.008020497858524323,
      0.04911131411790848,
      -0.0015417147660627961
    ],
    "ee_normal": [
      0.0,
      0.9999990463256836,
      0.0
    ],
    "knife": {
      "y_anim": 0.005331413354724646,
      "z_offset": 0.0009587852982804179
    },
    "relative_eef_force": 846.9135761260986,
    "force_world_N": {
      "x": -0.18742702901363373,
      "y": -28.8931884765625,
      "z": -12.09876537322998,
      "norm": 31.32461929321289
    },
    "force_normalized": {
      "x": -0.005983377806842327,
      "y": -0.9223795533180237,
      "z": -0.3862382173538208
    },
    "scales": {
      "dx": 0.004166666883975267,
      "dt": 1.956452385842877e-05,
      "E": 1200000.0,
      "vcap_dx_over_dt": 212.97052328621774
    },
    "telemetry": {
      "material": {
        "E_Pa": 1200000.0,
        "sigma_y_Pa": 50000.0,
        "E_ref_Pa": 300000.0,
        "sigma_ref_Pa": 5000.0
      },
      "knife_resistance": {
        "k2_base_per_s": 0.0,
        "k2_eff_per_s": 0.0,
        "mat_gain": 20.0,
        "c_hat": 0.08233867585659027,
        "c_hat_current": 0.08223871207612232
      }
    }
  },
  {
    "frame": 29,
    "timestep": 24706,
    "time": 0.4833333333333333,
    "ee_pos_m": [
      -0.008020497858524323,
      0.04577747732400894,
      -0.0015417147660627961
    ],
    "ee_normal": [
      0.0,
      0.9999990463256836,
      0.0
    ],
    "knife": {
      "y_anim": 0.0019975784234702587,
      "z_offset": 0.0009587852982804179
    },
    "relative_eef_force": 840.9072303771973,
    "force_world_N": {
      "x": -0.459125816822052,
      "y": -29.39372444152832,
      "z": -12.012960433959961,
      "norm": 31.757097244262695
    },
    "force_normalized": {
      "x": -0.01445742417126894,
      "y": -0.9255796670913696,
      "z": -0.37827640771865845
    },
    "scales": {
      "dx": 0.004166666883975267,
      "dt": 1.956452385842877e-05,
      "E": 1200000.0,
      "vcap_dx_over_dt": 212.97052328621774
    },
    "telemetry": {
      "material": {
        "E_Pa": 1200000.0,
        "sigma_y_Pa": 50000.0,
        "E_ref_Pa": 300000.0,
        "sigma_ref_Pa": 5000.0
      },
      "knife_resistance": {
        "k2_base_per_s": 0.0,
        "k2_eff_per_s": 0.0,
        "mat_gain": 20.0,
        "c_hat": 0.07861609756946564,
        "c_hat_current": 0.07842485566882104
      }
    }
  },
  {
    "frame": 30,
    "timestep": 25558,
    "time": 0.49999999999999994,
    "ee_pos_m": [
      -0.008020497858524323,
      0.04244367033243179,
      -0.0015417147660627961
    ],
    "ee_normal": [
      0.0,
      0.9999990463256836,
      0.0
    ],
    "knife": {
      "y_anim": -0.001336229033768177,
      "z_offset": 0.0009587852982804179
    },
    "relative_eef_force": 853.9902400970459,
    "force_world_N": {
      "x": -0.5057412385940552,
      "y": -30.55718994140625,
      "z": -12.199860572814941,
      "norm": 32.90644836425781
    },
    "force_normalized": {
      "x": -0.015369061380624771,
      "y": -0.9286079406738281,
      "z": -0.3707437515258789
    },
    "scales": {
      "dx": 0.004166666883975267,
      "dt": 1.956452385842877e-05,
      "E": 1200000.0,
      "vcap_dx_over_dt": 212.97052328621774
    },
    "telemetry": {
      "material": {
        "E_Pa": 1200000.0,
        "sigma_y_Pa": 50000.0,
        "E_ref_Pa": 300000.0,
        "sigma_ref_Pa": 5000.0
      },
      "knife_resistance": {
        "k2_base_per_s": 0.0,
        "k2_eff_per_s": 0.0,
        "mat_gain": 20.0,
        "c_hat": 0.11426474899053574,
        "c_hat_current": 0.11072605453494935
      }
    }
  },
  {
    "frame": 31,
    "timestep": 26410,
    "time": 0.5166666666666666,
    "ee_pos_m": [
      -0.008020497858524323,
      0.03910983353853226,
      -0.0015417147660627961
    ],
    "ee_normal": [
      0.0,
      0.9999990463256836,
      0.0
    ],
    "knife": {
      "y_anim": -0.004670063965022564,
      "z_offset": 0.0009587852982804179
    },
    "relative_eef_force": 961.0372161865234,
    "force_world_N": {
      "x": -1.415058970451355,
      "y": -35.30467987060547,
      "z": -13.729103088378906,
      "norm": 37.90660858154297
    },
    "force_normalized": {
      "x": -0.03733013942837715,
      "y": -0.9313594698905945,
      "z": -0.3621823191642761
    },
    "scales": {
      "dx": 0.004166666883975267,
      "dt": 1.956452385842877e-05,
      "E": 1200000.0,
      "vcap_dx_over_dt": 212.97052328621774
    },
    "telemetry": {
      "material": {
        "E_Pa": 1200000.0,
        "sigma_y_Pa": 50000.0,
        "E_ref_Pa": 300000.0,
        "sigma_ref_Pa": 5000.0
      },
      "knife_resistance": {
        "k2_base_per_s": 0.0,
        "k2_eff_per_s": 0.0,
        "mat_gain": 20.0,
        "c_hat": 0.15929585695266724,
        "c_hat_current": 0.16424853621751748
      }
    }
  },
  {
    "frame": 32,
    "timestep": 27262,
    "time": 0.5333333333333333,
    "ee_pos_m": [
      -0.008020497858524323,
      0.03577602282166481,
      -0.0015417147660627961
    ],
    "ee_normal": [
      0.0,
      0.9999990463256836,
      0.0
    ],
    "knife": {
      "y_anim": -0.00800387654453516,
      "z_offset": 0.0009587852982804179
    },
    "relative_eef_force": 855.2749824523926,
    "force_world_N": {
      "x": -0.65910404920578,
      "y": -31.548439025878906,
      "z": -12.21821403503418,
      "norm": 33.838191986083984
    },
    "force_normalized": {
      "x": -0.01947811059653759,
      "y": -0.9323322772979736,
      "z": -0.3610776364803314
    },
    "scales": {
      "dx": 0.004166666883975267,
      "dt": 1.956452385842877e-05,
      "E": 1200000.0,
      "vcap_dx_over_dt": 212.97052328621774
    },
    "telemetry": {
      "material": {
        "E_Pa": 1200000.0,
        "sigma_y_Pa": 50000.0,
        "E_ref_Pa": 300000.0,
        "sigma_ref_Pa": 5000.0
      },
      "knife_resistance": {
        "k2_base_per_s": 0.0,
        "k2_eff_per_s": 0.0,
        "mat_gain": 20.0,
        "c_hat": 0.5704729557037354,
        "c_hat_current": 0.3375271300651531
      }
    }
  },
  {
    "frame": 33,
    "timestep": 28114,
    "time": 0.55,
    "ee_pos_m": [
      -0.008020497858524323,
      0.03244258463382721,
      -0.0015417147660627961
    ],
    "ee_normal": [
      0.0,
      0.9999990463256836,
      0.0
    ],
    "knife": {
      "y_anim": -0.01133731473237276,
      "z_offset": 0.0009587852982804179
    },
    "relative_eef_force": 1206.368465423584,
    "force_world_N": {
      "x": -4.97733736038208,
      "y": -44.27200698852539,
      "z": -17.233835220336914,
      "norm": 47.76808166503906
    },
    "force_normalized": {
      "x": -0.10419797152280807,
      "y": -0.9268115162849426,
      "z": -0.36078140139579773
    },
    "scales": {
      "dx": 0.004166666883975267,
      "dt": 1.956452385842877e-05,
      "E": 1200000.0,
      "vcap_dx_over_dt": 212.97052328621774
    },
    "telemetry": {
      "material": {
        "E_Pa": 1200000.0,
        "sigma_y_Pa": 50000.0,
        "E_ref_Pa": 300000.0,
        "sigma_ref_Pa": 5000.0
      },
      "knife_resistance": {
        "k2_base_per_s": 0.0,
        "k2_eff_per_s": 0.0,
        "mat_gain": 20.0,
        "c_hat": 0.34939730167388916,
        "c_hat_current": 0.33879339594977104
      }
    }
  },
  {
    "frame": 34,
    "timestep": 28965,
    "time": 0.5666666666666668,
    "ee_pos_m": [
      -0.008020497858524323,
      0.029113058000802994,
      -0.0015417147660627961
    ],
    "ee_normal": [
      0.0,
      0.9999990463256836,
      0.0
    ],
    "knife": {
      "y_anim": -0.014666840434074402,
      "z_offset": 0.0009587852982804179
    },
    "relative_eef_force": 1078.503589630127,
    "force_world_N": {
      "x": -3.7482056617736816,
      "y": -40.31318283081055,
      "z": -15.407194137573242,
      "norm": 43.319549560546875
    },
    "force_normalized": {
      "x": -0.08652457594871521,
      "y": -0.9306002259254456,
      "z": -0.3556637763977051
    },
    "scales": {
      "dx": 0.004166666883975267,
      "dt": 1.956452385842877e-05,
      "E": 1200000.0,
      "vcap_dx_over_dt": 212.97052328621774
    },
    "telemetry": {
      "material": {
        "E_Pa": 1200000.0,
        "sigma_y_Pa": 50000.0,
        "E_ref_Pa": 300000.0,
        "sigma_ref_Pa": 5000.0
      },
      "knife_resistance": {
        "k2_base_per_s": 0.0,
        "k2_eff_per_s": 0.0,
        "mat_gain": 20.0,
        "c_hat": 0.22829098999500275,
        "c_hat_current": 0.22912646947589396
      }
    }
  },
  {
    "frame": 35,
    "timestep": 29817,
    "time": 0.5833333333333335,
    "ee_pos_m": [
      -0.008020497858524323,
      0.025779053568840027,
      -0.0015417147660627961
    ],
    "ee_normal": [
      0.0,
      0.9999990463256836,
      0.0
    ],
    "knife": {
      "y_anim": -0.01800084486603737,
      "z_offset": 0.0009587852982804179
    },
    "relative_eef_force": 1266.4364624023438,
    "force_world_N": {
      "x": 4.3418450355529785,
      "y": -45.76689910888672,
      "z": -18.091949462890625,
      "norm": 49.40424346923828
    },
    "force_normalized": {
      "x": 0.08788405358791351,
      "y": -0.9263758659362793,
      "z": -0.36620232462882996
    },
    "scales": {
      "dx": 0.004166666883975267,
      "dt": 1.956452385842877e-05,
      "E": 1200000.0,
      "vcap_dx_over_dt": 212.97052328621774
    },
    "telemetry": {
      "material": {
        "E_Pa": 1200000.0,
        "sigma_y_Pa": 50000.0,
        "E_ref_Pa": 300000.0,
        "sigma_ref_Pa": 5000.0
      },
      "knife_resistance": {
        "k2_base_per_s": 0.0,
        "k2_eff_per_s": 0.0,
        "mat_gain": 20.0,
        "c_hat": 0.5422356724739075,
        "c_hat_current": 0.5465951352421913
      }
    }
  },
  {
    "frame": 36,
    "timestep": 30669,
    "time": 0.6000000000000002,
    "ee_pos_m": [
      -0.008020497858524323,
      0.022444821894168854,
      -0.0015417147660627961
    ],
    "ee_normal": [
      0.0,
      0.9999990463256836,
      0.0
    ],
    "knife": {
      "y_anim": -0.021335076540708542,
      "z_offset": 0.0009587852982804179
    },
    "relative_eef_force": 1108.7325191497803,
    "force_world_N": {
      "x": 7.5758466720581055,
      "y": -45.47722625732422,
      "z": -15.839035987854004,
      "norm": 48.74881362915039
    },
    "force_normalized": {
      "x": 0.15540575981140137,
      "y": -0.9328888654708862,
      "z": -0.3249112069606781
    },
    "scales": {
      "dx": 0.004166666883975267,
      "dt": 1.956452385842877e-05,
      "E": 1200000.0,
      "vcap_dx_over_dt": 212.97052328621774
    },
    "telemetry": {
      "material": {
        "E_Pa": 1200000.0,
        "sigma_y_Pa": 50000.0,
        "E_ref_Pa": 300000.0,
        "sigma_ref_Pa": 5000.0
      },
      "knife_resistance": {
        "k2_base_per_s": 0.0,
        "k2_eff_per_s": 0.0,
        "mat_gain": 20.0,
        "c_hat": 0.6675217747688293,
        "c_hat_current": 1.0
      }
    }
  },
  {
    "frame": 37,
    "timestep": 31521,
    "time": 0.6166666666666669,
    "ee_pos_m": [
      -0.008020497858524323,
      0.01911059021949768,
      -0.0015417147660627961
    ],
    "ee_normal": [
      0.0,
      0.9999990463256836,
      0.0
    ],
    "knife": {
      "y_anim": -0.024669308215379715,
      "z_offset": 0.0009587852982804179
    },
    "relative_eef_force": 1011.3214111328125,
    "force_world_N": {
      "x": 6.680539131164551,
      "y": -51.118595123291016,
      "z": -14.44744873046875,
      "norm": 53.5394172668457
    },
    "force_normalized": {
      "x": 0.12477795779705048,
      "y": -0.9547842741012573,
      "z": -0.26984694600105286
    },
    "scales": {
      "dx": 0.004166666883975267,
      "dt": 1.956452385842877e-05,
      "E": 1200000.0,
      "vcap_dx_over_dt": 212.97052328621774
    },
    "telemetry": {
      "material": {
        "E_Pa": 1200000.0,
        "sigma_y_Pa": 50000.0,
        "E_ref_Pa": 300000.0,
        "sigma_ref_Pa": 5000.0
      },
      "knife_resistance": {
        "k2_base_per_s": 0.0,
        "k2_eff_per_s": 0.0,
        "mat_gain": 20.0,
        "c_hat": 1.0,
        "c_hat_current": 1.0
      }
    }
  },
  {
    "frame": 38,
    "timestep": 32373,
    "time": 0.6333333333333336,
    "ee_pos_m": [
      -0.008020497858524323,
      0.015776358544826508,
      -0.0015417147660627961
    ],
    "ee_normal": [
      0.0,
      0.9999990463256836,
      0.0
    ],
    "knife": {
      "y_anim": -0.028003539890050888,
      "z_offset": 0.0009587852982804179
    },
    "relative_eef_force": 1178.8627624511719,
    "force_world_N": {
      "x": -21.86093521118164,
      "y": -50.44215774536133,
      "z": -16.840896606445312,
      "norm": 57.497196197509766
    },
    "force_normalized": {
      "x": -0.38020873069763184,
      "y": -0.8772976994514465,
      "z": -0.2928994297981262
    },
    "scales": {
      "dx": 0.004166666883975267,
      "dt": 1.956452385842877e-05,
      "E": 1200000.0,
      "vcap_dx_over_dt": 212.97052328621774
    },
    "telemetry": {
      "material": {
        "E_Pa": 1200000.0,
        "sigma_y_Pa": 50000.0,
        "E_ref_Pa": 300000.0,
        "sigma_ref_Pa": 5000.0
      },
      "knife_resistance": {
        "k2_base_per_s": 0.0,
        "k2_eff_per_s": 0.0,
        "mat_gain": 20.0,
        "c_hat": 1.0,
        "c_hat_current": 1.0
      }
    }
  },
  {
    "frame": 39,
    "timestep": 33225,
    "time": 0.6500000000000004,
    "ee_pos_m": [
      -0.008020497858524323,
      0.012442167848348618,
      -0.0015417147660627961
    ],
    "ee_normal": [
      0.0,
      0.9999990463256836,
      0.0
    ],
    "knife": {
      "y_anim": -0.03133773058652878,
      "z_offset": 0.0009587852982804179
    },
    "relative_eef_force": 963.6215209960938,
    "force_world_N": {
      "x": -0.9645912647247314,
      "y": -34.04822540283203,
      "z": -13.766021728515625,
      "norm": 36.73847198486328
    },
    "force_normalized": {
      "x": -0.026255616918206215,
      "y": -0.9267730116844177,
      "z": -0.37470316886901855
    },
    "scales": {
      "dx": 0.004166666883975267,
      "dt": 1.956452385842877e-05,
      "E": 1200000.0,
      "vcap_dx_over_dt": 212.97052328621774
    },
    "telemetry": {
      "material": {
        "E_Pa": 1200000.0,
        "sigma_y_Pa": 50000.0,
        "E_ref_Pa": 300000.0,
        "sigma_ref_Pa": 5000.0
      },
      "knife_resistance": {
        "k2_base_per_s": 0.0,
        "k2_eff_per_s": 0.0,
        "mat_gain": 20.0,
        "c_hat": 0.26505935192108154,
        "c_hat_current": 0.2950817369178199
      }
    }
  },
  {
    "frame": 40,
    "timestep": 34077,
    "time": 0.6666666666666671,
    "ee_pos_m": [
      -0.008020497858524323,
      0.00910952314734459,
      -0.0015417147660627961
    ],
    "ee_normal": [
      0.0,
      0.9999990463256836,
      0.0
    ],
    "knife": {
      "y_anim": -0.034670375287532806,
      "z_offset": 0.0009587852982804179
    },
    "relative_eef_force": 728.781099319458,
    "force_world_N": {
      "x": -2.3402466773986816,
      "y": -27.95711898803711,
      "z": -10.411158561706543,
      "norm": 29.92439842224121
    },
    "force_normalized": {
      "x": -0.07820530235767365,
      "y": -0.9342583417892456,
      "z": -0.347915381193161
    },
    "scales": {
      "dx": 0.004166666883975267,
      "dt": 1.956452385842877e-05,
      "E": 1200000.0,
      "vcap_dx_over_dt": 212.97052328621774
    },
    "telemetry": {
      "material": {
        "E_Pa": 1200000.0,
        "sigma_y_Pa": 50000.0,
        "E_ref_Pa": 300000.0,
        "sigma_ref_Pa": 5000.0
      },
      "knife_resistance": {
        "k2_base_per_s": 0.0,
        "k2_eff_per_s": 0.0,
        "mat_gain": 20.0,
        "c_hat": 0.4852018356323242,
        "c_hat_current": 0.33675349140461197
      }
    }
  },
  {
    "frame": 41,
    "timestep": 34929,
    "time": 0.6833333333333338,
    "ee_pos_m": [
      -0.008020497858524323,
      0.016177091747522354,
      -0.0015417147660627961
    ],
    "ee_normal": [
      0.0,
      0.9999990463256836,
      0.0
    ],
    "knife": {
      "y_anim": -0.02760280668735504,
      "z_offset": 0.0009587852982804179
    },
    "relative_eef_force": -568.5507297515869,
    "force_world_N": {
      "x": -12.116814613342285,
      "y": -29.03472328186035,
      "z": 8.122153282165527,
      "norm": 32.49310302734375
    },
    "force_normalized": {
      "x": -0.3729042112827301,
      "y": -0.8935657143592834,
      "z": 0.24996545910835266
    },
    "scales": {
      "dx": 0.004166666883975267,
      "dt": 1.956452385842877e-05,
      "E": 1200000.0,
      "vcap_dx_over_dt": 212.97052328621774
    },
    "telemetry": {
      "material": {
        "E_Pa": 1200000.0,
        "sigma_y_Pa": 50000.0,
        "E_ref_Pa": 300000.0,
        "sigma_ref_Pa": 5000.0
      },
      "knife_resistance": {
        "k2_base_per_s": 0.0,
        "k2_eff_per_s": 0.0,
        "mat_gain": 20.0,
        "c_hat": 1.0,
        "c_hat_current": 0.31932200553425183
      }
    }
  },
  {
    "frame": 42,
    "timestep": 35781,
    "time": 0.7000000000000005,
    "ee_pos_m": [
      -0.008020497858524323,
      0.03284643962979317,
      -0.0015417147660627961
    ],
    "ee_normal": [
      0.0,
      0.9999990463256836,
      0.0
    ],
    "knife": {
      "y_anim": -0.010933458805084229,
      "z_offset": 0.0009587852982804179
    },
    "relative_eef_force": -1917.90678024292,
    "force_world_N": {
      "x": 7.872013092041016,
      "y": -36.373687744140625,
      "z": 27.39866828918457,
      "norm": 46.21364212036133
    },
    "force_normalized": {
      "x": 0.17033959925174713,
      "y": -0.7870768308639526,
      "z": 0.5928696990013123
    },
    "scales": {
      "dx": 0.004166666883975267,
      "dt": 1.956452385842877e-05,
      "E": 1200000.0,
      "vcap_dx_over_dt": 212.97052328621774
    },
    "telemetry": {
      "material": {
        "E_Pa": 1200000.0,
        "sigma_y_Pa": 50000.0,
        "E_ref_Pa": 300000.0,
        "sigma_ref_Pa": 5000.0
      },
      "knife_resistance": {
        "k2_base_per_s": 0.0,
        "k2_eff_per_s": 0.0,
        "mat_gain": 20.0,
        "c_hat": 0.029735619202256203,
        "c_hat_current": 0.03446456407915403
      }
    }
  },
  {
    "frame": 43,
    "timestep": 36632,
    "time": 0.7166666666666672,
    "ee_pos_m": [
      -0.008020497858524323,
      0.049495745450258255,
      -0.0015417147660627961
    ],
    "ee_normal": [
      0.0,
      0.9999990463256836,
      0.0
    ],
    "knife": {
      "y_anim": 0.005715847481042147,
      "z_offset": 0.0009587852982804179
    },
    "relative_eef_force": -1320.1218032836914,
    "force_world_N": {
      "x": 0.09399353712797165,
      "y": -16.54106903076172,
      "z": 18.858882904052734,
      "norm": 25.0853214263916
    },
    "force_normalized": {
      "x": 0.003746953560039401,
      "y": -0.6593923568725586,
      "z": 0.7517895698547363
    },
    "scales": {
      "dx": 0.004166666883975267,
      "dt": 1.956452385842877e-05,
      "E": 1200000.0,
      "vcap_dx_over_dt": 212.97052328621774
    },
    "telemetry": {
      "material": {
        "E_Pa": 1200000.0,
        "sigma_y_Pa": 50000.0,
        "E_ref_Pa": 300000.0,
        "sigma_ref_Pa": 5000.0
      },
      "knife_resistance": {
        "k2_base_per_s": 0.0,
        "k2_eff_per_s": 0.0,
        "mat_gain": 20.0,
        "c_hat": 0.015309284441173077,
        "c_hat_current": 0.015228976854299331
      }
    }
  },
  {
    "frame": 44,
    "timestep": 37484,
    "time": 0.733333333333334,
    "ee_pos_m": [
      -0.008020497858524323,
      0.06616484373807907,
      -0.0015417147660627961
    ],
    "ee_normal": [
      0.0,
      0.9999990463256836,
      0.0
    ],
    "knife": {
      "y_anim": 0.022384947165846825,
      "z_offset": 0.0009587852982804179
    },
    "relative_eef_force": -609.0413093566895,
    "force_world_N": {
      "x": 0.038958556950092316,
      "y": -7.425234317779541,
      "z": 8.700590133666992,
      "norm": 11.438352584838867
    },
    "force_normalized": {
      "x": 0.0034059586469084024,
      "y": -0.649152398109436,
      "z": 0.760650634765625
    },
    "scales": {
      "dx": 0.004166666883975267,
      "dt": 1.956452385842877e-05,
      "E": 1200000.0,
      "vcap_dx_over_dt": 212.97052328621774
    },
    "telemetry": {
      "material": {
        "E_Pa": 1200000.0,
        "sigma_y_Pa": 50000.0,
        "E_ref_Pa": 300000.0,
        "sigma_ref_Pa": 5000.0
      },
      "knife_resistance": {
        "k2_base_per_s": 0.0,
        "k2_eff_per_s": 0.0,
        "mat_gain": 20.0,
        "c_hat": 0.010727827437222004,
        "c_hat_current": 0.010708782387834676
      }
    }
  },
  {
    "frame": 45,
    "timestep": 38336,
    "time": 0.7500000000000007,
    "ee_pos_m": [
      -0.008020497858524323,
      0.08283441513776779,
      -0.0015417147660627961
    ],
    "ee_normal": [
      0.0,
      0.9999990463256836,
      0.0
    ],
    "knife": {
      "y_anim": 0.039054516702890396,
      "z_offset": 0.0009587852982804179
    },
    "relative_eef_force": -135.5868899822235,
    "force_world_N": {
      "x": 0.003917736932635307,
      "y": -2.3240771293640137,
      "z": 1.9369555711746216,
      "norm": 3.0254178047180176
    },
    "force_normalized": {
      "x": 0.0012949408264830709,
      "y": -0.7681838870048523,
      "z": 0.6402274370193481
    },
    "scales": {
      "dx": 0.004166666883975267,
      "dt": 1.956452385842877e-05,
      "E": 1200000.0,
      "vcap_dx_over_dt": 212.97052328621774
    },
    "telemetry": {
      "material": {
        "E_Pa": 1200000.0,
        "sigma_y_Pa": 50000.0,
        "E_ref_Pa": 300000.0,
        "sigma_ref_Pa": 5000.0
      },
      "knife_resistance": {
        "k2_base_per_s": 0.0,
        "k2_eff_per_s": 0.0,
        "mat_gain": 20.0,
        "c_hat": 0.027706164866685867,
        "c_hat_current": 0.02766975577951631
      }
    }
  },
  {
    "frame": 46,
    "timestep": 39188,
    "time": 0.7666666666666674,
    "ee_pos_m": [
      -0.008020497858524323,
      0.09950398653745651,
      -0.0015417147660627961
    ],
    "ee_normal": [
      0.0,
      0.9999990463256836,
      0.0
    ],
    "knife": {
      "y_anim": 0.05572408810257912,
      "z_offset": 0.0009587852982804179
    },
    "relative_eef_force": -12.26274624466896,
    "force_world_N": {
      "x": -0.002959221601486206,
      "y": -0.28813502192497253,
      "z": 0.17518208920955658,
      "norm": 0.33722394704818726
    },
    "force_normalized": {
      "x": -0.008775241672992706,
      "y": -0.8544322848320007,
      "z": 0.5194829702377319
    },
    "scales": {
      "dx": 0.004166666883975267,
      "dt": 1.956452385842877e-05,
      "E": 1200000.0,
      "vcap_dx_over_dt": 212.97052328621774
    },
    "telemetry": {
      "material": {
        "E_Pa": 1200000.0,
        "sigma_y_Pa": 50000.0,
        "E_ref_Pa": 300000.0,
        "sigma_ref_Pa": 5000.0
      },
      "knife_resistance": {
        "k2_base_per_s": 0.0,
        "k2_eff_per_s": 0.0,
        "mat_gain": 20.0,
        "c_hat": 0.06702620536088943,
        "c_hat_current": 0.005792958196798077
      }
    }
  },
  {
    "frame": 47,
    "timestep": 40040,
    "time": 0.7833333333333341,
    "ee_pos_m": [
      -0.008020497858524323,
      0.11617355793714523,
      -0.0015417147660627961
    ],
    "ee_normal": [
      0.0,
      0.9999990463256836,
      0.0
    ],
    "knife": {
      "y_anim": 0.07239365577697754,
      "z_offset": 0.0009587852982804179
    },
    "relative_eef_force": 0.27873469050973654,
    "force_world_N": {
      "x": 0.003500687889754772,
      "y": -0.010280614718794823,
      "z": -0.003981924150139093,
      "norm": 0.011568263173103333
    },
    "force_normalized": {
      "x": 0.3026113510131836,
      "y": -0.8886913061141968,
      "z": -0.34421107172966003
    },
    "scales": {
      "dx": 0.004166666883975267,
      "dt": 1.956452385842877e-05,
      "E": 1200000.0,
      "vcap_dx_over_dt": 212.97052328621774
    },
    "telemetry": {
      "material": {
        "E_Pa": 1200000.0,
        "sigma_y_Pa": 50000.0,
        "E_ref_Pa": 300000.0,
        "sigma_ref_Pa": 5000.0
      },
      "knife_resistance": {
        "k2_base_per_s": 0.0,
        "k2_eff_per_s": 0.0,
        "mat_gain": 20.0,
        "c_hat": 0.0,
        "c_hat_current": 0.0
      }
    }
  },
  {
    "frame": 48,
    "timestep": 40892,
    "time": 0.8000000000000008,
    "ee_pos_m": [
      -0.008020497858524323,
      0.13284313678741455,
      -0.0015417147660627961
    ],
    "ee_normal": [
      0.0,
      0.9999990463256836,
      0.0
    ],
    "knife": {
      "y_anim": 0.08906322717666626,
      "z_offset": 0.0009587852982804179
    },
    "relative_eef_force": 0.14080911176279187,
    "force_world_N": {
      "x": -0.0031285251025110483,
      "y": -0.004068335983902216,
      "z": -0.0020115587394684553,
      "norm": 0.005513294599950314
    },
    "force_normalized": {
      "x": -0.5674511194229126,
      "y": -0.7379137873649597,
      "z": -0.3648560345172882
    },
    "scales": {
      "dx": 0.004166666883975267,
      "dt": 1.956452385842877e-05,
      "E": 1200000.0,
      "vcap_dx_over_dt": 212.97052328621774
    },
    "telemetry": {
      "material": {
        "E_Pa": 1200000.0,
        "sigma_y_Pa": 50000.0,
        "E_ref_Pa": 300000.0,
        "sigma_ref_Pa": 5000.0
      },
      "knife_resistance": {
        "k2_base_per_s": 0.0,
        "k2_eff_per_s": 0.0,
        "mat_gain": 20.0,
        "c_hat": 0.0,
        "c_hat_current": 0.0
      }
    }
  },
  {
    "frame": 49,
    "timestep": 41744,
    "time": 0.8166666666666675,
    "ee_pos_m": [
      -0.008020497858524323,
      0.14101174473762512,
      -0.0015417147660627961
    ],
    "ee_normal": [
      0.0,
      0.9999990463256836,
      0.0
    ],
    "knife": {
      "y_anim": 0.09723184257745743,
      "z_offset": 0.0009587852982804179
    },
    "relative_eef_force": 0.0,
    "force_world_N": {
      "x": 0.0,
      "y": 0.0,
      "z": 0.0,
      "norm": 9.999999974752427e-07
    },
    "force_normalized": {
      "x": 0.0,
      "y": 0.0,
      "z": 0.0
    },
    "scales": {
      "dx": 0.004166666883975267,
      "dt": 1.956452385842877e-05,
      "E": 1200000.0,
      "vcap_dx_over_dt": 212.97052328621774
    },
    "telemetry": {
      "material": {
        "E_Pa": 1200000.0,
        "sigma_y_Pa": 50000.0,
        "E_ref_Pa": 300000.0,
        "sigma_ref_Pa": 5000.0
      },
      "knife_resistance": {
        "k2_base_per_s": 0.0,
        "k2_eff_per_s": 0.0,
        "mat_gain": 20.0,
        "c_hat": 0.0,
        "c_hat_current": 0.0
      }
    }
  },
  {
    "frame": 50,
    "timestep": 42596,
    "time": 0.8333333333333343,
    "ee_pos_m": [
      -0.008020497858524323,
      0.1376791000366211,
      -0.0015417147660627961
    ],
    "ee_normal": [
      0.0,
      0.9999990463256836,
      0.0
    ],
    "knife": {
      "y_anim": 0.0938991978764534,
      "z_offset": 0.0009587852982804179
    },
    "relative_eef_force": 0.0,
    "force_world_N": {
      "x": 0.0,
      "y": 0.0,
      "z": 0.0,
      "norm": 9.999999974752427e-07
    },
    "force_normalized": {
      "x": 0.0,
      "y": 0.0,
      "z": 0.0
    },
    "scales": {
      "dx": 0.004166666883975267,
      "dt": 1.956452385842877e-05,
      "E": 1200000.0,
      "vcap_dx_over_dt": 212.97052328621774
    },
    "telemetry": {
      "material": {
        "E_Pa": 1200000.0,
        "sigma_y_Pa": 50000.0,
        "E_ref_Pa": 300000.0,
        "sigma_ref_Pa": 5000.0
      },
      "knife_resistance": {
        "k2_base_per_s": 0.0,
        "k2_eff_per_s": 0.0,
        "mat_gain": 20.0,
        "c_hat": 0.0,
        "c_hat_current": 0.0
      }
    }
  },
  {
    "frame": 51,
    "timestep": 43447,
    "time": 0.850000000000001,
    "ee_pos_m": [
      -0.008020497858524323,
      0.13435035943984985,
      -0.0015417147660627961
    ],
    "ee_normal": [
      0.0,
      0.9999990463256836,
      0.0
    ],
    "knife": {
      "y_anim": 0.09057046473026276,
      "z_offset": 0.0009587852982804179
    },
    "relative_eef_force": 0.0,
    "force_world_N": {
      "x": 0.0,
      "y": 0.0,
      "z": 0.0,
      "norm": 9.999999974752427e-07
    },
    "force_normalized": {
      "x": 0.0,
      "y": 0.0,
      "z": 0.0
    },
    "scales": {
      "dx": 0.004166666883975267,
      "dt": 1.956452385842877e-05,
      "E": 1200000.0,
      "vcap_dx_over_dt": 212.97052328621774
    },
    "telemetry": {
      "material": {
        "E_Pa": 1200000.0,
        "sigma_y_Pa": 50000.0,
        "E_ref_Pa": 300000.0,
        "sigma_ref_Pa": 5000.0
      },
      "knife_resistance": {
        "k2_base_per_s": 0.0,
        "k2_eff_per_s": 0.0,
        "mat_gain": 20.0,
        "c_hat": 0.0,
        "c_hat_current": 0.0
      }
    }
  },
  {
    "frame": 52,
    "timestep": 44299,
    "time": 0.8666666666666677,
    "ee_pos_m": [
      -0.008020497858524323,
      0.13101771473884583,
      -0.0015417147660627961
    ],
    "ee_normal": [
      0.0,
      0.9999990463256836,
      0.0
    ],
    "knife": {
      "y_anim": 0.08723782002925873,
      "z_offset": 0.0009587852982804179
    },
    "relative_eef_force": 0.0,
    "force_world_N": {
      "x": 0.0,
      "y": 0.0,
      "z": 0.0,
      "norm": 9.999999974752427e-07
    },
    "force_normalized": {
      "x": 0.0,
      "y": 0.0,
      "z": 0.0
    },
    "scales": {
      "dx": 0.004166666883975267,
      "dt": 1.956452385842877e-05,
      "E": 1200000.0,
      "vcap_dx_over_dt": 212.97052328621774
    },
    "telemetry": {
      "material": {
        "E_Pa": 1200000.0,
        "sigma_y_Pa": 50000.0,
        "E_ref_Pa": 300000.0,
        "sigma_ref_Pa": 5000.0
      },
      "knife_resistance": {
        "k2_base_per_s": 0.0,
        "k2_eff_per_s": 0.0,
        "mat_gain": 20.0,
        "c_hat": 0.0,
        "c_hat_current": 0.0
      }
    }
  },
  {
    "frame": 53,
    "timestep": 45151,
    "time": 0.8833333333333344,
    "ee_pos_m": [
      -0.008020497858524323,
      0.1276850700378418,
      -0.0015417147660627961
    ],
    "ee_normal": [
      0.0,
      0.9999990463256836,
      0.0
    ],
    "knife": {
      "y_anim": 0.0839051753282547,
      "z_offset": 0.0009587852982804179
    },
    "relative_eef_force": 0.00010333062959944073,
    "force_world_N": {
      "x": -1.0455448773427634e-07,
      "y": -4.999265001970343e-07,
      "z": -1.4761518514205818e-06,
      "norm": 2.5620124688430224e-06
    },
    "force_normalized": {
      "x": -0.040809515863657,
      "y": -0.19513039290905,
      "z": -0.5761688947677612
    },
    "scales": {
      "dx": 0.004166666883975267,
      "dt": 1.956452385842877e-05,
      "E": 1200000.0,
      "vcap_dx_over_dt": 212.97052328621774
    },
    "telemetry": {
      "material": {
        "E_Pa": 1200000.0,
        "sigma_y_Pa": 50000.0,
        "E_ref_Pa": 300000.0,
        "sigma_ref_Pa": 5000.0
      },
      "knife_resistance": {
        "k2_base_per_s": 0.0,
        "k2_eff_per_s": 0.0,
        "mat_gain": 20.0,
        "c_hat": 0.003035695292055607,
        "c_hat_current": 0.0031590327268165566
      }
    }
  },
  {
    "frame": 54,
    "timestep": 46003,
    "time": 0.9000000000000011,
    "ee_pos_m": [
      -0.008020497858524323,
      0.12435243278741837,
      -0.0015417147660627961
    ],
    "ee_normal": [
      0.0,
      0.9999990463256836,
      0.0
    ],
    "knife": {
      "y_anim": 0.08057253062725067,
      "z_offset": 0.0009587852982804179
    },
    "relative_eef_force": 0.020113180216867477,
    "force_world_N": {
      "x": -1.928224264702294e-05,
      "y": -0.000501845614053309,
      "z": -0.00028733114595524967,
      "norm": 0.0005796017940156162
    },
    "force_normalized": {
      "x": -0.03326808661222458,
      "y": -0.8658455014228821,
      "z": -0.4957388937473297
    },
    "scales": {
      "dx": 0.004166666883975267,
      "dt": 1.956452385842877e-05,
      "E": 1200000.0,
      "vcap_dx_over_dt": 212.97052328621774
    },
    "telemetry": {
      "material": {
        "E_Pa": 1200000.0,
        "sigma_y_Pa": 50000.0,
        "E_ref_Pa": 300000.0,
        "sigma_ref_Pa": 5000.0
      },
      "knife_resistance": {
        "k2_base_per_s": 0.0,
        "k2_eff_per_s": 0.0,
        "mat_gain": 20.0,
        "c_hat": 0.006388880778104067,
        "c_hat_current": 0.004043411238819804
      }
    }
  },
  {
    "frame": 55,
    "timestep": 46855,
    "time": 0.9166666666666679,
    "ee_pos_m": [
      -0.008020497858524323,
      0.12101978808641434,
      -0.0015417147660627961
    ],
    "ee_normal": [
      0.0,
      0.9999990463256836,
      0.0
    ],
    "knife": {
      "y_anim": 0.07723988592624664,
      "z_offset": 0.0009587852982804179
    },
    "relative_eef_force": 0.22150349337607622,
    "force_world_N": {
      "x": -0.00018647158867679536,
      "y": -0.006030036602169275,
      "z": -0.0031643356196582317,
      "norm": 0.00681342463940382
    },
    "force_normalized": {
      "x": -0.02736826241016388,
      "y": -0.8850228786468506,
      "z": -0.46442660689353943
    },
    "scales": {
      "dx": 0.004166666883975267,
      "dt": 1.956452385842877e-05,
      "E": 1200000.0,
      "vcap_dx_over_dt": 212.97052328621774
    },
    "telemetry": {
      "material": {
        "E_Pa": 1200000.0,
        "sigma_y_Pa": 50000.0,
        "E_ref_Pa": 300000.0,
        "sigma_ref_Pa": 5000.0
      },
      "knife_resistance": {
        "k2_base_per_s": 0.0,
        "k2_eff_per_s": 0.0,
        "mat_gain": 20.0,
        "c_hat": 0.014455556869506836,
        "c_hat_current": 0.018347982779541385
      }
    }
  },
  {
    "frame": 56,
    "timestep": 47707,
    "time": 0.9333333333333346,
    "ee_pos_m": [
      -0.008020497858524323,
      0.11768714338541031,
      -0.0015417147660627961
    ],
    "ee_normal": [
      0.0,
      0.9999990463256836,
      0.0
    ],
    "knife": {
      "y_anim": 0.07390724122524261,
      "z_offset": 0.0009587852982804179
    },
    "relative_eef_force": 1.49278087541461,
    "force_world_N": {
      "x": -0.0007820638129487634,
      "y": -0.04046865552663803,
      "z": -0.02132544107735157,
      "norm": 0.04575138911604881
    },
    "force_normalized": {
      "x": -0.017093772068619728,
      "y": -0.8845339417457581,
      "z": -0.46611571311950684
    },
    "scales": {
      "dx": 0.004166666883975267,
      "dt": 1.956452385842877e-05,
      "E": 1200000.0,
      "vcap_dx_over_dt": 212.97052328621774
    },
    "telemetry": {
      "material": {
        "E_Pa": 1200000.0,
        "sigma_y_Pa": 50000.0,
        "E_ref_Pa": 300000.0,
        "sigma_ref_Pa": 5000.0
      },
      "knife_resistance": {
        "k2_base_per_s": 0.0,
        "k2_eff_per_s": 0.0,
        "mat_gain": 20.0,
        "c_hat": 0.03163759410381317,
        "c_hat_current": 0.03169276509419333
      }
    }
  },
  {
    "frame": 57,
    "timestep": 48559,
    "time": 0.9500000000000013,
    "ee_pos_m": [
      -0.008020497858524323,
      0.11435449868440628,
      -0.0015417147660627961
    ],
    "ee_normal": [
      0.0,
      0.9999990463256836,
      0.0
    ],
    "knife": {
      "y_anim": 0.07057459652423859,
      "z_offset": 0.0009587852982804179
    },
    "relative_eef_force": 4.900146573781967,
    "force_world_N": {
      "x": -0.0017941148253157735,
      "y": -0.13495677709579468,
      "z": -0.07000209391117096,
      "norm": 0.15204323828220367
    },
    "force_normalized": {
      "x": -0.011800030246376991,
      "y": -0.8876210451126099,
      "z": -0.46040913462638855
    },
    "scales": {
      "dx": 0.004166666883975267,
      "dt": 1.956452385842877e-05,
      "E": 1200000.0,
      "vcap_dx_over_dt": 212.97052328621774
    },
    "telemetry": {
      "material": {
        "E_Pa": 1200000.0,
        "sigma_y_Pa": 50000.0,
        "E_ref_Pa": 300000.0,
        "sigma_ref_Pa": 5000.0
      },
      "knife_resistance": {
        "k2_base_per_s": 0.0,
        "k2_eff_per_s": 0.0,
        "mat_gain": 20.0,
        "c_hat": 0.04891292750835419,
        "c_hat_current": 0.04892276177282342
      }
    }
  },
  {
    "frame": 58,
    "timestep": 49411,
    "time": 0.966666666666668,
    "ee_pos_m": [
      -0.008020497858524323,
      0.11102185398340225,
      -0.0015417147660627961
    ],
    "ee_normal": [
      0.0,
      0.9999990463256836,
      0.0
    ],
    "knife": {
      "y_anim": 0.06724195182323456,
      "z_offset": 0.0009587852982804179
    },
    "relative_eef_force": 14.445552378892899,
    "force_world_N": {
      "x": -0.00488374475389719,
      "y": -0.4056011438369751,
      "z": -0.20636503398418427,
      "norm": 0.45510831475257874
    },
    "force_normalized": {
      "x": -0.01073095016181469,
      "y": -0.891218900680542,
      "z": -0.4534415900707245
    },
    "scales": {
      "dx": 0.004166666883975267,
      "dt": 1.956452385842877e-05,
      "E": 1200000.0,
      "vcap_dx_over_dt": 212.97052328621774
    },
    "telemetry": {
      "material": {
        "E_Pa": 1200000.0,
        "sigma_y_Pa": 50000.0,
        "E_ref_Pa": 300000.0,
        "sigma_ref_Pa": 5000.0
      },
      "knife_resistance": {
        "k2_base_per_s": 0.0,
        "k2_eff_per_s": 0.0,
        "mat_gain": 20.0,
        "c_hat": 0.0817110687494278,
        "c_hat_current": 0.08162498790949702
      }
    }
  },
  {
    "frame": 59,
    "timestep": 50263,
    "time": 0.9833333333333347,
    "ee_pos_m": [
      -0.008020497858524323,
      0.10768920928239822,
      -0.0015417147660627961
    ],
    "ee_normal": [
      0.0,
      0.9999990463256836,
      0.0
    ],
    "knife": {
      "y_anim": 0.06390930712223053,
      "z_offset": 0.0009587852982804179
    },
    "relative_eef_force": 22.45432734489441,
    "force_world_N": {
      "x": -0.008438780903816223,
      "y": -0.6480992436408997,
      "z": -0.320776104927063,
      "norm": 0.7231891751289368
    },
    "force_normalized": {
      "x": -0.01166884321719408,
      "y": -0.8961683511734009,
      "z": -0.4435576796531677
    },
    "scales": {
      "dx": 0.004166666883975267,
      "dt": 1.956452385842877e-05,
      "E": 1200000.0,
      "vcap_dx_over_dt": 212.97052328621774
    },
    "telemetry": {
      "material": {
        "E_Pa": 1200000.0,
        "sigma_y_Pa": 50000.0,
        "E_ref_Pa": 300000.0,
        "sigma_ref_Pa": 5000.0
      },
      "knife_resistance": {
        "k2_base_per_s": 0.0,
        "k2_eff_per_s": 0.0,
        "mat_gain": 20.0,
        "c_hat": 0.10759613662958145,
        "c_hat_current": 0.10761662025790003
      }
    }
  },
  {
    "frame": 60,
    "timestep": 51114,
    "time": 1.0000000000000013,
    "ee_pos_m": [
      -0.008020497858524323,
      0.10436047613620758,
      -0.0015417147660627961
    ],
    "ee_normal": [
      0.0,
      0.9999990463256836,
      0.0
    ],
    "knife": {
      "y_anim": 0.060580573976039886,
      "z_offset": 0.0009587852982804179
    },
    "relative_eef_force": 29.64303284883499,
    "force_world_N": {
      "x": -0.011316921561956406,
      "y": -0.8915981650352478,
      "z": -0.4234718978404999,
      "norm": 0.9871199727058411
    },
    "force_normalized": {
      "x": -0.011464585550129414,
      "y": -0.9032317996025085,
      "z": -0.4289973974227905
    },
    "scales": {
      "dx": 0.004166666883975267,
      "dt": 1.956452385842877e-05,
      "E": 1200000.0,
      "vcap_dx_over_dt": 212.97052328621774
    },
    "telemetry": {
      "material": {
        "E_Pa": 1200000.0,
        "sigma_y_Pa": 50000.0,
        "E_ref_Pa": 300000.0,
        "sigma_ref_Pa": 5000.0
      },
      "knife_resistance": {
        "k2_base_per_s": 0.0,
        "k2_eff_per_s": 0.0,
        "mat_gain": 20.0,
        "c_hat": 0.13482636213302612,
        "c_hat_current": 0.13389809842616196
      }
    }
  },
  {
    "frame": 61,
    "timestep": 51966,
    "time": 1.016666666666668,
    "ee_pos_m": [
      -0.008020497858524323,
      0.10102783143520355,
      -0.0015417147660627961
    ],
    "ee_normal": [
      0.0,
      0.9999990463256836,
      0.0
    ],
    "knife": {
      "y_anim": 0.05724792927503586,
      "z_offset": 0.0009587852982804179
    },
    "relative_eef_force": 28.35132896900177,
    "force_world_N": {
      "x": -0.011396152898669243,
      "y": -0.9032323360443115,
      "z": -0.40501898527145386,
      "norm": 0.9899500012397766
    },
    "force_normalized": {
      "x": -0.011511847376823425,
      "y": -0.9124019742012024,
      "z": -0.4091307520866394
    },
    "scales": {
      "dx": 0.004166666883975267,
      "dt": 1.956452385842877e-05,
      "E": 1200000.0,
      "vcap_dx_over_dt": 212.97052328621774
    },
    "telemetry": {
      "material": {
        "E_Pa": 1200000.0,
        "sigma_y_Pa": 50000.0,
        "E_ref_Pa": 300000.0,
        "sigma_ref_Pa": 5000.0
      },
      "knife_resistance": {
        "k2_base_per_s": 0.0,
        "k2_eff_per_s": 0.0,
        "mat_gain": 20.0,
        "c_hat": 0.1620398312807083,
        "c_hat_current": 0.16204200023234236
      }
    }
  },
  {
    "frame": 62,
    "timestep": 52818,
    "time": 1.0333333333333345,
    "ee_pos_m": [
      -0.008020497858524323,
      0.09769518673419952,
      -0.0015417147660627961
    ],
    "ee_normal": [
      0.0,
      0.9999990463256836,
      0.0
    ],
    "knife": {
      "y_anim": 0.05391528457403183,
      "z_offset": 0.0009587852982804179
    },
    "relative_eef_force": 27.189275920391083,
    "force_world_N": {
      "x": -0.014286478981375694,
      "y": -0.9068902134895325,
      "z": -0.3884182274341583,
      "norm": 0.9866735339164734
    },
    "force_normalized": {
      "x": -0.0144794387742877,
      "y": -0.9191390872001648,
      "z": -0.3936643898487091
    },
    "scales": {
      "dx": 0.004166666883975267,
      "dt": 1.956452385842877e-05,
      "E": 1200000.0,
      "vcap_dx_over_dt": 212.97052328621774
    },
    "telemetry": {
      "material": {
        "E_Pa": 1200000.0,
        "sigma_y_Pa": 50000.0,
        "E_ref_Pa": 300000.0,
        "sigma_ref_Pa": 5000.0
      },
      "knife_resistance": {
        "k2_base_per_s": 0.0,
        "k2_eff_per_s": 0.0,
        "mat_gain": 20.0,
        "c_hat": 0.14128604531288147,
        "c_hat_current": 0.14118533244149348
      }
    }
  },
  {
    "frame": 63,
    "timestep": 53670,
    "time": 1.0500000000000012,
    "ee_pos_m": [
      -0.008020497858524323,
      0.0943625420331955,
      -0.0015417147660627961
    ],
    "ee_normal": [
      0.0,
      0.9999990463256836,
      0.0
    ],
    "knife": {
      "y_anim": 0.0505826398730278,
      "z_offset": 0.0009587852982804179
    },
    "relative_eef_force": 31.28122329711914,
    "force_world_N": {
      "x": -0.009119982831180096,
      "y": -1.0710469484329224,
      "z": -0.44687461853027344,
      "norm": 1.160570502281189
    },
    "force_normalized": {
      "x": -0.00785818975418806,
      "y": -0.9228624701499939,
      "z": -0.38504737615585327
    },
    "scales": {
      "dx": 0.004166666883975267,
      "dt": 1.956452385842877e-05,
      "E": 1200000.0,
      "vcap_dx_over_dt": 212.97052328621774
    },
    "telemetry": {
      "material": {
        "E_Pa": 1200000.0,
        "sigma_y_Pa": 50000.0,
        "E_ref_Pa": 300000.0,
        "sigma_ref_Pa": 5000.0
      },
      "knife_resistance": {
        "k2_base_per_s": 0.0,
        "k2_eff_per_s": 0.0,
        "mat_gain": 20.0,
        "c_hat": 0.12151738256216049,
        "c_hat_current": 0.12075427594391644
      }
    }
  },
  {
    "frame": 64,
    "timestep": 54522,
    "time": 1.0666666666666678,
    "ee_pos_m": [
      -0.008020497858524323,
      0.09102989733219147,
      -0.0015417147660627961
    ],
    "ee_normal": [
      0.0,
      0.9999990463256836,
      0.0
    ],
    "knife": {
      "y_anim": 0.04724999517202377,
      "z_offset": 0.0009587852982804179
    },
    "relative_eef_force": 35.78831076622009,
    "force_world_N": {
      "x": -0.012944787740707397,
      "y": -1.2473399639129639,
      "z": -0.5112615823745728,
      "norm": 1.3481155633926392
    },
    "force_normalized": {
      "x": -0.009602135047316551,
      "y": -0.925247073173523,
      "z": -0.3792416453361511
    },
    "scales": {
      "dx": 0.004166666883975267,
      "dt": 1.956452385842877e-05,
      "E": 1200000.0,
      "vcap_dx_over_dt": 212.97052328621774
    },
    "telemetry": {
      "material": {
        "E_Pa": 1200000.0,
        "sigma_y_Pa": 50000.0,
        "E_ref_Pa": 300000.0,
        "sigma_ref_Pa": 5000.0
      },
      "knife_resistance": {
        "k2_base_per_s": 0.0,
        "k2_eff_per_s": 0.0,
        "mat_gain": 20.0,
        "c_hat": 0.12992426753044128,
        "c_hat_current": 0.12992225486729106
      }
    }
  },
  {
    "frame": 65,
    "timestep": 55374,
    "time": 1.0833333333333344,
    "ee_pos_m": [
      -0.008020497858524323,
      0.08769725263118744,
      -0.0015417147660627961
    ],
    "ee_normal": [
      0.0,
      0.9999990463256836,
      0.0
    ],
    "knife": {
      "y_anim": 0.043917350471019745,
      "z_offset": 0.0009587852982804179
    },
    "relative_eef_force": 41.3701057434082,
    "force_world_N": {
      "x": -0.015187113545835018,
      "y": -1.4750585556030273,
      "z": -0.5910015106201172,
      "norm": 1.5891237258911133
    },
    "force_normalized": {
      "x": -0.009556910954415798,
      "y": -0.9282213449478149,
      "z": -0.37190401554107666
    },
    "scales": {
      "dx": 0.004166666883975267,
      "dt": 1.956452385842877e-05,
      "E": 1200000.0,
      "vcap_dx_over_dt": 212.97052328621774
    },
    "telemetry": {
      "material": {
        "E_Pa": 1200000.0,
        "sigma_y_Pa": 50000.0,
        "E_ref_Pa": 300000.0,
        "sigma_ref_Pa": 5000.0
      },
      "knife_resistance": {
        "k2_base_per_s": 0.0,
        "k2_eff_per_s": 0.0,
        "mat_gain": 20.0,
        "c_hat": 0.16540075838565826,
        "c_hat_current": 0.16550262203987384
      }
    }
  },
  {
    "frame": 66,
    "timestep": 56226,
    "time": 1.100000000000001,
    "ee_pos_m": [
      -0.008020497858524323,
      0.08436460793018341,
      -0.0015417147660627961
    ],
    "ee_normal": [
      0.0,
      0.9999990463256836,
      0.0
    ],
    "knife": {
      "y_anim": 0.04058470577001572,
      "z_offset": 0.0009587852982804179
    },
    "relative_eef_force": 47.21139430999756,
    "force_world_N": {
      "x": -0.01597987860441208,
      "y": -1.7609446048736572,
      "z": -0.6744484901428223,
      "norm": 1.8857532739639282
    },
    "force_normalized": {
      "x": -0.008474002592265606,
      "y": -0.9338149428367615,
      "z": -0.3576546907424927
    },
    "scales": {
      "dx": 0.004166666883975267,
      "dt": 1.956452385842877e-05,
      "E": 1200000.0,
      "vcap_dx_over_dt": 212.97052328621774
    },
    "telemetry": {
      "material": {
        "E_Pa": 1200000.0,
        "sigma_y_Pa": 50000.0,
        "E_ref_Pa": 300000.0,
        "sigma_ref_Pa": 5000.0
      },
      "knife_resistance": {
        "k2_base_per_s": 0.0,
        "k2_eff_per_s": 0.0,
        "mat_gain": 20.0,
        "c_hat": 0.18975362181663513,
        "c_hat_current": 0.1897681335794593
      }
    }
  },
  {
    "frame": 67,
    "timestep": 57078,
    "time": 1.1166666666666676,
    "ee_pos_m": [
      -0.008020497858524323,
      0.08103196322917938,
      -0.0015417147660627961
    ],
    "ee_normal": [
      0.0,
      0.9999990463256836,
      0.0
    ],
    "knife": {
      "y_anim": 0.03725206106901169,
      "z_offset": 0.0009587852982804179
    },
    "relative_eef_force": 54.71075236797333,
    "force_world_N": {
      "x": -0.01823423057794571,
      "y": -2.0871028900146484,
      "z": -0.7815821766853333,
      "norm": 2.2287230491638184
    },
    "force_normalized": {
      "x": -0.008181469514966011,
      "y": -0.9364567995071411,
      "z": -0.35068610310554504
    },
    "scales": {
      "dx": 0.004166666883975267,
      "dt": 1.956452385842877e-05,
      "E": 1200000.0,
      "vcap_dx_over_dt": 212.97052328621774
    },
    "telemetry": {
      "material": {
        "E_Pa": 1200000.0,
        "sigma_y_Pa": 50000.0,
        "E_ref_Pa": 300000.0,
        "sigma_ref_Pa": 5000.0
      },
      "knife_resistance": {
        "k2_base_per_s": 0.0,
        "k2_eff_per_s": 0.0,
        "mat_gain": 20.0,
        "c_hat": 0.18837346136569977,
        "c_hat_current": 0.18850790654923996
      }
    }
  },
  {
    "frame": 68,
    "timestep": 57929,
    "time": 1.1333333333333342,
    "ee_pos_m": [
      -0.008020497858524323,
      0.07770322263240814,
      -0.0015417147660627961
    ],
    "ee_normal": [
      0.0,
      0.9999990463256836,
      0.0
    ],
    "knife": {
      "y_anim": 0.033923327922821045,
      "z_offset": 0.0009587852982804179
    },
    "relative_eef_force": 66.13977313041687,
    "force_world_N": {
      "x": -0.027317414060235023,
      "y": -2.5251781940460205,
      "z": -0.9448539018630981,
      "norm": 2.696298360824585
    },
    "force_normalized": {
      "x": -0.01013145036995411,
      "y": -0.9365351796150208,
      "z": -0.3504263162612915
    },
    "scales": {
      "dx": 0.004166666883975267,
      "dt": 1.956452385842877e-05,
      "E": 1200000.0,
      "vcap_dx_over_dt": 212.97052328621774
    },
    "telemetry": {
      "material": {
        "E_Pa": 1200000.0,
        "sigma_y_Pa": 50000.0,
        "E_ref_Pa": 300000.0,
        "sigma_ref_Pa": 5000.0
      },
      "knife_resistance": {
        "k2_base_per_s": 0.0,
        "k2_eff_per_s": 0.0,
        "mat_gain": 20.0,
        "c_hat": 0.19001030921936035,
        "c_hat_current": 0.1900148693995383
      }
    }
  },
  {
    "frame": 69,
    "timestep": 58781,
    "time": 1.1500000000000008,
    "ee_pos_m": [
      -0.008020497858524323,
      0.07437026500701904,
      -0.0015417147660627961
    ],
    "ee_normal": [
      0.0,
      0.9999990463256836,
      0.0
    ],
    "knife": {
      "y_anim": 0.030590368434786797,
      "z_offset": 0.0009587852982804179
    },
    "relative_eef_force": 72.44415640830994,
    "force_world_N": {
      "x": -0.02237527258694172,
      "y": -2.856356620788574,
      "z": -1.0349165201187134,
      "norm": 3.0381462574005127
    },
    "force_normalized": {
      "x": -0.007364777848124504,
      "y": -0.9401642680168152,
      "z": -0.3406407833099365
    },
    "scales": {
      "dx": 0.004166666883975267,
      "dt": 1.956452385842877e-05,
      "E": 1200000.0,
      "vcap_dx_over_dt": 212.97052328621774
    },
    "telemetry": {
      "material": {
        "E_Pa": 1200000.0,
        "sigma_y_Pa": 50000.0,
        "E_ref_Pa": 300000.0,
        "sigma_ref_Pa": 5000.0
      },
      "knife_resistance": {
        "k2_base_per_s": 0.0,
        "k2_eff_per_s": 0.0,
        "mat_gain": 20.0,
        "c_hat": 0.18778768181800842,
        "c_hat_current": 0.1879325649317584
      }
    }
  },
  {
    "frame": 70,
    "timestep": 59633,
    "time": 1.1666666666666674,
    "ee_pos_m": [
      -0.008020497858524323,
      0.07103604078292847,
      -0.0015417147660627961
    ],
    "ee_normal": [
      0.0,
      0.9999990463256836,
      0.0
    ],
    "knife": {
      "y_anim": 0.027256136760115623,
      "z_offset": 0.0009587852982804179
    },
    "relative_eef_force": 64.46597397327423,
    "force_world_N": {
      "x": -0.02042463794350624,
      "y": -2.79378342628479,
      "z": -0.920942485332489,
      "norm": 2.9417314529418945
    },
    "force_normalized": {
      "x": -0.006943066604435444,
      "y": -0.9497071504592896,
      "z": -0.313061386346817
    },
    "scales": {
      "dx": 0.004166666883975267,
      "dt": 1.956452385842877e-05,
      "E": 1200000.0,
      "vcap_dx_over_dt": 212.97052328621774
    },
    "telemetry": {
      "material": {
        "E_Pa": 1200000.0,
        "sigma_y_Pa": 50000.0,
        "E_ref_Pa": 300000.0,
        "sigma_ref_Pa": 5000.0
      },
      "knife_resistance": {
        "k2_base_per_s": 0.0,
        "k2_eff_per_s": 0.0,
        "mat_gain": 20.0,
        "c_hat": 0.18728546798229218,
        "c_hat_current": 1.0
      }
    }
  }
]