[
  {
    "frame": 0,
    "timestep": 1,
    "time": 0.0,
    "ee_pos_m": [
      -0.008020497858524323,
      0.1424238681793213,
      -0.0015417147660627961
    ],
    "ee_normal": [
      0.0,
      0.9999990463256836,
      0.0
    ],
    "knife": {
      "y_anim": 0.0986439660191536,
      "z_offset": 0.0009587852982804179
    },
    "relative_eef_force": 0.0,
    "force_world_N": {
      "x": 0.0,
      "y": 0.0,
      "z": 0.0,
      "norm": 9.999999974752427e-07
    },
    "force_normalized": {
      "x": 0.0,
      "y": 0.0,
      "z": 0.0
    },
    "scales": {
      "dx": 0.004166666883975267,
      "dt": 1.2857669036389097e-05,
      "E": 2819808.3930243584,
      "vcap_dx_over_dt": 324.0608287694283
    },
    "telemetry": {
      "material": {
        "E_Pa": 2819808.3930243584,
        "sigma_y_Pa": 237045.56369017874,
        "E_ref_Pa": 300000.0,
        "sigma_ref_Pa": 5000.0
      },
      "knife_resistance": {
        "k2_base_per_s": 0.0,
        "k2_eff_per_s": 0.0,
        "mat_gain": 145.34864907848944,
        "c_hat": 0.0,
        "c_hat_current": 0.0
      }
    }
  },
  {
    "frame": 1,
    "timestep": 1298,
    "time": 0.016666666666666666,
    "ee_pos_m": [
      -0.008020497858524323,
      0.1374182254076004,
      -0.0015417147660627961
    ],
    "ee_normal": [
      0.0,
      0.9999990463256836,
      0.0
    ],
    "knife": {
      "y_anim": 0.09363832324743271,
      "z_offset": 0.0009587852982804179
    },
    "relative_eef_force": 0.0,
    "force_world_N": {
      "x": 0.0,
      "y": 0.0,
      "z": 0.0,
      "norm": 9.999999974752427e-07
    },
    "force_normalized": {
      "x": 0.0,
      "y": 0.0,
      "z": 0.0
    },
    "scales": {
      "dx": 0.004166666883975267,
      "dt": 1.2857669036389097e-05,
      "E": 2819808.3930243584,
      "vcap_dx_over_dt": 324.0608287694283
    },
    "telemetry": {
      "material": {
        "E_Pa": 2819808.3930243584,
        "sigma_y_Pa": 237045.56369017874,
        "E_ref_Pa": 300000.0,
        "sigma_ref_Pa": 5000.0
      },
      "knife_resistance": {
        "k2_base_per_s": 0.0,
        "k2_eff_per_s": 0.0,
        "mat_gain": 145.34864907848944,
        "c_hat": 0.0,
        "c_hat_current": 0.0
      }
    }
  },
  {
    "frame": 2,
    "timestep": 2594,
    "time": 0.03333333333333333,
    "ee_pos_m": [
      -0.008020497858524323,
      0.13241644203662872,
      -0.0015417147660627961
    ],
    "ee_normal": [
      0.0,
      0.9999990463256836,
      0.0
    ],
    "knife": {
      "y_anim": 0.08863653987646103,
      "z_offset": 0.0009587852982804179
    },
    "relative_eef_force": 0.0,
    "force_world_N": {
      "x": 0.0,
      "y": 0.0,
      "z": 0.0,
      "norm": 9.999999974752427e-07
    },
    "force_normalized": {
      "x": 0.0,
      "y": 0.0,
      "z": 0.0
    },
    "scales": {
      "dx": 0.004166666883975267,
      "dt": 1.2857669036389097e-05,
      "E": 2819808.3930243584,
      "vcap_dx_over_dt": 324.0608287694283
    },
    "telemetry": {
      "material": {
        "E_Pa": 2819808.3930243584,
        "sigma_y_Pa": 237045.56369017874,
        "E_ref_Pa": 300000.0,
        "sigma_ref_Pa": 5000.0
      },
      "knife_resistance": {
        "k2_base_per_s": 0.0,
        "k2_eff_per_s": 0.0,
        "mat_gain": 145.34864907848944,
        "c_hat": 0.0,
        "c_hat_current": 0.0
      }
    }
  },
  {
    "frame": 3,
    "timestep": 3890,
    "time": 0.05,
    "ee_pos_m": [
      -0.008020497858524323,
      0.12741465866565704,
      -0.0015417147660627961
    ],
    "ee_normal": [
      0.0,
      0.9999990463256836,
      0.0
    ],
    "knife": {
      "y_anim": 0.08363475650548935,
      "z_offset": 0.0009587852982804179
    },
    "relative_eef_force": 0.0,
    "force_world_N": {
      "x": 0.0,
      "y": 0.0,
      "z": 0.0,
      "norm": 9.999999974752427e-07
    },
    "force_normalized": {
      "x": 0.0,
      "y": 0.0,
      "z": 0.0
    },
    "scales": {
      "dx": 0.004166666883975267,
      "dt": 1.2857669036389097e-05,
      "E": 2819808.3930243584,
      "vcap_dx_over_dt": 324.0608287694283
    },
    "telemetry": {
      "material": {
        "E_Pa": 2819808.3930243584,
        "sigma_y_Pa": 237045.56369017874,
        "E_ref_Pa": 300000.0,
        "sigma_ref_Pa": 5000.0
      },
      "knife_resistance": {
        "k2_base_per_s": 0.0,
        "k2_eff_per_s": 0.0,
        "mat_gain": 145.34864907848944,
        "c_hat": 0.0,
        "c_hat_current": 0.0
      }
    }
  },
  {
    "frame": 4,
    "timestep": 5186,
    "time": 0.06666666666666667,
    "ee_pos_m": [
      -0.008020497858524323,
      0.12241287529468536,
      -0.0015417147660627961
    ],
    "ee_normal": [
      0.0,
      0.9999990463256836,
      0.0
    ],
    "knife": {
      "y_anim": 0.07863297313451767,
      "z_offset": 0.0009587852982804179
    },
    "relative_eef_force": 0.0,
    "force_world_N": {
      "x": 0.0,
      "y": 0.0,
      "z": 0.0,
      "norm": 9.999999974752427e-07
    },
    "force_normalized": {
      "x": 0.0,
      "y": 0.0,
      "z": 0.0
    },
    "scales": {
      "dx": 0.004166666883975267,
      "dt": 1.2857669036389097e-05,
      "E": 2819808.3930243584,
      "vcap_dx_over_dt": 324.0608287694283
    },
    "telemetry": {
      "material": {
        "E_Pa": 2819808.3930243584,
        "sigma_y_Pa": 237045.56369017874,
        "E_ref_Pa": 300000.0,
        "sigma_ref_Pa": 5000.0
      },
      "knife_resistance": {
        "k2_base_per_s": 0.0,
        "k2_eff_per_s": 0.0,
        "mat_gain": 145.34864907848944,
        "c_hat": 0.0,
        "c_hat_current": 0.0
      }
    }
  },
  {
    "frame": 5,
    "timestep": 6483,
    "time": 0.08333333333333333,
    "ee_pos_m": [
      -0.008020497858524323,
      0.11740723252296448,
      -0.0015417147660627961
    ],
    "ee_normal": [
      0.0,
      0.9999990463256836,
      0.0
    ],
    "knife": {
      "y_anim": 0.07362733036279678,
      "z_offset": 0.0009587852982804179
    },
    "relative_eef_force": 0.0,
    "force_world_N": {
      "x": 0.0,
      "y": 0.0,
      "z": 0.0,
      "norm": 9.999999974752427e-07
    },
    "force_normalized": {
      "x": 0.0,
      "y": 0.0,
      "z": 0.0
    },
    "scales": {
      "dx": 0.004166666883975267,
      "dt": 1.2857669036389097e-05,
      "E": 2819808.3930243584,
      "vcap_dx_over_dt": 324.0608287694283
    },
    "telemetry": {
      "material": {
        "E_Pa": 2819808.3930243584,
        "sigma_y_Pa": 237045.56369017874,
        "E_ref_Pa": 300000.0,
        "sigma_ref_Pa": 5000.0
      },
      "knife_resistance": {
        "k2_base_per_s": 0.0,
        "k2_eff_per_s": 0.0,
        "mat_gain": 145.34864907848944,
        "c_hat": 0.0,
        "c_hat_current": 0.0
      }
    }
  },
  {
    "frame": 6,
    "timestep": 7779,
    "time": 0.09999999999999999,
    "ee_pos_m": [
      -0.008020497858524323,
      0.1124054491519928,
      -0.0015417147660627961
    ],
    "ee_normal": [
      0.0,
      0.9999990463256836,
      0.0
    ],
    "knife": {
      "y_anim": 0.0686255469918251,
      "z_offset": 0.0009587852982804179
    },
    "relative_eef_force": 0.0,
    "force_world_N": {
      "x": 0.0,
      "y": 0.0,
      "z": 0.0,
      "norm": 9.999999974752427e-07
    },
    "force_normalized": {
      "x": 0.0,
      "y": 0.0,
      "z": 0.0
    },
    "scales": {
      "dx": 0.004166666883975267,
      "dt": 1.2857669036389097e-05,
      "E": 2819808.3930243584,
      "vcap_dx_over_dt": 324.0608287694283
    },
    "telemetry": {
      "material": {
        "E_Pa": 2819808.3930243584,
        "sigma_y_Pa": 237045.56369017874,
        "E_ref_Pa": 300000.0,
        "sigma_ref_Pa": 5000.0
      },
      "knife_resistance": {
        "k2_base_per_s": 0.0,
        "k2_eff_per_s": 0.0,
        "mat_gain": 145.34864907848944,
        "c_hat": 0.0,
        "c_hat_current": 0.0
      }
    }
  },
  {
    "frame": 7,
    "timestep": 9075,
    "time": 0.11666666666666665,
    "ee_pos_m": [
      -0.008020497858524323,
      0.10740366578102112,
      -0.0015417147660627961
    ],
    "ee_normal": [
      0.0,
      0.9999990463256836,
      0.0
    ],
    "knife": {
      "y_anim": 0.06362376362085342,
      "z_offset": 0.0009587852982804179
    },
    "relative_eef_force": 0.0,
    "force_world_N": {
      "x": 0.0,
      "y": 0.0,
      "z": 0.0,
      "norm": 9.999999974752427e-07
    },
    "force_normalized": {
      "x": 0.0,
      "y": 0.0,
      "z": 0.0
    },
    "scales": {
      "dx": 0.004166666883975267,
      "dt": 1.2857669036389097e-05,
      "E": 2819808.3930243584,
      "vcap_dx_over_dt": 324.0608287694283
    },
    "telemetry": {
      "material": {
        "E_Pa": 2819808.3930243584,
        "sigma_y_Pa": 237045.56369017874,
        "E_ref_Pa": 300000.0,
        "sigma_ref_Pa": 5000.0
      },
      "knife_resistance": {
        "k2_base_per_s": 0.0,
        "k2_eff_per_s": 0.0,
        "mat_gain": 145.34864907848944,
        "c_hat": 0.0,
        "c_hat_current": 0.0
      }
    }
  },
  {
    "frame": 8,
    "timestep": 10371,
    "time": 0.13333333333333333,
    "ee_pos_m": [
      -0.008020497858524323,
      0.1024056226015091,
      -0.0015417147660627961
    ],
    "ee_normal": [
      0.0,
      0.9999990463256836,
      0.0
    ],
    "knife": {
      "y_anim": 0.0586257241666317,
      "z_offset": 0.0009587852982804179
    },
    "relative_eef_force": 0.0,
    "force_world_N": {
      "x": 0.0,
      "y": 0.0,
      "z": 0.0,
      "norm": 9.999999974752427e-07
    },
    "force_normalized": {
      "x": 0.0,
      "y": 0.0,
      "z": 0.0
    },
    "scales": {
      "dx": 0.004166666883975267,
      "dt": 1.2857669036389097e-05,
      "E": 2819808.3930243584,
      "vcap_dx_over_dt": 324.0608287694283
    },
    "telemetry": {
      "material": {
        "E_Pa": 2819808.3930243584,
        "sigma_y_Pa": 237045.56369017874,
        "E_ref_Pa": 300000.0,
        "sigma_ref_Pa": 5000.0
      },
      "knife_resistance": {
        "k2_base_per_s": 0.0,
        "k2_eff_per_s": 0.0,
        "mat_gain": 145.34864907848944,
        "c_hat": 0.0,
        "c_hat_current": 0.0
      }
    }
  },
  {
    "frame": 9,
    "timestep": 11668,
    "time": 0.15,
    "ee_pos_m": [
      -0.008020497858524323,
      0.09740480780601501,
      -0.0015417147660627961
    ],
    "ee_normal": [
      0.0,
      0.9999990463256836,
      0.0
    ],
    "knife": {
      "y_anim": 0.05362491309642792,
      "z_offset": 0.0009587852982804179
    },
    "relative_eef_force": 0.0,
    "force_world_N": {
      "x": 0.0,
      "y": 0.0,
      "z": 0.0,
      "norm": 9.999999974752427e-07
    },
    "force_normalized": {
      "x": 0.0,
      "y": 0.0,
      "z": 0.0
    },
    "scales": {
      "dx": 0.004166666883975267,
      "dt": 1.2857669036389097e-05,
      "E": 2819808.3930243584,
      "vcap_dx_over_dt": 324.0608287694283
    },
    "telemetry": {
      "material": {
        "E_Pa": 2819808.3930243584,
        "sigma_y_Pa": 237045.56369017874,
        "E_ref_Pa": 300000.0,
        "sigma_ref_Pa": 5000.0
      },
      "knife_resistance": {
        "k2_base_per_s": 0.0,
        "k2_eff_per_s": 0.0,
        "mat_gain": 145.34864907848944,
        "c_hat": 0.0,
        "c_hat_current": 0.0
      }
    }
  },
  {
    "frame": 10,
    "timestep": 12964,
    "time": 0.16666666666666666,
    "ee_pos_m": [
      -0.008020497858524323,
      0.09240785241127014,
      -0.0015417147660627961
    ],
    "ee_normal": [
      0.0,
      0.9999990463256836,
      0.0
    ],
    "knife": {
      "y_anim": 0.048627957701683044,
      "z_offset": 0.0009587852982804179
    },
    "relative_eef_force": 0.0,
    "force_world_N": {
      "x": 0.0,
      "y": 0.0,
      "z": 0.0,
      "norm": 9.999999974752427e-07
    },
    "force_normalized": {
      "x": 0.0,
      "y": 0.0,
      "z": 0.0
    },
    "scales": {
      "dx": 0.004166666883975267,
      "dt": 1.2857669036389097e-05,
      "E": 2819808.3930243584,
      "vcap_dx_over_dt": 324.0608287694283
    },
    "telemetry": {
      "material": {
        "E_Pa": 2819808.3930243584,
        "sigma_y_Pa": 237045.56369017874,
        "E_ref_Pa": 300000.0,
        "sigma_ref_Pa": 5000.0
      },
      "knife_resistance": {
        "k2_base_per_s": 0.0,
        "k2_eff_per_s": 0.0,
        "mat_gain": 145.34864907848944,
        "c_hat": 0.0,
        "c_hat_current": 0.0
      }
    }
  },
  {
    "frame": 11,
    "timestep": 14260,
    "time": 0.18333333333333332,
    "ee_pos_m": [
      -0.008020497858524323,
      0.08741089701652527,
      -0.0015417147660627961
    ],
    "ee_normal": [
      0.0,
      0.9999990463256836,
      0.0
    ],
    "knife": {
      "y_anim": 0.04363100230693817,
      "z_offset": 0.0009587852982804179
    },
    "relative_eef_force": 0.0,
    "force_world_N": {
      "x": 0.0,
      "y": 0.0,
      "z": 0.0,
      "norm": 9.999999974752427e-07
    },
    "force_normalized": {
      "x": 0.0,
      "y": 0.0,
      "z": 0.0
    },
    "scales": {
      "dx": 0.004166666883975267,
      "dt": 1.2857669036389097e-05,
      "E": 2819808.3930243584,
      "vcap_dx_over_dt": 324.0608287694283
    },
    "telemetry": {
      "material": {
        "E_Pa": 2819808.3930243584,
        "sigma_y_Pa": 237045.56369017874,
        "E_ref_Pa": 300000.0,
        "sigma_ref_Pa": 5000.0
      },
      "knife_resistance": {
        "k2_base_per_s": 0.0,
        "k2_eff_per_s": 0.0,
        "mat_gain": 145.34864907848944,
        "c_hat": 0.0,
        "c_hat_current": 0.0
      }
    }
  },
  {
    "frame": 12,
    "timestep": 15556,
    "time": 0.19999999999999998,
    "ee_pos_m": [
      -0.008020497858524323,
      0.0824139416217804,
      -0.0015417147660627961
    ],
    "ee_normal": [
      0.0,
      0.9999990463256836,
      0.0
    ],
    "knife": {
      "y_anim": 0.0386340469121933,
      "z_offset": 0.0009587852982804179
    },
    "relative_eef_force": 0.0,
    "force_world_N": {
      "x": 0.0,
      "y": 0.0,
      "z": 0.0,
      "norm": 9.999999974752427e-07
    },
    "force_normalized": {
      "x": 0.0,
      "y": 0.0,
      "z": 0.0
    },
    "scales": {
      "dx": 0.004166666883975267,
      "dt": 1.2857669036389097e-05,
      "E": 2819808.3930243584,
      "vcap_dx_over_dt": 324.0608287694283
    },
    "telemetry": {
      "material": {
        "E_Pa": 2819808.3930243584,
        "sigma_y_Pa": 237045.56369017874,
        "E_ref_Pa": 300000.0,
        "sigma_ref_Pa": 5000.0
      },
      "knife_resistance": {
        "k2_base_per_s": 0.0,
        "k2_eff_per_s": 0.0,
        "mat_gain": 145.34864907848944,
        "c_hat": 0.0,
        "c_hat_current": 0.0
      }
    }
  },
  {
    "frame": 13,
    "timestep": 16853,
    "time": 0.21666666666666665,
    "ee_pos_m": [
      -0.008020497858524323,
      0.07741313427686691,
      -0.0015417147660627961
    ],
    "ee_normal": [
      0.0,
      0.9999990463256836,
      0.0
    ],
    "knife": {
      "y_anim": 0.03363323584198952,
      "z_offset": 0.0009587852982804179
    },
    "relative_eef_force": 0.0,
    "force_world_N": {
      "x": 0.0,
      "y": 0.0,
      "z": 0.0,
      "norm": 9.999999974752427e-07
    },
    "force_normalized": {
      "x": 0.0,
      "y": 0.0,
      "z": 0.0
    },
    "scales": {
      "dx": 0.004166666883975267,
      "dt": 1.2857669036389097e-05,
      "E": 2819808.3930243584,
      "vcap_dx_over_dt": 324.0608287694283
    },
    "telemetry": {
      "material": {
        "E_Pa": 2819808.3930243584,
        "sigma_y_Pa": 237045.56369017874,
        "E_ref_Pa": 300000.0,
        "sigma_ref_Pa": 5000.0
      },
      "knife_resistance": {
        "k2_base_per_s": 0.0,
        "k2_eff_per_s": 0.0,
        "mat_gain": 145.34864907848944,
        "c_hat": 0.0,
        "c_hat_current": 0.0
      }
    }
  },
  {
    "frame": 14,
    "timestep": 18149,
    "time": 0.2333333333333333,
    "ee_pos_m": [
      -0.008020497858524323,
      0.07241491973400116,
      -0.0015417147660627961
    ],
    "ee_normal": [
      0.0,
      0.9999990463256836,
      0.0
    ],
    "knife": {
      "y_anim": 0.028635017573833466,
      "z_offset": 0.0009587852982804179
    },
    "relative_eef_force": 0.0,
    "force_world_N": {
      "x": 0.0,
      "y": 0.0,
      "z": 0.0,
      "norm": 9.999999974752427e-07
    },
    "force_normalized": {
      "x": 0.0,
      "y": 0.0,
      "z": 0.0
    },
    "scales": {
      "dx": 0.004166666883975267,
      "dt": 1.2857669036389097e-05,
      "E": 2819808.3930243584,
      "vcap_dx_over_dt": 324.0608287694283
    },
    "telemetry": {
      "material": {
        "E_Pa": 2819808.3930243584,
        "sigma_y_Pa": 237045.56369017874,
        "E_ref_Pa": 300000.0,
        "sigma_ref_Pa": 5000.0
      },
      "knife_resistance": {
        "k2_base_per_s": 0.0,
        "k2_eff_per_s": 0.0,
        "mat_gain": 145.34864907848944,
        "c_hat": 0.0,
        "c_hat_current": 0.0
      }
    }
  },
  {
    "frame": 15,
    "timestep": 19445,
    "time": 0.24999999999999997,
    "ee_pos_m": [
      -0.008020497858524323,
      0.06741555035114288,
      -0.0015417147660627961
    ],
    "ee_normal": [
      0.0,
      0.9999990463256836,
      0.0
    ],
    "knife": {
      "y_anim": 0.02363564819097519,
      "z_offset": 0.0009587852982804179
    },
    "relative_eef_force": 0.0,
    "force_world_N": {
      "x": 0.0,
      "y": 0.0,
      "z": 0.0,
      "norm": 9.999999974752427e-07
    },
    "force_normalized": {
      "x": 0.0,
      "y": 0.0,
      "z": 0.0
    },
    "scales": {
      "dx": 0.004166666883975267,
      "dt": 1.2857669036389097e-05,
      "E": 2819808.3930243584,
      "vcap_dx_over_dt": 324.0608287694283
    },
    "telemetry": {
      "material": {
        "E_Pa": 2819808.3930243584,
        "sigma_y_Pa": 237045.56369017874,
        "E_ref_Pa": 300000.0,
        "sigma_ref_Pa": 5000.0
      },
      "knife_resistance": {
        "k2_base_per_s": 0.0,
        "k2_eff_per_s": 0.0,
        "mat_gain": 145.34864907848944,
        "c_hat": 0.0,
        "c_hat_current": 0.0
      }
    }
  },
  {
    "frame": 16,
    "timestep": 20741,
    "time": 0.26666666666666666,
    "ee_pos_m": [
      -0.008020497858524323,
      0.06241617724299431,
      -0.0015417147660627961
    ],
    "ee_normal": [
      0.0,
      0.9999990463256836,
      0.0
    ],
    "knife": {
      "y_anim": 0.018636278808116913,
      "z_offset": 0.0009587852982804179
    },
    "relative_eef_force": 0.0,
    "force_world_N": {
      "x": 0.0,
      "y": 0.0,
      "z": 0.0,
      "norm": 9.999999974752427e-07
    },
    "force_normalized": {
      "x": 0.0,
      "y": 0.0,
      "z": 0.0
    },
    "scales": {
      "dx": 0.004166666883975267,
      "dt": 1.2857669036389097e-05,
      "E": 2819808.3930243584,
      "vcap_dx_over_dt": 324.0608287694283
    },
    "telemetry": {
      "material": {
        "E_Pa": 2819808.3930243584,
        "sigma_y_Pa": 237045.56369017874,
        "E_ref_Pa": 300000.0,
        "sigma_ref_Pa": 5000.0
      },
      "knife_resistance": {
        "k2_base_per_s": 0.0,
        "k2_eff_per_s": 0.0,
        "mat_gain": 145.34864907848944,
        "c_hat": 0.0,
        "c_hat_current": 0.0
      }
    }
  },
  {
    "frame": 17,
    "timestep": 22038,
    "time": 0.2833333333333333,
    "ee_pos_m": [
      -0.008020497858524323,
      0.057412952184677124,
      -0.0015417147660627961
    ],
    "ee_normal": [
      0.0,
      0.9999990463256836,
      0.0
    ],
    "knife": {
      "y_anim": 0.01363305188715458,
      "z_offset": 0.0009587852982804179
    },
    "relative_eef_force": 1.66496517136693,
    "force_world_N": {
      "x": -0.0004649161419365555,
      "y": -0.044612981379032135,
      "z": -0.023785216733813286,
      "norm": 0.05056057497859001
    },
    "force_normalized": {
      "x": -0.009195230901241302,
      "y": -0.882366955280304,
      "z": -0.4704301059246063
    },
    "scales": {
      "dx": 0.004166666883975267,
      "dt": 1.2857669036389097e-05,
      "E": 2819808.3930243584,
      "vcap_dx_over_dt": 324.0608287694283
    },
    "telemetry": {
      "material": {
        "E_Pa": 2819808.3930243584,
        "sigma_y_Pa": 237045.56369017874,
        "E_ref_Pa": 300000.0,
        "sigma_ref_Pa": 5000.0
      },
      "knife_resistance": {
        "k2_base_per_s": 0.0,
        "k2_eff_per_s": 0.0,
        "mat_gain": 145.34864907848944,
        "c_hat": 0.010699352249503136,
        "c_hat_current": 0.010702213572190358
      }
    }
  },
  {
    "frame": 18,
    "timestep": 23334,
    "time": 0.3,
    "ee_pos_m": [
      -0.008020497858524323,
      0.05241358280181885,
      -0.0015417147660627961
    ],
    "ee_normal": [
      0.0,
      0.9999990463256836,
      0.0
    ],
    "knife": {
      "y_anim": 0.008633682504296303,
      "z_offset": 0.0009587852982804179
    },
    "relative_eef_force": 29.496235847473145,
    "force_world_N": {
      "x": -0.008542180061340332,
      "y": -0.7346584796905518,
      "z": -0.4213747978210449,
      "norm": 0.8469678163528442
    },
    "force_normalized": {
      "x": -0.01008560135960579,
      "y": -0.8673983216285706,
      "z": -0.49750980734825134
    },
    "scales": {
      "dx": 0.004166666883975267,
      "dt": 1.2857669036389097e-05,
      "E": 2819808.3930243584,
      "vcap_dx_over_dt": 324.0608287694283
    },
    "telemetry": {
      "material": {
        "E_Pa": 2819808.3930243584,
        "sigma_y_Pa": 237045.56369017874,
        "E_ref_Pa": 300000.0,
        "sigma_ref_Pa": 5000.0
      },
      "knife_resistance": {
        "k2_base_per_s": 0.0,
        "k2_eff_per_s": 0.0,
        "mat_gain": 145.34864907848944,
        "c_hat": 0.02086768113076687,
        "c_hat_current": 0.02088438961668815
      }
    }
  },
  {
    "frame": 19,
    "timestep": 24630,
    "time": 0.31666666666666665,
    "ee_pos_m": [
      -0.008020497858524323,
      0.04741470143198967,
      -0.0015417147660627961
    ],
    "ee_normal": [
      0.0,
      0.9999990463256836,
      0.0
    ],
    "knife": {
      "y_anim": 0.0036348013672977686,
      "z_offset": 0.0009587852982804179
    },
    "relative_eef_force": 87.68671154975891,
    "force_world_N": {
      "x": -0.025927547365427017,
      "y": -2.1242775917053223,
      "z": -1.2526673078536987,
      "norm": 2.4662537574768066
    },
    "force_normalized": {
      "x": -0.010512927547097206,
      "y": -0.8613377809524536,
      "z": -0.5079231262207031
    },
    "scales": {
      "dx": 0.004166666883975267,
      "dt": 1.2857669036389097e-05,
      "E": 2819808.3930243584,
      "vcap_dx_over_dt": 324.0608287694283
    },
    "telemetry": {
      "material": {
        "E_Pa": 2819808.3930243584,
        "sigma_y_Pa": 237045.56369017874,
        "E_ref_Pa": 300000.0,
        "sigma_ref_Pa": 5000.0
      },
      "knife_resistance": {
        "k2_base_per_s": 0.0,
        "k2_eff_per_s": 0.0,
        "mat_gain": 145.34864907848944,
        "c_hat": 0.03010733798146248,
        "c_hat_current": 0.030067615346868817
      }
    }
  },
  {
    "frame": 20,
    "timestep": 25926,
    "time": 0.3333333333333333,
    "ee_pos_m": [
      -0.008020497858524323,
      0.04241563379764557,
      -0.0015417147660627961
    ],
    "ee_normal": [
      0.0,
      0.9999990463256836,
      0.0
    ],
    "knife": {
      "y_anim": -0.0013642659178003669,
      "z_offset": 0.0009587852982804179
    },
    "relative_eef_force": 148.64397287368774,
    "force_world_N": {
      "x": -0.030740760266780853,
      "y": -3.596853256225586,
      "z": -2.1234853267669678,
      "norm": 4.177020072937012
    },
    "force_normalized": {
      "x": -0.007359495386481285,
      "y": -0.8611050844192505,
      "z": -0.5083732604980469
    },
    "scales": {
      "dx": 0.004166666883975267,
      "dt": 1.2857669036389097e-05,
      "E": 2819808.3930243584,
      "vcap_dx_over_dt": 324.0608287694283
    },
    "telemetry": {
      "material": {
        "E_Pa": 2819808.3930243584,
        "sigma_y_Pa": 237045.56369017874,
        "E_ref_Pa": 300000.0,
        "sigma_ref_Pa": 5000.0
      },
      "knife_resistance": {
        "k2_base_per_s": 0.0,
        "k2_eff_per_s": 0.0,
        "mat_gain": 145.34864907848944,
        "c_hat": 0.03703689202666283,
        "c_hat_current": 0.03705857959129861
      }
    }
  },
  {
    "frame": 21,
    "timestep": 27223,
    "time": 0.35,
    "ee_pos_m": [
      -0.008020497858524323,
      0.0374128557741642,
      -0.0015417147660627961
    ],
    "ee_normal": [
      0.0,
      0.9999990463256836,
      0.0
    ],
    "knife": {
      "y_anim": -0.0063670421950519085,
      "z_offset": 0.0009587852982804179
    },
    "relative_eef_force": 254.32850122451782,
    "force_world_N": {
      "x": 0.1455598622560501,
      "y": -6.7725372314453125,
      "z": -3.6332643032073975,
      "norm": 7.686941623687744
    },
    "force_normalized": {
      "x": 0.01893599145114422,
      "y": -0.8810444474220276,
      "z": -0.4726540744304657
    },
    "scales": {
      "dx": 0.004166666883975267,
      "dt": 1.2857669036389097e-05,
      "E": 2819808.3930243584,
      "vcap_dx_over_dt": 324.0608287694283
    },
    "telemetry": {
      "material": {
        "E_Pa": 2819808.3930243584,
        "sigma_y_Pa": 237045.56369017874,
        "E_ref_Pa": 300000.0,
        "sigma_ref_Pa": 5000.0
      },
      "knife_resistance": {
        "k2_base_per_s": 0.0,
        "k2_eff_per_s": 0.0,
        "mat_gain": 145.34864907848944,
        "c_hat": 0.06084710732102394,
        "c_hat_current": 0.060972095210964625
      }
    }
  },
  {
    "frame": 22,
    "timestep": 28519,
    "time": 0.36666666666666664,
    "ee_pos_m": [
      -0.008020497858524323,
      0.03241366147994995,
      -0.0015417147660627961
    ],
    "ee_normal": [
      0.0,
      0.9999990463256836,
      0.0
    ],
    "knife": {
      "y_anim": -0.011366236954927444,
      "z_offset": 0.0009587852982804179
    },
    "relative_eef_force": 264.3083691596985,
    "force_world_N": {
      "x": 0.25945910811424255,
      "y": -7.4181809425354,
      "z": -3.77583384513855,
      "norm": 8.327884674072266
    },
    "force_normalized": {
      "x": 0.031155463308095932,
      "y": -0.8907641172409058,
      "z": -0.4533964991569519
    },
    "scales": {
      "dx": 0.004166666883975267,
      "dt": 1.2857669036389097e-05,
      "E": 2819808.3930243584,
      "vcap_dx_over_dt": 324.0608287694283
    },
    "telemetry": {
      "material": {
        "E_Pa": 2819808.3930243584,
        "sigma_y_Pa": 237045.56369017874,
        "E_ref_Pa": 300000.0,
        "sigma_ref_Pa": 5000.0
      },
      "knife_resistance": {
        "k2_base_per_s": 0.0,
        "k2_eff_per_s": 0.0,
        "mat_gain": 145.34864907848944,
        "c_hat": 0.0953439250588417,
        "c_hat_current": 0.07957191759513343
      }
    }
  },
  {
    "frame": 23,
    "timestep": 29815,
    "time": 0.3833333333333333,
    "ee_pos_m": [
      -0.008020497858524323,
      0.027414292097091675,
      -0.0015417147660627961
    ],
    "ee_normal": [
      0.0,
      0.9999990463256836,
      0.0
    ],
    "knife": {
      "y_anim": -0.01636560633778572,
      "z_offset": 0.0009587852982804179
    },
    "relative_eef_force": 379.2965316772461,
    "force_world_N": {
      "x": 1.0875136852264404,
      "y": -12.055163383483887,
      "z": -5.418521881103516,
      "norm": 13.261600494384766
    },
    "force_normalized": {
      "x": 0.08200471103191376,
      "y": -0.9090278148651123,
      "z": -0.40858733654022217
    },
    "scales": {
      "dx": 0.004166666883975267,
      "dt": 1.2857669036389097e-05,
      "E": 2819808.3930243584,
      "vcap_dx_over_dt": 324.0608287694283
    },
    "telemetry": {
      "material": {
        "E_Pa": 2819808.3930243584,
        "sigma_y_Pa": 237045.56369017874,
        "E_ref_Pa": 300000.0,
        "sigma_ref_Pa": 5000.0
      },
      "knife_resistance": {
        "k2_base_per_s": 0.0,
        "k2_eff_per_s": 0.0,
        "mat_gain": 145.34864907848944,
        "c_hat": 0.13069114089012146,
        "c_hat_current": 0.1773744471997339
      }
    }
  },
  {
    "frame": 24,
    "timestep": 31111,
    "time": 0.39999999999999997,
    "ee_pos_m": [
      -0.008020497858524323,
      0.0224149227142334,
      -0.0015417147660627961
    ],
    "ee_normal": [
      0.0,
      0.9999990463256836,
      0.0
    ],
    "knife": {
      "y_anim": -0.021364975720643997,
      "z_offset": 0.0009587852982804179
    },
    "relative_eef_force": 374.32872772216797,
    "force_world_N": {
      "x": 7.737942695617676,
      "y": -13.652429580688477,
      "z": -5.347553253173828,
      "norm": 16.57893180847168
    },
    "force_normalized": {
      "x": 0.46673348546028137,
      "y": -0.8234806656837463,
      "z": -0.3225511312484741
    },
    "scales": {
      "dx": 0.004166666883975267,
      "dt": 1.2857669036389097e-05,
      "E": 2819808.3930243584,
      "vcap_dx_over_dt": 324.0608287694283
    },
    "telemetry": {
      "material": {
        "E_Pa": 2819808.3930243584,
        "sigma_y_Pa": 237045.56369017874,
        "E_ref_Pa": 300000.0,
        "sigma_ref_Pa": 5000.0
      },
      "knife_resistance": {
        "k2_base_per_s": 0.0,
        "k2_eff_per_s": 0.0,
        "mat_gain": 145.34864907848944,
        "c_hat": 0.2801547944545746,
        "c_hat_current": 0.2705067583815939
      }
    }
  },
  {
    "frame": 25,
    "timestep": 32408,
    "time": 0.41666666666666663,
    "ee_pos_m": [
      -0.008020497858524323,
      0.017411695793271065,
      -0.0015417147660627961
    ],
    "ee_normal": [
      0.0,
      0.9999990463256836,
      0.0
    ],
    "knife": {
      "y_anim": -0.02636820264160633,
      "z_offset": 0.0009587852982804179
    },
    "relative_eef_force": 516.8415355682373,
    "force_world_N": {
      "x": -1.2512346506118774,
      "y": -24.15675926208496,
      "z": -7.383450508117676,
      "norm": 25.290908813476562
    },
    "force_normalized": {
      "x": -0.04947369173169136,
      "y": -0.9551558494567871,
      "z": -0.2919408977031708
    },
    "scales": {
      "dx": 0.004166666883975267,
      "dt": 1.2857669036389097e-05,
      "E": 2819808.3930243584,
      "vcap_dx_over_dt": 324.0608287694283
    },
    "telemetry": {
      "material": {
        "E_Pa": 2819808.3930243584,
        "sigma_y_Pa": 237045.56369017874,
        "E_ref_Pa": 300000.0,
        "sigma_ref_Pa": 5000.0
      },
      "knife_resistance": {
        "k2_base_per_s": 0.0,
        "k2_eff_per_s": 0.0,
        "mat_gain": 145.34864907848944,
        "c_hat": 0.33894819021224976,
        "c_hat_current": 0.4766109782794774
      }
    }
  },
  {
    "frame": 26,
    "timestep": 33704,
    "time": 0.4333333333333333,
    "ee_pos_m": [
      -0.008020497858524323,
      0.012412384152412415,
      -0.0015417147660627961
    ],
    "ee_normal": [
      0.0,
      0.9999990463256836,
      0.0
    ],
    "knife": {
      "y_anim": -0.03136751428246498,
      "z_offset": 0.0009587852982804179
    },
    "relative_eef_force": 350.4281806945801,
    "force_world_N": {
      "x": 0.8460773825645447,
      "y": -14.34566593170166,
      "z": -5.00611686706543,
      "norm": 15.217595100402832
    },
    "force_normalized": {
      "x": 0.055598627775907516,
      "y": -0.94270259141922,
      "z": -0.32896900177001953
    },
    "scales": {
      "dx": 0.004166666883975267,
      "dt": 1.2857669036389097e-05,
      "E": 2819808.3930243584,
      "vcap_dx_over_dt": 324.0608287694283
    },
    "telemetry": {
      "material": {
        "E_Pa": 2819808.3930243584,
        "sigma_y_Pa": 237045.56369017874,
        "E_ref_Pa": 300000.0,
        "sigma_ref_Pa": 5000.0
      },
      "knife_resistance": {
        "k2_base_per_s": 0.0,
        "k2_eff_per_s": 0.0,
        "mat_gain": 145.34864907848944,
        "c_hat": 0.3546724319458008,
        "c_hat_current": 0.4755387921249022
      }
    }
  },
  {
    "frame": 27,
    "timestep": 35000,
    "time": 0.44999999999999996,
    "ee_pos_m": [
      -0.008020497858524323,
      0.007816508412361145,
      -0.0015417147660627961
    ],
    "ee_normal": [
      0.0,
      0.9999990463256836,
      0.0
    ],
    "knife": {
      "y_anim": -0.03596339002251625,
      "z_offset": 0.0009587852982804179
    },
    "relative_eef_force": 549.8813772201538,
    "force_world_N": {
      "x": -5.180556297302246,
      "y": -16.72220230102539,
      "z": -7.855448246002197,
      "norm": 19.18797492980957
    },
    "force_normalized": {
      "x": -0.2699897289276123,
      "y": -0.8714938759803772,
      "z": -0.4093943238258362
    },
    "scales": {
      "dx": 0.004166666883975267,
      "dt": 1.2857669036389097e-05,
      "E": 2819808.3930243584,
      "vcap_dx_over_dt": 324.0608287694283
    },
    "telemetry": {
      "material": {
        "E_Pa": 2819808.3930243584,
        "sigma_y_Pa": 237045.56369017874,
        "E_ref_Pa": 300000.0,
        "sigma_ref_Pa": 5000.0
      },
      "knife_resistance": {
        "k2_base_per_s": 0.0,
        "k2_eff_per_s": 0.0,
        "mat_gain": 145.34864907848944,
        "c_hat": 0.07652430236339569,
        "c_hat_current": 0.07812738058522078
      }
    }
  },
  {
    "frame": 28,
    "timestep": 36296,
    "time": 0.4666666666666666,
    "ee_pos_m": [
      -0.008020497858524323,
      0.024479586631059647,
      -0.0015417147660627961
    ],
    "ee_normal": [
      0.0,
      0.9999990463256836,
      0.0
    ],
    "knife": {
      "y_anim": -0.01930031180381775,
      "z_offset": 0.0009587852982804179
    },
    "relative_eef_force": 34.87498253583908,
    "force_world_N": {
      "x": -0.3112424314022064,
      "y": -4.011561870574951,
      "z": -0.4982140362262726,
      "norm": 4.054346561431885
    },
    "force_normalized": {
      "x": -0.07676759362220764,
      "y": -0.9894471764564514,
      "z": -0.12288393080234528
    },
    "scales": {
      "dx": 0.004166666883975267,
      "dt": 1.2857669036389097e-05,
      "E": 2819808.3930243584,
      "vcap_dx_over_dt": 324.0608287694283
    },
    "telemetry": {
      "material": {
        "E_Pa": 2819808.3930243584,
        "sigma_y_Pa": 237045.56369017874,
        "E_ref_Pa": 300000.0,
        "sigma_ref_Pa": 5000.0
      },
      "knife_resistance": {
        "k2_base_per_s": 0.0,
        "k2_eff_per_s": 0.0,
        "mat_gain": 145.34864907848944,
        "c_hat": 1.0,
        "c_hat_current": 0.05835201365768542
      }
    }
  },
  {
    "frame": 29,
    "timestep": 37593,
    "time": 0.4833333333333333,
    "ee_pos_m": [
      -0.008020497858524323,
      0.04115618020296097,
      -0.0015417147660627961
    ],
    "ee_normal": [
      0.0,
      0.9999990463256836,
      0.0
    ],
    "knife": {
      "y_anim": -0.002623717300593853,
      "z_offset": 0.0009587852982804179
    },
    "relative_eef_force": 359.3472099304199,
    "force_world_N": {
      "x": -0.9358572959899902,
      "y": -14.021427154541016,
      "z": -5.13353157043457,
      "norm": 14.960929870605469
    },
    "force_normalized": {
      "x": -0.06255342066287994,
      "y": -0.9372029304504395,
      "z": -0.3431291878223419
    },
    "scales": {
      "dx": 0.004166666883975267,
      "dt": 1.2857669036389097e-05,
      "E": 2819808.3930243584,
      "vcap_dx_over_dt": 324.0608287694283
    },
    "telemetry": {
      "material": {
        "E_Pa": 2819808.3930243584,
        "sigma_y_Pa": 237045.56369017874,
        "E_ref_Pa": 300000.0,
        "sigma_ref_Pa": 5000.0
      },
      "knife_resistance": {
        "k2_base_per_s": 0.0,
        "k2_eff_per_s": 0.0,
        "mat_gain": 145.34864907848944,
        "c_hat": 0.004228869453072548,
        "c_hat_current": 0.004281778910331416
      }
    }
  },
  {
    "frame": 30,
    "timestep": 38889,
    "time": 0.49999999999999994,
    "ee_pos_m": [
      -0.008020497858524323,
      0.057819850742816925,
      -0.0015417147660627961
    ],
    "ee_normal": [
      0.0,
      0.9999990463256836,
      0.0
    ],
    "knife": {
      "y_anim": 0.01403995044529438,
      "z_offset": 0.0009587852982804179
    },
    "relative_eef_force": -0.042259268811903894,
    "force_world_N": {
      "x": -3.165300586260855e-05,
      "y": -0.0011694409186020494,
      "z": 0.0006037038401700556,
      "norm": 0.0013174543855711818
    },
    "force_normalized": {
      "x": -0.02402588352560997,
      "y": -0.8876519203186035,
      "z": 0.45823508501052856
    },
    "scales": {
      "dx": 0.004166666883975267,
      "dt": 1.2857669036389097e-05,
      "E": 2819808.3930243584,
      "vcap_dx_over_dt": 324.0608287694283
    },
    "telemetry": {
      "material": {
        "E_Pa": 2819808.3930243584,
        "sigma_y_Pa": 237045.56369017874,
        "E_ref_Pa": 300000.0,
        "sigma_ref_Pa": 5000.0
      },
      "knife_resistance": {
        "k2_base_per_s": 0.0,
        "k2_eff_per_s": 0.0,
        "mat_gain": 145.34864907848944,
        "c_hat": 0.0,
        "c_hat_current": 0.0
      }
    }
  },
  {
    "frame": 31,
    "timestep": 40185,
    "time": 0.5166666666666666,
    "ee_pos_m": [
      -0.008020497858524323,
      0.07448361068964005,
      -0.0015417147660627961
    ],
    "ee_normal": [
      0.0,
      0.9999990463256836,
      0.0
    ],
    "knife": {
      "y_anim": 0.0307037103921175,
      "z_offset": 0.0009587852982804179
    },
    "relative_eef_force": 0.0,
    "force_world_N": {
      "x": 0.0,
      "y": 0.0,
      "z": 0.0,
      "norm": 9.999999974752427e-07
    },
    "force_normalized": {
      "x": 0.0,
      "y": 0.0,
      "z": 0.0
    },
    "scales": {
      "dx": 0.004166666883975267,
      "dt": 1.2857669036389097e-05,
      "E": 2819808.3930243584,
      "vcap_dx_over_dt": 324.0608287694283
    },
    "telemetry": {
      "material": {
        "E_Pa": 2819808.3930243584,
        "sigma_y_Pa": 237045.56369017874,
        "E_ref_Pa": 300000.0,
        "sigma_ref_Pa": 5000.0
      },
      "knife_resistance": {
        "k2_base_per_s": 0.0,
        "k2_eff_per_s": 0.0,
        "mat_gain": 145.34864907848944,
        "c_hat": 0.0,
        "c_hat_current": 0.0
      }
    }
  },
  {
    "frame": 32,
    "timestep": 41481,
    "time": 0.5333333333333333,
    "ee_pos_m": [
      -0.008020497858524323,
      0.09114503860473633,
      -0.0015417147660627961
    ],
    "ee_normal": [
      0.0,
      0.9999990463256836,
      0.0
    ],
    "knife": {
      "y_anim": 0.047365136444568634,
      "z_offset": 0.0009587852982804179
    },
    "relative_eef_force": 0.0,
    "force_world_N": {
      "x": 0.0,
      "y": 0.0,
      "z": 0.0,
      "norm": 9.999999974752427e-07
    },
    "force_normalized": {
      "x": 0.0,
      "y": 0.0,
      "z": 0.0
    },
    "scales": {
      "dx": 0.004166666883975267,
      "dt": 1.2857669036389097e-05,
      "E": 2819808.3930243584,
      "vcap_dx_over_dt": 324.0608287694283
    },
    "telemetry": {
      "material": {
        "E_Pa": 2819808.3930243584,
        "sigma_y_Pa": 237045.56369017874,
        "E_ref_Pa": 300000.0,
        "sigma_ref_Pa": 5000.0
      },
      "knife_resistance": {
        "k2_base_per_s": 0.0,
        "k2_eff_per_s": 0.0,
        "mat_gain": 145.34864907848944,
        "c_hat": 0.0,
        "c_hat_current": 0.0
      }
    }
  },
  {
    "frame": 33,
    "timestep": 42778,
    "time": 0.55,
    "ee_pos_m": [
      -0.008020497858524323,
      0.10781968384981155,
      -0.0015417147660627961
    ],
    "ee_normal": [
      0.0,
      0.9999990463256836,
      0.0
    ],
    "knife": {
      "y_anim": 0.06403978168964386,
      "z_offset": 0.0009587852982804179
    },
    "relative_eef_force": 0.0,
    "force_world_N": {
      "x": 0.0,
      "y": 0.0,
      "z": 0.0,
      "norm": 9.999999974752427e-07
    },
    "force_normalized": {
      "x": 0.0,
      "y": 0.0,
      "z": 0.0
    },
    "scales": {
      "dx": 0.004166666883975267,
      "dt": 1.2857669036389097e-05,
      "E": 2819808.3930243584,
      "vcap_dx_over_dt": 324.0608287694283
    },
    "telemetry": {
      "material": {
        "E_Pa": 2819808.3930243584,
        "sigma_y_Pa": 237045.56369017874,
        "E_ref_Pa": 300000.0,
        "sigma_ref_Pa": 5000.0
      },
      "knife_resistance": {
        "k2_base_per_s": 0.0,
        "k2_eff_per_s": 0.0,
        "mat_gain": 145.34864907848944,
        "c_hat": 0.0,
        "c_hat_current": 0.0
      }
    }
  },
  {
    "frame": 34,
    "timestep": 44074,
    "time": 0.5666666666666668,
    "ee_pos_m": [
      -0.008020497858524323,
      0.12448585778474808,
      -0.0015417147660627961
    ],
    "ee_normal": [
      0.0,
      0.9999990463256836,
      0.0
    ],
    "knife": {
      "y_anim": 0.08070595562458038,
      "z_offset": 0.0009587852982804179
    },
    "relative_eef_force": 0.0,
    "force_world_N": {
      "x": 0.0,
      "y": 0.0,
      "z": 0.0,
      "norm": 9.999999974752427e-07
    },
    "force_normalized": {
      "x": 0.0,
      "y": 0.0,
      "z": 0.0
    },
    "scales": {
      "dx": 0.004166666883975267,
      "dt": 1.2857669036389097e-05,
      "E": 2819808.3930243584,
      "vcap_dx_over_dt": 324.0608287694283
    },
    "telemetry": {
      "material": {
        "E_Pa": 2819808.3930243584,
        "sigma_y_Pa": 237045.56369017874,
        "E_ref_Pa": 300000.0,
        "sigma_ref_Pa": 5000.0
      },
      "knife_resistance": {
        "k2_base_per_s": 0.0,
        "k2_eff_per_s": 0.0,
        "mat_gain": 145.34864907848944,
        "c_hat": 0.0,
        "c_hat_current": 0.0
      }
    }
  },
  {
    "frame": 35,
    "timestep": 45370,
    "time": 0.5833333333333335,
    "ee_pos_m": [
      -0.008020497858524323,
      0.141152024269104,
      -0.0015417147660627961
    ],
    "ee_normal": [
      0.0,
      0.9999990463256836,
      0.0
    ],
    "knife": {
      "y_anim": 0.0973721295595169,
      "z_offset": 0.0009587852982804179
    },
    "relative_eef_force": 0.0,
    "force_world_N": {
      "x": 0.0,
      "y": 0.0,
      "z": 0.0,
      "norm": 9.999999974752427e-07
    },
    "force_normalized": {
      "x": 0.0,
      "y": 0.0,
      "z": 0.0
    },
    "scales": {
      "dx": 0.004166666883975267,
      "dt": 1.2857669036389097e-05,
      "E": 2819808.3930243584,
      "vcap_dx_over_dt": 324.0608287694283
    },
    "telemetry": {
      "material": {
        "E_Pa": 2819808.3930243584,
        "sigma_y_Pa": 237045.56369017874,
        "E_ref_Pa": 300000.0,
        "sigma_ref_Pa": 5000.0
      },
      "knife_resistance": {
        "k2_base_per_s": 0.0,
        "k2_eff_per_s": 0.0,
        "mat_gain": 145.34864907848944,
        "c_hat": 0.0,
        "c_hat_current": 0.0
      }
    }
  },
  {
    "frame": 36,
    "timestep": 46666,
    "time": 0.6000000000000002,
    "ee_pos_m": [
      -0.008020497858524323,
      0.13781188428401947,
      -0.0015417147660627961
    ],
    "ee_normal": [
      0.0,
      0.9999990463256836,
      0.0
    ],
    "knife": {
      "y_anim": 0.09403198212385178,
      "z_offset": 0.0009587852982804179
    },
    "relative_eef_force": 0.0,
    "force_world_N": {
      "x": 0.0,
      "y": 0.0,
      "z": 0.0,
      "norm": 9.999999974752427e-07
    },
    "force_normalized": {
      "x": 0.0,
      "y": 0.0,
      "z": 0.0
    },
    "scales": {
      "dx": 0.004166666883975267,
      "dt": 1.2857669036389097e-05,
      "E": 2819808.3930243584,
      "vcap_dx_over_dt": 324.0608287694283
    },
    "telemetry": {
      "material": {
        "E_Pa": 2819808.3930243584,
        "sigma_y_Pa": 237045.56369017874,
        "E_ref_Pa": 300000.0,
        "sigma_ref_Pa": 5000.0
      },
      "knife_resistance": {
        "k2_base_per_s": 0.0,
        "k2_eff_per_s": 0.0,
        "mat_gain": 145.34864907848944,
        "c_hat": 0.0,
        "c_hat_current": 0.0
      }
    }
  },
  {
    "frame": 37,
    "timestep": 47963,
    "time": 0.6166666666666669,
    "ee_pos_m": [
      -0.008020497858524323,
      0.13280624151229858,
      -0.0015417147660627961
    ],
    "ee_normal": [
      0.0,
      0.9999990463256836,
      0.0
    ],
    "knife": {
      "y_anim": 0.08902633935213089,
      "z_offset": 0.0009587852982804179
    },
    "relative_eef_force": 0.0,
    "force_world_N": {
      "x": 0.0,
      "y": 0.0,
      "z": 0.0,
      "norm": 9.999999974752427e-07
    },
    "force_normalized": {
      "x": 0.0,
      "y": 0.0,
      "z": 0.0
    },
    "scales": {
      "dx": 0.004166666883975267,
      "dt": 1.2857669036389097e-05,
      "E": 2819808.3930243584,
      "vcap_dx_over_dt": 324.0608287694283
    },
    "telemetry": {
      "material": {
        "E_Pa": 2819808.3930243584,
        "sigma_y_Pa": 237045.56369017874,
        "E_ref_Pa": 300000.0,
        "sigma_ref_Pa": 5000.0
      },
      "knife_resistance": {
        "k2_base_per_s": 0.0,
        "k2_eff_per_s": 0.0,
        "mat_gain": 145.34864907848944,
        "c_hat": 0.0,
        "c_hat_current": 0.0
      }
    }
  },
  {
    "frame": 38,
    "timestep": 49259,
    "time": 0.6333333333333336,
    "ee_pos_m": [
      -0.008020497858524323,
      0.1278044581413269,
      -0.0015417147660627961
    ],
    "ee_normal": [
      0.0,
      0.9999990463256836,
      0.0
    ],
    "knife": {
      "y_anim": 0.08402455598115921,
      "z_offset": 0.0009587852982804179
    },
    "relative_eef_force": 0.0,
    "force_world_N": {
      "x": 0.0,
      "y": 0.0,
      "z": 0.0,
      "norm": 9.999999974752427e-07
    },
    "force_normalized": {
      "x": 0.0,
      "y": 0.0,
      "z": 0.0
    },
    "scales": {
      "dx": 0.004166666883975267,
      "dt": 1.2857669036389097e-05,
      "E": 2819808.3930243584,
      "vcap_dx_over_dt": 324.0608287694283
    },
    "telemetry": {
      "material": {
        "E_Pa": 2819808.3930243584,
        "sigma_y_Pa": 237045.56369017874,
        "E_ref_Pa": 300000.0,
        "sigma_ref_Pa": 5000.0
      },
      "knife_resistance": {
        "k2_base_per_s": 0.0,
        "k2_eff_per_s": 0.0,
        "mat_gain": 145.34864907848944,
        "c_hat": 0.0,
        "c_hat_current": 0.0
      }
    }
  },
  {
    "frame": 39,
    "timestep": 50555,
    "time": 0.6500000000000004,
    "ee_pos_m": [
      -0.008020497858524323,
      0.12280267477035522,
      -0.0015417147660627961
    ],
    "ee_normal": [
      0.0,
      0.9999990463256836,
      0.0
    ],
    "knife": {
      "y_anim": 0.07902277261018753,
      "z_offset": 0.0009587852982804179
    },
    "relative_eef_force": 0.0,
    "force_world_N": {
      "x": 0.0,
      "y": 0.0,
      "z": 0.0,
      "norm": 9.999999974752427e-07
    },
    "force_normalized": {
      "x": 0.0,
      "y": 0.0,
      "z": 0.0
    },
    "scales": {
      "dx": 0.004166666883975267,
      "dt": 1.2857669036389097e-05,
      "E": 2819808.3930243584,
      "vcap_dx_over_dt": 324.0608287694283
    },
    "telemetry": {
      "material": {
        "E_Pa": 2819808.3930243584,
        "sigma_y_Pa": 237045.56369017874,
        "E_ref_Pa": 300000.0,
        "sigma_ref_Pa": 5000.0
      },
      "knife_resistance": {
        "k2_base_per_s": 0.0,
        "k2_eff_per_s": 0.0,
        "mat_gain": 145.34864907848944,
        "c_hat": 0.0,
        "c_hat_current": 0.0
      }
    }
  },
  {
    "frame": 40,
    "timestep": 51851,
    "time": 0.6666666666666671,
    "ee_pos_m": [
      -0.008020497858524323,
      0.11780089139938354,
      -0.0015417147660627961
    ],
    "ee_normal": [
      0.0,
      0.9999990463256836,
      0.0
    ],
    "knife": {
      "y_anim": 0.07402098923921585,
      "z_offset": 0.0009587852982804179
    },
    "relative_eef_force": 0.0,
    "force_world_N": {
      "x": 0.0,
      "y": 0.0,
      "z": 0.0,
      "norm": 9.999999974752427e-07
    },
    "force_normalized": {
      "x": 0.0,
      "y": 0.0,
      "z": 0.0
    },
    "scales": {
      "dx": 0.004166666883975267,
      "dt": 1.2857669036389097e-05,
      "E": 2819808.3930243584,
      "vcap_dx_over_dt": 324.0608287694283
    },
    "telemetry": {
      "material": {
        "E_Pa": 2819808.3930243584,
        "sigma_y_Pa": 237045.56369017874,
        "E_ref_Pa": 300000.0,
        "sigma_ref_Pa": 5000.0
      },
      "knife_resistance": {
        "k2_base_per_s": 0.0,
        "k2_eff_per_s": 0.0,
        "mat_gain": 145.34864907848944,
        "c_hat": 0.0,
        "c_hat_current": 0.0
      }
    }
  },
  {
    "frame": 41,
    "timestep": 53147,
    "time": 0.6833333333333338,
    "ee_pos_m": [
      -0.008020497858524323,
      0.11279910802841187,
      -0.0015417147660627961
    ],
    "ee_normal": [
      0.0,
      0.9999990463256836,
      0.0
    ],
    "knife": {
      "y_anim": 0.06901920586824417,
      "z_offset": 0.0009587852982804179
    },
    "relative_eef_force": 0.0,
    "force_world_N": {
      "x": 0.0,
      "y": 0.0,
      "z": 0.0,
      "norm": 9.999999974752427e-07
    },
    "force_normalized": {
      "x": 0.0,
      "y": 0.0,
      "z": 0.0
    },
    "scales": {
      "dx": 0.004166666883975267,
      "dt": 1.2857669036389097e-05,
      "E": 2819808.3930243584,
      "vcap_dx_over_dt": 324.0608287694283
    },
    "telemetry": {
      "material": {
        "E_Pa": 2819808.3930243584,
        "sigma_y_Pa": 237045.56369017874,
        "E_ref_Pa": 300000.0,
        "sigma_ref_Pa": 5000.0
      },
      "knife_resistance": {
        "k2_base_per_s": 0.0,
        "k2_eff_per_s": 0.0,
        "mat_gain": 145.34864907848944,
        "c_hat": 0.0,
        "c_hat_current": 0.0
      }
    }
  },
  {
    "frame": 42,
    "timestep": 54444,
    "time": 0.7000000000000005,
    "ee_pos_m": [
      -0.008020497858524323,
      0.10779346525669098,
      -0.0015417147660627961
    ],
    "ee_normal": [
      0.0,
      0.9999990463256836,
      0.0
    ],
    "knife": {
      "y_anim": 0.06401356309652328,
      "z_offset": 0.0009587852982804179
    },
    "relative_eef_force": 0.0,
    "force_world_N": {
      "x": 0.0,
      "y": 0.0,
      "z": 0.0,
      "norm": 9.999999974752427e-07
    },
    "force_normalized": {
      "x": 0.0,
      "y": 0.0,
      "z": 0.0
    },
    "scales": {
      "dx": 0.004166666883975267,
      "dt": 1.2857669036389097e-05,
      "E": 2819808.3930243584,
      "vcap_dx_over_dt": 324.0608287694283
    },
    "telemetry": {
      "material": {
        "E_Pa": 2819808.3930243584,
        "sigma_y_Pa": 237045.56369017874,
        "E_ref_Pa": 300000.0,
        "sigma_ref_Pa": 5000.0
      },
      "knife_resistance": {
        "k2_base_per_s": 0.0,
        "k2_eff_per_s": 0.0,
        "mat_gain": 145.34864907848944,
        "c_hat": 0.0,
        "c_hat_current": 0.0
      }
    }
  },
  {
    "frame": 43,
    "timestep": 55740,
    "time": 0.7166666666666672,
    "ee_pos_m": [
      -0.008020497858524323,
      0.10279504954814911,
      -0.0015417147660627961
    ],
    "ee_normal": [
      0.0,
      0.9999990463256836,
      0.0
    ],
    "knife": {
      "y_anim": 0.059015147387981415,
      "z_offset": 0.0009587852982804179
    },
    "relative_eef_force": -0.0017763856340025086,
    "force_world_N": {
      "x": -1.05189137684647e-05,
      "y": -5.832848182762973e-05,
      "z": 2.5376937628607266e-05,
      "norm": 6.547362136188895e-05
    },
    "force_normalized": {
      "x": -0.1606588065624237,
      "y": -0.8908699750900269,
      "z": 0.3875902593135834
    },
    "scales": {
      "dx": 0.004166666883975267,
      "dt": 1.2857669036389097e-05,
      "E": 2819808.3930243584,
      "vcap_dx_over_dt": 324.0608287694283
    },
    "telemetry": {
      "material": {
        "E_Pa": 2819808.3930243584,
        "sigma_y_Pa": 237045.56369017874,
        "E_ref_Pa": 300000.0,
        "sigma_ref_Pa": 5000.0
      },
      "knife_resistance": {
        "k2_base_per_s": 0.0,
        "k2_eff_per_s": 0.0,
        "mat_gain": 145.34864907848944,
        "c_hat": 0.0,
        "c_hat_current": 0.0
      }
    }
  },
  {
    "frame": 44,
    "timestep": 57036,
    "time": 0.733333333333334,
    "ee_pos_m": [
      -0.008020497858524323,
      0.09779809415340424,
      -0.0015417147660627961
    ],
    "ee_normal": [
      0.0,
      0.9999990463256836,
      0.0
    ],
    "knife": {
      "y_anim": 0.05401819199323654,
      "z_offset": 0.0009587852982804179
    },
    "relative_eef_force": 0.0,
    "force_world_N": {
      "x": 0.0,
      "y": 0.0,
      "z": 0.0,
      "norm": 9.999999974752427e-07
    },
    "force_normalized": {
      "x": 0.0,
      "y": 0.0,
      "z": 0.0
    },
    "scales": {
      "dx": 0.004166666883975267,
      "dt": 1.2857669036389097e-05,
      "E": 2819808.3930243584,
      "vcap_dx_over_dt": 324.0608287694283
    },
    "telemetry": {
      "material": {
        "E_Pa": 2819808.3930243584,
        "sigma_y_Pa": 237045.56369017874,
        "E_ref_Pa": 300000.0,
        "sigma_ref_Pa": 5000.0
      },
      "knife_resistance": {
        "k2_base_per_s": 0.0,
        "k2_eff_per_s": 0.0,
        "mat_gain": 145.34864907848944,
        "c_hat": 0.0,
        "c_hat_current": 0.0
      }
    }
  },
  {
    "frame": 45,
    "timestep": 58332,
    "time": 0.7500000000000007,
    "ee_pos_m": [
      -0.008020497858524323,
      0.09280113875865936,
      -0.0015417147660627961
    ],
    "ee_normal": [
      0.0,
      0.9999990463256836,
      0.0
    ],
    "knife": {
      "y_anim": 0.04902123659849167,
      "z_offset": 0.0009587852982804179
    },
    "relative_eef_force": 0.0,
    "force_world_N": {
      "x": 0.0,
      "y": 0.0,
      "z": 0.0,
      "norm": 9.999999974752427e-07
    },
    "force_normalized": {
      "x": 0.0,
      "y": 0.0,
      "z": 0.0
    },
    "scales": {
      "dx": 0.004166666883975267,
      "dt": 1.2857669036389097e-05,
      "E": 2819808.3930243584,
      "vcap_dx_over_dt": 324.0608287694283
    },
    "telemetry": {
      "material": {
        "E_Pa": 2819808.3930243584,
        "sigma_y_Pa": 237045.56369017874,
        "E_ref_Pa": 300000.0,
        "sigma_ref_Pa": 5000.0
      },
      "knife_resistance": {
        "k2_base_per_s": 0.0,
        "k2_eff_per_s": 0.0,
        "mat_gain": 145.34864907848944,
        "c_hat": 0.0,
        "c_hat_current": 0.0
      }
    }
  },
  {
    "frame": 46,
    "timestep": 59629,
    "time": 0.7666666666666674,
    "ee_pos_m": [
      -0.008020497858524323,
      0.08780032396316528,
      -0.0015417147660627961
    ],
    "ee_normal": [
      0.0,
      0.9999990463256836,
      0.0
    ],
    "knife": {
      "y_anim": 0.04402042552828789,
      "z_offset": 0.0009587852982804179
    },
    "relative_eef_force": 0.0,
    "force_world_N": {
      "x": 0.0,
      "y": 0.0,
      "z": 0.0,
      "norm": 9.999999974752427e-07
    },
    "force_normalized": {
      "x": 0.0,
      "y": 0.0,
      "z": 0.0
    },
    "scales": {
      "dx": 0.004166666883975267,
      "dt": 1.2857669036389097e-05,
      "E": 2819808.3930243584,
      "vcap_dx_over_dt": 324.0608287694283
    },
    "telemetry": {
      "material": {
        "E_Pa": 2819808.3930243584,
        "sigma_y_Pa": 237045.56369017874,
        "E_ref_Pa": 300000.0,
        "sigma_ref_Pa": 5000.0
      },
      "knife_resistance": {
        "k2_base_per_s": 0.0,
        "k2_eff_per_s": 0.0,
        "mat_gain": 145.34864907848944,
        "c_hat": 0.0,
        "c_hat_current": 0.0
      }
    }
  }
]